Workbook
Name Base_Cost_180deg_Belt_Curve: #REF!
Name Base_Cost_180deg_Belt_Curve: #REF!
Name Base_Cost_180deg_Roller_Curve: #REF!
Name Base_Cost_180deg_Roller_Curve: #REF!
Name Base_Cost_30deg_Belt_Curve: #REF!
Name Base_Cost_30deg_Belt_Curve: #REF!
Name Base_Cost_30deg_Roller_Curve: #REF!
Name Base_Cost_30deg_Roller_Curve: #REF!
Name Base_Cost_45deg_Belt_Curve: #REF!
Name Base_Cost_45deg_Belt_Curve: #REF!
Name Base_Cost_45deg_Roller_Curve: #REF!
Name Base_Cost_45deg_Roller_Curve: #REF!
Name Base_Cost_60deg_Belt_Merge: #REF!
Name Base_Cost_60deg_Belt_Merge: #REF!
Name Base_Cost_60deg_Roller_Curve: #REF!
Name Base_Cost_60deg_Roller_Curve: #REF!
Name Base_Cost_90deg_Belt_Merge: #REF!
Name Base_Cost_90deg_Belt_Merge: #REF!
Name Base_Cost_90deg_Roller_Curve: #REF!
Name Base_Cost_90deg_Roller_Curve: #REF!
Name Base_Cost_Accumulation_Roller: #REF!
Name Base_Cost_Accumulation_Roller: #REF!
Name Base_Cost_Belt_Decline: #REF!
Name Base_Cost_Belt_Decline: #REF!
Name Base_Cost_Belt_Incline: #REF!
Name Base_Cost_Belt_Incline: #REF!
Name Base_Cost_Belt_Merge: #REF!
Name Base_Cost_Belt_Merge: #REF!
Name Base_Cost_Belt_Transport: #REF!
Name Base_Cost_Belt_Transport: #REF!
Name Base_Cost_Belt_Under_Roller: #REF!
Name Base_Cost_Belt_Under_Roller: #REF!
Name Base_Cost_Gravity_Roller: #REF!
Name Base_Cost_Gravity_Roller: #REF!
Name Base_Cost_Gravity_Spur: #REF!
Name Base_Cost_Gravity_Spur: #REF!
Name Base_Cost_Lineshaft_Roller: #REF!
Name Base_Cost_Lineshaft_Roller: #REF!
Name Base_Cost_Metering_Belt: #REF!
Name Base_Cost_Metering_Belt: #REF!
Name Base_Cost_Photo_Eyes: #REF!
Name Base_Cost_Photo_Eyes: #REF!
Name Base_Cost_Power_Feeder: #REF!
Name Base_Cost_Power_Feeder: #REF!
Name Base_Cost_Powered_Roller_Spur: #REF!
Name Base_Cost_Powered_Roller_Spur: #REF!
Name Belt_Width: #REF!
Name Belt_Width: #REF!
Name BeltCost: #REF!
Name BeltCost: #REF!
Name BeltType: '[1]Main Page'!$J$3
Name BodyHeight: #REF!
Name BodyHeight: #REF!
Name BodySection: '[1]Main Page'!$D$3
Name BTP10Price: [2]Sheet4!$G$115
Name BTP11Price: [2]Sheet4!$G$125
Name BTP1Price: [2]Sheet4!$G$21
Name BTP2Price: [2]Sheet4!$G$33
Name BTP3Price: [2]Sheet4!$G$43
Name BTP4Price: [2]Sheet4!$G$53

Sheet Final 
A1: S. No | B1: Component | C1: Qty per set | D1: Set | E1: UOM | G1: Price
A2: 1 | B2: CBS, Induct & Scanning Package | C2: 1 | D2: 1 | E2: Set | F2: € | G2: ='Overall Costing'!J2 -> 1311723.2 | L2: Preventive Maintenance for 2 days | M2: =4*500 -> 2000
A3: 2 | B3: Infeed Conveyors & VDS Package | C3: 1 | D3: 1 | E3: Set | F3: € | G3: ='Overall Costing'!J3+'Overall Costing'!J4 -> 842200.81 | L3: PM for 1 Year (1 in each month) | M3: =M2*12 -> 24000
A4: 3 | B4: Chute Package | C4: 1 | D4: 1 | E4: Set | F4: € | G4: ='Overall Costing'!J5 -> 400836.41 | L4: Breakdown Visit 12 Nos | M4: =12*1000 -> 12000
A5: 4 | B5: Mezannine Package | C5: 1 | D5: 1 | E5: Set | F5: € | G5: ='Overall Costing'!J6 -> 629102.13 | M5: =SUM(M3:M4) -> 36000
A6: 4 | B6: Software Packages | C6: 1 | D6: 1 | E6: Set | F6: € | G6: ='Overall Costing'!J8 -> 15957.447
A7: 5 | B7: Installation & Commissioning | C7: 1 | D7: 1 | E7: Set | F7: € | G7: ='Overall Costing'!J9+'Overall Costing'!J12+'Overall Costing'!J14 -> 604556.17
A8: 6 | B8: Packaging & Documentation | C8: 1 | D8: 1 | E8: Set | F8: € | G8: ='Overall Costing'!J10 -> 159193.13
A9: 7 | B9: Project Management and Engineering Charges | C9: 1 | D9: 1 | E9: Set | F9: € | G9: ='Overall Costing'!J11 -> 98078.468
A10: 8 | B10: Freight | C10: 1 | D10: 1 | E10: Set | F10: € | G10: ='Overall Costing'!J13 -> 204545.45
A11: 9 | B11: Spare Kit as per Inpost List | C11: 1 | D11: 1 | E11: Set | F11: € | G11: ='Overall Costing'!J15 -> 63869.011
A12: 10 | B12: Protection on Ground | C12: 1 | D12: 1 | E12: Set | F12: € | G12: ='Overall Costing'!J16 -> 15957.447 | H12: =SUM(G2:G12) -> 4346019.7
A13: Total Package for 1 Sorter per Piece | F13: € | G13: =SUM(G2:G12) -> 4346019.7
A14: Total Package for 2 Sorters per piece | F14: € | G14: ='[5]Final '!$G$13 -> 3548906.5
A15: Total Package for 3 Sorters per piece | F15: € | G15: ='[6]Final '!$G$13 -> 3507251.9
A16: 11 | B16: Recommended Spare Package by Falcon | C16: 1 | D16: 1 | E16: Set | F16: € | G16: ='Overall Costing'!J19 -> 204380.84
A17: 12 | B17: Hotline Support | C17: 1 | D17: 1 | E17: Set | F17: € | G17: 45000
A18: 13 | B18: Warranty Inspection | C18: 1 | D18: 1 | E18: Set | F18: € | G18: 36000

Sheet Inpost Sheet
A1: S. No | B1: Component | C1: Qty per set | D1: Set | E1: UOM | F1: Price
A2: 1 | B2: CBS & Scanning | C2: 1 | D2: 1 | E2: Set | F2: ='Loop CBS'!D70+'Loop CBS'!D132-F7-F8 -> 855583.84
A3: =A2+1 -> 2 | B3: Outbound Manual Chutes | C3: 1 | D3: 1 | E3: Set | F3: =Destinations!F26 -> 320051.31
A4: =A3+1 -> 3 | B4: Inbound Manual Lines | C4: 1 | D4: 1 | E4: Set | F4: =Conveyors!N75+'Overall Costing'!J3 -> 283929.23
A5: =A4+1 -> 4 | B5: Inbound Reject Lines | C5: 1 | D5: 1 | E5: Set | F5: =Conveyors!N76 -> 113652.84
A6: =A5+1 -> 5 | B6: Sorter Induct Line | C6: 1 | D6: 1 | E6: Set | F6: ='Loop CBS'!D130 -> 240378.93
A7: =A6+1 -> 6 | B7: Dimesnion Checking System | F7: ='Loop CBS'!D56 -> 32939.322
A8: =A7+1 -> 7 | B8: Scanning Gate | F8: ='Loop CBS'!D51 -> 182821.12
A9: =A8+1 -> 8 | B9: Maintenance Platform | C9: 1 | D9: 1 | E9: Set | F9: =Steelworks!H10 -> 629102.13
A10: =A9+1 -> 9 | B10: Protection on the ground of sorter | C10: 1 | D10: 1 | E10: Set | F10: ='Overall Costing'!J16 -> 15957.447 | J10: 45855
A11: =A10+1 -> 10 | B11: Project management | C11: 1 | D11: 1 | E11: Set | F11: ='Overall Costing'!J11 -> 98078.468 | J11: 46120
A12: =A11+1 -> 11 | B12: mechanical installation | C12: 1 | D12: 1 | E12: Set | F12: ='I&C Cost'!D2 -> 343752.13
A13: =A12+1 -> 12 | B13: electrical installation | C13: 1 | D13: 1 | E13: Set | F13: ='I&C Cost'!D3 -> 113026.91 | J13: =J11-J10 -> 265
A14: =A13+1 -> 13 | B14: commisioning | C14: 1 | D14: 1 | E14: Set | F14: ='I&C Cost'!D4 -> 30919.149 | J14: =J13/30 -> 8.8333333
A15: =A14+1 -> 14 | B15: I.T. software implementation | C15: 1 | D15: 1 | E15: Set | F15: ='I&C Cost'!D5+'Overall Costing'!J8 -> 30981.383
A16: =A15+1 -> 15 | B16: Acceptance Test | C16: 1 | D16: 1 | E16: Set | F16: ='Overall Costing'!J12 -> 44636.17
A17: =A16+1 -> 16 | B17: Support Ramp Up | C17: 1 | D17: 1 | E17: Set | F17: ='Overall Costing'!J14 -> 12197.872
A18: =A17+1 -> 17 | B18: Transport & Packaging | C18: 1 | D18: 1 | E18: Set | F18: ='Overall Costing'!J10+'Overall Costing'!J13 -> 363738.58
A19: =A18+1 -> 18 | B19: Field Wiring | C19: 1 | D19: 1 | E19: Set | F19: =Conveyors!N77 -> 97325.737
A20: =A19+1 -> 19 | B20: Chute Accessories | C20: 1 | D20: 1 | E20: Set | F20: =Destinations!F27 -> 80785.106
A21: =A20+1 -> 20 | B21: Spare Kit | C21: 1 | D21: 1 | E21: Set | F21: ='Overall Costing'!J15 -> 63869.011 | G21: =F21*92 -> 5875949
A22: =A21+1 -> 21 | B22: Others (MHE,Waste Management,) | C22: 1 | D22: 1 | E22: Set | F22: ='I&C Cost'!D6+'I&C Cost'!D7+'I&C Cost'!D8 -> 45000
A23: Total System Package | F23: =SUM(F2:F22) -> 3998726.7 | G23: =F23-'Overall Costing'!J17 -> -363696.48
A24: Warranty Inspection | F24: ='Final '!G18 -> 36000
A25: Hotline Support | F25: 45000
A26: Recommended Spare Package | F26: ='Overall Costing'!J19 -> 204380.84

Sheet Support Rampup
A1: B. FALCON HO TEAM
A2: Charges
A3: Person | B3: NO. OF MANPOWER REQUIRED | C3: No. of working days required | D3: AIR FARE | E3: VISA | F3: HOTEL | G3: MAN DAY COST | H3: DAILY ALLOWANCE
A4: Site Manager | B4: 1 | C4: 12 | D4: 90000 | E4: 25000 | F4: 9000 | G4: 9000 | H4: 9000
A5: Mechanical Engineer | B5: 0 | C5: 0 | D5: =D4 -> 90000 | E5: =E4 -> 25000 | F5: =F4 -> 9000 | G5: 6000 | H5: =H4 -> 9000
A6: Electrical Engineer | B6: 1 | C6: 12 | D6: =D5 -> 90000 | E6: =E5 -> 25000 | F6: =F5 -> 9000 | G6: 6000 | H6: =H5 -> 9000
A7: PLC | B7: 1 | C7: 12 | D7: =D6 -> 90000 | E7: =E6 -> 25000 | F7: =F6 -> 9000 | G7: 9000 | H7: =H6 -> 9000
A8: PLC Engineer | B8: 1 | C8: 0 | D8: =D7 -> 90000 | E8: =E7 -> 25000 | F8: =F7 -> 9000 | G8: 9000 | H8: =H7 -> 9000
A9: IT Engineer | B9: 1 | C9: 0 | D9: =D7 -> 90000 | E9: =E7 -> 25000 | F9: =F7 -> 9000 | G9: 12000 | H9: =H7 -> 9000
A11: Cost Calculation
A13: FALCON SUPERVISORS REQUIRED | B13: Total NO. OF DAYS REQUIRED | C13: AIR FARE | D13: VISA | E13: HOTEL | F13: MAN DAY COST | G13: DAILY ALLOWANCE
A14: Project Supervisor | B14: =ROUNDUP(C4*7/6,0) -> 14 | C14: =B4*D4 -> 90000 | D14: =B4*E4 -> 25000 | E14: =B4*(B14)*F4 -> 126000 | F14: =B4*B14*G4 -> 126000 | G14: =B4*(B14)*H4 -> 126000
A15: Mechanical Supervisor | B15: =ROUNDUP(C5*7/6,0) -> 0 | C15: =B5*D5 -> 0 | D15: =B5*E5 -> 0 | E15: =B5*(B15)*F5 -> 0 | F15: =B5*B15*G5 -> 0 | G15: =B5*(B15)*H5 -> 0 | H15: =ROUNDUP(#REF!/(8*6),0) -> #REF!
A16: Electrical Supervisor | B16: =ROUNDUP(C6*7/6,0) -> 14 | C16: =B6*D6 -> 90000 | D16: =B6*E6 -> 25000 | E16: =B6*(B16)*F6 -> 126000 | F16: =B6*B16*G6 -> 84000 | G16: =B6*(B16)*H6 -> 126000
A17: PLC Programmer | B17: =ROUNDUP(C7*7/6,0) -> 14 | C17: =B7*D7 -> 90000 | D17: =B7*E7 -> 25000 | E17: =B7*((B17))*F7 -> 126000 | F17: =B7*B17*G7 -> 126000 | G17: =B7*(B17)*H7 -> 126000
A18: IT Engineer | B18: =ROUNDUP(C8*7/6,0) -> 0 | C18: =B8*D8 -> 90000 | D18: =B8*E8 -> 25000 | E18: =B8*((B18))*F8 -> 0 | F18: =B8*B18*G8 -> 0 | G18: =B8*(B18)*H8 -> 0
A19: IT Engineer | B19: =ROUNDUP(C9*7/6,0) -> 0 | C19: =B9*D9 -> 90000 | D19: =B9*E9 -> 25000 | E19: =B9*(B19)*F9 -> 0 | F19: =B9*B19*G9 -> 0 | G19: =B9*(B19)*H9 -> 0
B20: Total Cost (INR) | C20: 0 | D20: 0 | E20: =SUM(E14:E19) -> 378000 | F20: =SUM(F14:F19) -> 336000 | G20: =SUM(G14:G19) -> 378000
B21: Total Cost (EUR) | C21: =C20/'[7]Overall Costing'!N2 -> 0 | D21: =D20/'[7]Overall Costing'!N2 -> 0 | E21: =E20/'[7]Overall Costing'!N2 -> 4344.8276 | F21: =F20/'[7]Overall Costing'!N2 -> 3862.069 | G21: =G20/'[7]Overall Costing'!N2 -> 4344.8276
B24: Total Falcon Team Cost (B) | C24: =SUM(C21:G21) -> 12551.724 | D24: =SUM(C20:G20) -> 1092000
B25: FOS | C25: 0.05
B26: Final Quote | C26: =C24*(1+C25) -> 13179.31 | D26: =D24*(1+C25) -> 1146600
B27: Insurance | D27: =C27*'[8]Overall Costing'!M5 -> 0
D28: =SUM(D26:D27) -> 1146600 | E28: =D28/'Overall Costing'!M5 -> 12197.872

Sheet I&C Cost
B2: Mechanical Installation Cost | C2: ='Local I&C'!E2+'FAPL I&C'!J14 -> 327382.98 | D2: =C2*(1+5%) -> 343752.13 | I2: Container Cost | J2: =400000*1.25 -> 500000
B3: Electrical Installation Cost | C3: ='Local I&C'!E3+'FAPL I&C'!J16 -> 107644.68 | D3: =C3*(1+5%) -> 113026.91 | I3: Container Cost | J3: =J2/88 -> 5681.8182
B4: PLC Comissioning Cost | C4: ='FAPL I&C'!J17+'FAPL I&C'!J18 -> 29446.809 | D4: =C4*(1+5%) -> 30919.149 | I4: For 36 Nos Containers from India | J4: =J3*36 -> 204545.45
B5: IT Comissioning Cost | C5: ='FAPL I&C'!J19 -> 14308.511 | D5: =C5*(1+5%) -> 15023.936 | I5: For Chute from Poland | J5: 0
B6: MHEs | D6: ='Local I&C'!E8 -> 20000 | I6: Total | J6: =J4+J5 -> 204545.45
B7: Waste Management | D7: ='Local I&C'!E9 -> 15000 | I7: Total | J7: =J6*'Overall Costing'!M5 -> 19227273
B8: Insurance Cost | D8: ='FAPL I&C'!C27 -> 10000

Sheet Local I&C
A1: Team | B1: Mandays | C1: Manhours | D1: Manhour Rate | E1: Price
A2: Technician | B2: 800 | C2: =B2*10 -> 8000 | D2: 37 | E2: =D2*C2 -> 296000
A3: Electrician | B3: 220 | C3: =B3*10 -> 2200 | D3: 37 | E3: =D3*C3 -> 81400
D4: Total Manpower Cost | E4: =SUM(E2:E3) -> 377400
D5: Factor of Saftey | E5: 0.05
D6: Final Manpower Cost | E6: =(E4*E5)+E4 -> 396270
D7: VAT | E7: =E6*0% -> 0
D8: Material Handling Equipment | E8: 20000
D9: Waste Management | E9: 15000
D10: Over all Cost | E10: =E6+E7+E9+E8 -> 431270 | F10: =E10*'Overall Costing'!M5 -> 40539380
F13: =E10+'[8]FAPl I&C'!C26 -> 489654.48

Sheet FAPL SAT
A1: B. FALCON HO TEAM
A2: Charges
A3: Person | B3: NO. OF MANPOWER REQUIRED | C3: No. of working days required | D3: AIR FARE | E3: VISA | F3: HOTEL | G3: MAN DAY COST | H3: DAILY ALLOWANCE
A4: Site Manager | B4: 1 | C4: =24+7 -> 31 | D4: 90000 | E4: 25000 | F4: 9000 | G4: 9000 | H4: 9000
A5: Mechanical Engineer | B5: 0 | C5: 0 | D5: =D4 -> 90000 | E5: =E4 -> 25000 | F5: =F4 -> 9000 | G5: 6000 | H5: =H4 -> 9000
A6: Electrical Engineer | B6: 1 | C6: =24+7 -> 31 | D6: =D5 -> 90000 | E6: =E5 -> 25000 | F6: =F5 -> 9000 | G6: 6000 | H6: =H5 -> 9000
A7: PLC | B7: 1 | C7: =24+7 -> 31 | D7: =D6 -> 90000 | E7: =E6 -> 25000 | F7: =F6 -> 9000 | G7: 9000 | H7: =H6 -> 9000
A8: PLC Engineer | B8: 1 | C8: 0 | D8: =D7 -> 90000 | E8: =E7 -> 25000 | F8: =F7 -> 9000 | G8: 9000 | H8: =H7 -> 9000
A9: IT Engineer | B9: 1 | C9: =24+7 -> 31 | D9: =D7 -> 90000 | E9: =E7 -> 25000 | F9: =F7 -> 9000 | G9: 12000 | H9: =H7 -> 9000
A11: Cost Calculation
A13: FALCON SUPERVISORS REQUIRED | B13: Total NO. OF DAYS REQUIRED | C13: AIR FARE | D13: VISA | E13: HOTEL | F13: MAN DAY COST | G13: DAILY ALLOWANCE
A14: Project Supervisor | B14: =ROUNDUP(C4*7/6,0) -> 37 | C14: =B4*D4 -> 90000 | D14: =B4*E4 -> 25000 | E14: =B4*(B14)*F4 -> 333000 | F14: =B4*B14*G4 -> 333000 | G14: =B4*(B14)*H4 -> 333000
A15: Mechanical Supervisor | B15: =ROUNDUP(C5*7/6,0) -> 0 | C15: =B5*D5 -> 0 | D15: =B5*E5 -> 0 | E15: =B5*(B15)*F5 -> 0 | F15: =B5*B15*G5 -> 0 | G15: =B5*(B15)*H5 -> 0 | H15: =ROUNDUP(#REF!/(8*6),0) -> #REF!
A16: Electrical Supervisor | B16: =ROUNDUP(C6*7/6,0) -> 37 | C16: =B6*D6 -> 90000 | D16: =B6*E6 -> 25000 | E16: =B6*(B16)*F6 -> 333000 | F16: =B6*B16*G6 -> 222000 | G16: =B6*(B16)*H6 -> 333000
A17: PLC Programmer | B17: =ROUNDUP(C7*7/6,0) -> 37 | C17: =B7*D7 -> 90000 | D17: =B7*E7 -> 25000 | E17: =B7*((B17))*F7 -> 333000 | F17: =B7*B17*G7 -> 333000 | G17: =B7*(B17)*H7 -> 333000
A18: IT Engineer | B18: =ROUNDUP(C8*7/6,0) -> 0 | C18: =B8*D8 -> 90000 | D18: =B8*E8 -> 25000 | E18: =B8*((B18))*F8 -> 0 | F18: =B8*B18*G8 -> 0 | G18: =B8*(B18)*H8 -> 0
A19: IT Engineer | B19: =ROUNDUP(C9*7/6,0) -> 37 | C19: =B9*D9 -> 90000 | D19: =B9*E9 -> 25000 | E19: =B9*(B19)*F9 -> 333000 | F19: =B9*B19*G9 -> 444000 | G19: =B9*(B19)*H9 -> 333000
B20: Total Cost (INR) | C20: 0 | D20: 0 | E20: =SUM(E14:E19) -> 1332000 | F20: =SUM(F14:F19) -> 1332000 | G20: =SUM(G14:G19) -> 1332000
B21: Total Cost (EUR) | C21: =C20/'[7]Overall Costing'!N2 -> 0 | D21: =D20/'[7]Overall Costing'!N2 -> 0 | E21: =E20/'[7]Overall Costing'!N2 -> 15310.345 | F21: =F20/'[7]Overall Costing'!N2 -> 15310.345 | G21: =G20/'[7]Overall Costing'!N2 -> 15310.345
B24: Total Falcon Team Cost (B) | C24: =SUM(C21:G21) -> 45931.034 | D24: =SUM(C20:G20) -> 3996000
B25: FOS | C25: 0.05
B26: Final Quote | C26: =C24*(1+C25) -> 48227.586 | D26: =D24*(1+C25) -> 4195800
B27: Insurance | D27: =C27*'[8]Overall Costing'!M5 -> 0
D28: =SUM(D26:D27) -> 4195800 | E28: =D28/'Overall Costing'!M5 -> 44636.17

Sheet FAPL I&C
A1: B. FALCON HO TEAM
A2: Charges
A3: Person | B3: NO. OF MANPOWER REQUIRED | C3: No. of working days required | D3: AIR FARE | E3: VISA | F3: HOTEL | G3: MAN DAY COST | H3: DAILY ALLOWANCE
A4: Site Manager | B4: 1 | C4: 90 | D4: 90000 | E4: 25000 | F4: 9000 | G4: 9000 | H4: 9000
A5: Mechanical Engineer | B5: 0 | C5: 0 | D5: =D4 -> 90000 | E5: =E4 -> 25000 | F5: =F4 -> 9000 | G5: 6000 | H5: =H4 -> 9000
A6: Electrical Engineer | B6: 1 | C6: 84 | D6: =D5 -> 90000 | E6: =E5 -> 25000 | F6: =F5 -> 9000 | G6: 6000 | H6: =H5 -> 9000
A7: PLC | B7: 1 | C7: 40 | D7: =D6 -> 90000 | E7: =E6 -> 25000 | F7: =F6 -> 9000 | G7: 9000 | H7: =H6 -> 9000
A8: PLC | B8: 1 | C8: 40 | D8: =D7 -> 90000 | E8: =E7 -> 25000 | F8: =F7 -> 9000 | G8: 9000 | H8: =H7 -> 9000
A9: IT Engineer | B9: 1 | C9: 35 | D9: =D7 -> 90000 | E9: =E7 -> 25000 | F9: =F7 -> 9000 | G9: 12000 | H9: =H7 -> 9000
A11: Cost Calculation
A13: FALCON SUPERVISORS REQUIRED | B13: Total NO. OF DAYS REQUIRED | C13: AIR FARE | D13: VISA | E13: HOTEL | F13: MAN DAY COST | G13: DAILY ALLOWANCE | I13: Total | J13: Total
A14: Project Supervisor | B14: =ROUNDUP(C4*7/6,0) -> 105 | C14: =B4*D4 -> 90000 | D14: =B4*E4 -> 25000 | E14: =B4*(B14)*F4 -> 945000 | F14: =B4*B14*G4 -> 945000 | G14: =B4*(B14)*H4 -> 945000 | I14: =SUM(C14:G14) -> 2950000 | J14: =I14/'Overall Costing'!$M$5 -> 31382.979
A15: Mechanical Supervisor | B15: =ROUNDUP(C5*7/6,0) -> 0 | C15: =B5*D5 -> 0 | D15: =B5*E5 -> 0 | E15: =B5*(B15)*F5 -> 0 | F15: =B5*B15*G5 -> 0 | G15: =B5*(B15)*H5 -> 0 | I15: =SUM(C15:G15) -> 0 | J15: =I15/'Overall Costing'!$M$5 -> 0
A16: Electrical Supervisor | B16: =ROUNDUP(C6*7/6,0) -> 98 | C16: =B6*D6 -> 90000 | D16: =B6*E6 -> 25000 | E16: =B6*(B16)*F6 -> 882000 | F16: =B6*B16*G6 -> 588000 | G16: =B6*(B16)*H6 -> 882000 | I16: =SUM(C16:G16) -> 2467000 | J16: =I16/'Overall Costing'!$M$5 -> 26244.681
A17: PLC Programmer | B17: =ROUNDUP(C7*7/6,0) -> 47 | C17: =B7*D7 -> 90000 | D17: =B7*E7 -> 25000 | E17: =B7*((B17))*F7 -> 423000 | F17: =B7*B17*G7 -> 423000 | G17: =B7*(B17)*H7 -> 423000 | I17: =SUM(C17:G17) -> 1384000 | J17: =I17/'Overall Costing'!$M$5 -> 14723.404
A18: PLC Programmer | B18: =ROUNDUP(C8*7/6,0) -> 47 | C18: =B8*D8 -> 90000 | D18: =B8*E8 -> 25000 | E18: =B8*((B18))*F8 -> 423000 | F18: =B8*B18*G8 -> 423000 | G18: =B8*(B18)*H8 -> 423000 | I18: =SUM(C18:G18) -> 1384000 | J18: =I18/'Overall Costing'!$M$5 -> 14723.404
A19: IT Engineer | B19: =ROUNDUP(C9*7/6,0) -> 41 | C19: =B9*D9 -> 90000 | D19: =B9*E9 -> 25000 | E19: =B9*(B19)*F9 -> 369000 | F19: =B9*B19*G9 -> 492000 | G19: =B9*(B19)*H9 -> 369000 | I19: =SUM(C19:G19) -> 1345000 | J19: =I19/'Overall Costing'!$M$5 -> 14308.511
B20: Total Cost (INR) | C20: =SUM(C14:C19) -> 450000 | D20: =SUM(D14:D19) -> 125000 | E20: =SUM(E14:E19) -> 3042000 | F20: =SUM(F14:F19) -> 2871000 | G20: =SUM(G14:G19) -> 3042000
B21: Total Cost (EUR) | C21: =C20/'Overall Costing'!$M$5 -> 4787.234 | D21: =D20/'Overall Costing'!$M$5 -> 1329.7872 | E21: =E20/'Overall Costing'!$M$5 -> 32361.702 | F21: =F20/'Overall Costing'!$M$5 -> 30542.553 | G21: =G20/'Overall Costing'!$M$5 -> 32361.702
B24: Total Falcon Team Cost (B) | C24: =SUM(C21:G21) -> 101382.98 | D24: =SUM(C20:G20) -> 9530000
B25: FOS | C25: 0.05
B26: Final Quote | C26: =C24*(1+C25) -> 106452.13 | D26: =D24*(1+C25) -> 10006500
B27: Insurance | C27: 10000 | D27: =C27*'Overall Costing'!M5 -> 940000
C28: =SUM(C26:C27) -> 116452.13 | D28: =SUM(D26:D27) -> 10946500

Sheet Overall Costing
A1: Sr. No | B1: Component | D1: Qty per set | E1: Set | F1: UOM | G1: Unit Rate | H1: Total(INR) | I1: Hiked INR | J1: =L5 -> EURO | K1: Family | L1: Sales Factor | M1: 0.675
A2: 1 | B2: Loop Cross Belt Sorter with VMS, ICR | D2: 1 | E2: 1 | F2: Set | G2: =+'Loop CBS'!C133 -> 1.2330198e+08 | H2: =G2*E2*D2 -> 1.2330198e+08 | I2: =H2*$M$2 -> 1.2330198e+08 | J2: =I2/$M$5 -> 1311723.2 | K2: Sorter + Scanning + Server + Induct Lines | L2: Hiked INR Factor | M2: 1
A3: 2 | B3: Arm Sorter | D3: 1 | E3: 1 | F3: Set | G3: =+'Arm Sorter'!C42 -> 16890000 | H3: =G3*E3*D3 -> 16890000 | I3: =H3*$M$2 -> 16890000 | J3: =I3/$M$5 -> 179680.85 | K3: Sorter+ Induct Lines | L3: Field wiring and controls | M3: 0.15
A4: 3 | B4: Conveyors | D4: 1 | E4: 1 | F4: Set | G4: =Conveyors!G70 -> 62276876 | H4: =G4*E4*D4 -> 62276876 | I4: =H4*$M$2 -> 62276876 | J4: =I4/$M$5 -> 662519.96 | K4: Conveyors | L4: Region | M4: Europe
A5: 4 | B5: Destinations | D5: 1 | E5: 1 | F5: Set | G5: =+Destinations!G23 -> 37678623 | H5: =G5*E5*D5 -> 37678623 | I5: =H5*$M$2 -> 37678623 | J5: =I5/$M$5 -> 400836.41 | K5: Destinations | L5: EURO | M5: 94 | N5: current rate is 100
A6: 5 | B6: Steelwork | D6: 1 | E6: 1 | F6: Set | G6: =+Steelworks!G10 -> 59135600 | H6: =G6*E6*D6 -> 59135600 | I6: =H6*$M$2 -> 59135600 | J6: =I6/$M$5 -> 629102.13 | K6: Steelworks
B7: CE Compliance | D7: 1 | E7: 1 | F7: Set | G7: ='Safety Cost Calc'!$D$19*2 -> 1040800 | H7: =(G7*E7*D7)/$M$1 -> 1541925.9 | I7: =H7*$M$2 -> 1541925.9 | J7: =I7/$M$5 -> 16403.467 | K7: CE Compliance
A8: 8 | B8: Software Packages | D8: 1 | E8: 1 | F8: Set | G8: =+'Software Packages'!F7 -> 1500000 | H8: =G8*E8*D8 -> 1500000 | I8: =H8*$M$2 -> 1500000 | J8: =I8/$M$5 -> 15957.447 | K8: Software
A9: 9 | B9: Installation & Commissioning | D9: 1 | E9: 1 | F9: Set | G9: ='Local I&C'!F10+'FAPL I&C'!D28 -> 51485880 | H9: =G9*E9*D9 -> 51485880 | I9: =H9*$M$2 -> 51485880 | J9: =I9/$M$5 -> 547722.13 | K9: Installation & Commissioning
A10: 10 | B10: Packaging & Documentation | D10: 1 | E10: 1 | F10: Set | G10: =SUM(H2:H6,)*5% -> 14964154 | H10: =G10*E10*D10 -> 14964154 | I10: =H10*$M$2 -> 14964154 | J10: =I10/$M$5 -> 159193.13 | K10: Packaging & Forwarding
A11: 11 | B11: Project Management and Engineering Charges | D11: 1 | E11: 1 | F11: Set | G11: =SUM(H2:H10)*2.5% -> 9219376 | H11: =G11*E11*D11 -> 9219376 | I11: =H11*$M$2 -> 9219376 | J11: =I11/$M$5 -> 98078.468 | K11: Project Management and Engineering Charges
A12: 12 | B12: System Acceptance Test | D12: 1 | E12: 1 | F12: Set | G12: ='FAPL SAT'!D28 -> 4195800 | H12: =G12*E12*D12 -> 4195800 | I12: =H12*$M$2 -> 4195800 | J12: =I12/$M$5 -> 44636.17
A13: 13 | B13: Freight | D13: 1 | E13: 1 | F13: Set | G13: ='I&C Cost'!J7 -> 19227273 | H13: =G13*E13*D13 -> 19227273 | I13: =H13*$M$2 -> 19227273 | J13: =I13/$M$5 -> 204545.45
A14: 14 | B14: Support Ramp Up | D14: 1 | E14: 1 | F14: Set | G14: ='Support Rampup'!D28 -> 1146600 | H14: =G14*E14*D14 -> 1146600 | I14: =H14*$M$2 -> 1146600 | J14: =I14/$M$5 -> 12197.872
A15: 15 | B15: Spare Kit | D15: 1 | E15: 1 | F15: Set | G15: =SUM(G2:G5)*2.5% -> 6003687 | H15: =G15*E15*D15 -> 6003687 | I15: =H15*$M$2 -> 6003687 | J15: =I15/$M$5 -> 63869.011
A16: 16 | B16: Protection on Ground | D16: 1 | E16: 1 | F16: Set | G16: 1500000 | H16: =G16*E16*D16 -> 1500000 | I16: =H16*$M$2 -> 1500000 | J16: =I16/$M$5 -> 15957.447
G17: Total | H17: =SUM(H2:H11) -> 3.7799442e+08 | I17: =SUM(I2:I12) -> 3.8219022e+08 | J17: =SUM(J2:J16) -> 4362423.2
H19: Recommended Spare Package | I19: =SUM(I2:I5)*8% -> 19211798 | J19: =SUM(J2:J5)*8% -> 204380.84

Sheet Safety Cost Calc
B3: Compliance Requirement | D3: CE/AS/NZS Compliance
B4: Type of Sorter | D4: CBS
B5: E-Stop Feedback | D5: Individual E-Stop
B6: Sorter Safety Component Costing
B7: Sr No. | C7: Section | D7: Qty | E7: UoM | F7: Remarks
B9: 1 | C9: Manual Feed Zone | D9: 2 | E9: No. | F9: considered 01 safety zone per each manual feeding zone
B10: 2 | C10: Auto Feedline | D10: 0 | E10: No. | F10: considered 01 safety zone per each auto feedline
B11: 3 | C11: CBS loop/Arm Sorter/SWEDI Sorter/POP-up Sorter | D11: 1 | E11: No. | F11: considered 01 safety zone per each CBS Loop CBS Safety zone serves as Global Stop (entire system stop)
B12: 4 | C12: Inbound Zone | D12: 2 | E12: No. | F12: considered 01 safety zone per each inbound zone
B13: 5 | C13: Highway | D13: 0 | E13: No. | F13: considered 01 safety zone per each Highway
B14: 6 | C14: VDS Loop | D14: 2 | E14: No. | F14: considered 01 safety zone per each VDS Loop
B15: 7 | C15: Outbound Zone | D15: 2 | E15: No. | F15: considered 01 safety zone per each outbound Zone
B16: 8 | C16: Maintenance Zone/Sorter Access | D16: 2 | E16: No. | F16: considered 01 safety zone per each outbound Zone
B17: 9 | C17: Pull Cord | D17: 2 | E17: No. | F17: Avg lenght 30 mtr
C19: Costing | D19: =Data!N25 -> 520400 | E19: INR | F19: Costing includes only material cost

Sheet Data
B2: Unit safety Zone Panel Cost | I2: Number of Zones
B3: Sr No. | C3: Component | D3: Qty | E3: Cost | F3: Total Cost | G3: Remarks | I3: Sr No. | J3: Section | K3: Qty | L3: UoM | M3: No. of Zones | N3: Zone Cost | O3: Remarks
B5: 1 | C5: Safety Controller | D5: 1 | E5: 15000 | F5: =D5*E5 -> 15000 | G5: Controller with 04 Test signal and 04 safety Outputs for 02 safety Zones | I5: 1 | J5: Manual Feedline | K5: ='Safety Cost Calc'!D9 -> 2 | L5: No. | M5: =K5*1 -> 2 | N5: =(M5/2)*$D$30 -> 84600
B6: 2 | C6: Contactors | D6: 4 | E6: 1500 | F6: =D6*E6 -> 6000 | G6: 04 contactor for 02 dual chanel output isolation | I6: 2 | J6: Auto Feedline | K6: ='Safety Cost Calc'!D10 -> 0 | L6: No. | M6: =K6*1 -> 0 | N6: =(M6/2)*$D$30 -> 0
B7: 3 | C7: Panel | D7: 1 | E7: 8000 | F7: =D7*E7 -> 8000 | I7: 3 | J7: ='Safety Cost Calc'!C11 -> CBS loop/Arm Sorter/SWEDI Sorter/POP-up Sorter | K7: ='Safety Cost Calc'!D11 -> 1 | L7: No. | M7: =K7*1 -> 1 | N7: =(M7/2)*$D$30 -> 42300
B8: 4 | C8: Cables | D8: 1 | E8: 10000 | F8: =D8*E8 -> 10000 | I8: 4 | J8: Inbound Zone | K8: ='Safety Cost Calc'!D12 -> 2 | L8: No. | M8: =K8*1 -> 2 | N8: =(M8/2)*$D$30 -> 84600
B9: 5 | C9: Switchgear | D9: 1 | E9: 2000 | F9: =D9*E9 -> 2000 | I9: 5 | J9: Highway | K9: ='Safety Cost Calc'!D13 -> 0 | L9: No. | M9: =K9*1 -> 0 | N9: =(M9/2)*$D$30 -> 0
B10: 6 | C10: SMPS | D10: 1 | E10: 7000 | F10: =D10*E10 -> 7000 | I10: 6 | J10: VDS Loop | K10: ='Safety Cost Calc'!D14 -> 2 | L10: No. | M10: =K10*1 -> 2 | N10: =(M10/2)*$D$30 -> 84600
B11: 7 | C11: E-Stop+mounting | D11: 8 | E11: 2700 | F11: =D11*E11 -> 21600 | G11: 04 E-stops considered for each safety zone | I11: 7 | J11: Outbound Zone | K11: ='Safety Cost Calc'!D15 -> 2 | L11: No. | M11: =K11*1 -> 2 | N11: =(M11/2)*$D$30 -> 84600
F12: =SUM(F5:F11) -> 69600 | I12: 8 | J12: Maintenance Zone/Sorter Access | K12: ='Safety Cost Calc'!D16 -> 2 | L12: No. | M12: NA | N12: =K12*$F$20 -> 36000
B13: 8 | C13: Murr Card for feedback+cabling | D13: 0.5 | E13: 30000 | F13: =D13*E13 -> 15000 | G13: 01 card per 16 E-Stop inputs | I13: 9 | J13: =C21 -> Inching Station (Mech+Elec) | K13: =IF('Safety Cost Calc'!D4=Data!J22,0,Data!K7) -> 1 | L13: No. | M13: NA | N13: =(K13*F21) -> 9300
F14: =F12+F13 -> 84600 | I14: 10 | J14: =C22 -> Pull Cord | K14: ='Safety Cost Calc'!D17 -> 2 | L14: No. | M14: NA | N14: =K14*F22 -> 18400
B15: Safety Components Costing | I15: 11 | J15: =C18 -> Speed Monitoring Controller (SMC) | K15: =IF('Safety Cost Calc'!D4=Data!J22,0,Data!K7) -> 1 | L15: No. | M15: NA | N15: =K15*(F18+F19) -> 76000
B16: Sr No. | C16: Component | D16: Qty | E16: Cost | F16: Total Cost
B18: 1 | C18: Speed Monitoring Controller (SMC) | D18: 1 | E18: 60000 | F18: =E18*D18 -> 60000 | G18: For Sorter Dead speed and safe speed monitoring
B19: 2 | C19: SMC Photo sensors + Cables | D19: 2 | E19: 8000 | F19: =E19*D19 -> 16000 | G19: For Sorter Dead speed and safe speed monitoring | J19: Compliance | N19: Cost
B20: 3 | C20: Safety Door Switches | D20: 1 | E20: 18000 | F20: =E20*D20 -> 18000 | J20: CE/AS/NZS Compliance | N20: =(SUM(N5:N15)) -> 520400
B21: 4 | C21: Inching Station (Mech+Elec) | D21: 1 | E21: =5000+4300 -> 9300 | F21: =E21*D21 -> 9300 | G21: For inching mode | J21: STD Compliance | N21: =SUM(N5:N14) -> 444400
B22: 5 | C22: Pull Cord | D22: 1 | E22: 9200 | F22: =E22*D22 -> 9200 | G22: Avg length 30 mtrs | J22: Non CBS | N22: =SUM(N5:N12)+N14 -> 435100
N25: =IF('Safety Cost Calc'!D4=Data!J22,Data!N22,IF('Safety Cost Calc'!D3=Data!J20,Data!N20,Data!N21)) -> 520400
C27: Safety Door Switches
C28: CBS
C29: Non CBS
C30: FeedBack of | D30: =IF('Safety Cost Calc'!D5=Data!C31,Data!D31,Data!D32) -> 84600
C31: Individual Zone | D31: =F12 -> 69600
C32: Individual E-Stop | D32: =F14 -> 84600

Sheet Section Identification
A3: Sr No. | B3: Section
A5: 1 | B5: Manual Feed Zone
A6: 2 | B6: Auto Feedline
A7: 3 | B7: CBS loop/Arm Sorter/SWEDI Sorter/POP-up Sorter
A8: 4 | B8: Inbound Zone
A9: 5 | B9: Highway
A10: 6 | B10: VDS Loop
A11: 7 | B11: Outbound Zone
A12: 8 | B12: Maintenance Zone/Sorter Access
A13: 9 | B13: Pull Cord

Sheet Loop CBS
B1: Factor | C1: ='Overall Costing'!$M$1 -> 0.675 | D1: Speed Factor | E1: 1.1
A3: Model Number Understanding->> | B3: CB-[Single/Dual Belt]-[Carrier Pitch]-[Belt Length]
A4: Model Number | B4: Carrier Type | C4: Carrier Pitch | D4: Carrier Belt- Belt Pitch/Length (mm) | E4: Curve Radius (m) | F4: LIM Compatible? | G4: LSM Compatible? | H4: Belts Per Carrier | I4: Belts per LIM | J4: Belts per LSM
A5: CB-SB-600-800 | B5: Single Belt | C5: 600 | D5: 600/800 | E5: 3.5 | F5: Yes | G5: Yes | H5: 1 | I5: 40 | J5: 60
A6: CB-DB-1175-800 | B6: Dual Belt | C6: 1175 | D6: 600/800 | E6: 4.5 | F6: Yes | G6: No | H6: 2 | I6: 40 | J6: NA
A7: XL-CB-DB-1200-1200 | B7: XL- Dual Belt | C7: 1200 | D7: 600/1200 | E7: 4.58 | F7: Yes | G7: Yes | H7: 2 | I7: 32 | J7: 36
A8: XL-CB-SB-800-1200 | B8: XL- Single Belt | C8: 800 | D8: 800/1200 | E8: 4.58 | F8: Yes | G8: Yes | H8: 1 | I8: 32 | J8: 36
A11: 1 | B11: Select Model | C11: CB-DB-1175-800
A12: Output | B12: Radius | C12: =VLOOKUP(C11,A4:G8,5,FALSE) -> 4.5
A13: Output | B13: Radius Price | C13: =VLOOKUP(C12,Loop!$C$4:$D$6,2,FALSE) -> 27466.436
A14: 2 | B14: Enter the Number of 30 Degree Curves | C14: =(16*45)/30 -> 24
A15: 3 | B15: Enter the Loop Length (Including length of Curves) in meters | C15: =(146.875*2)+(3.6*16) -> 351.35
A16: Output | B16: Curve Length (m) | C16: =C14*2*3.14*C12/12 -> 56.52
A17: Output | B17: Straight Track length (m) | C17: =C15-C16 -> 294.83
A18: Output | B18: Cost of Straight Track | C18: =IF(OR(C11=A5,C11=A6),C17*Loop!D2,C17*Loop!D3) -> 6445087
A19: Output | B19: Cost of Curved track | C19: =C13*C14 -> 659194.46
A20: Output | B20: Total Track Cost (A) | C20: =C19+C18 -> 7104281.4
A21: Output | B21: Carrier Pitch | C21: =VLOOKUP(C11,A4:G8,3,FALSE) -> 1175
A22: Output | B22: Carrier Unit Price | C22: =VLOOKUP(C21,Loop!C7:D10,2,FALSE) -> 14796.02
A23: Output | B23: Number of Carriers | C23: =ROUND(C15*1000/C21,0) -> 299
A24: Output | B24: Total Carrier Cost (B) | C24: =C23*C22 -> 4424010
A25: Output | B25: Belts per Carrier | C25: =VLOOKUP(C11,A4:H8,8,FALSE) -> 2
A26: Output | B26: Total Carrier Belts | C26: =C23*C25 -> 598
A27: Output | B27: Carrier Belt Type | C27: =VLOOKUP(C11,A4:H8,4,FALSE) -> 600/800
A28: Output | B28: Carrier Belt Unit Price | C28: =VLOOKUP(C27,Loop!C12:D14,2,FALSE) -> 30378.6
A29: Output | B29: Total Carrier Belt Cost (C) | C29: =C28*C26 -> 18166403
A30: 4 | B30: Select the Sorter Height | C30: >2.4 meter and <=3.5 meter | D30: 3.1m
A31: Output | B31: Unit Price per Leg | C31: =VLOOKUP(C30,Loop!C16:D18,2,FALSE) -> 15584.8
A32: Output | B32: Number of Legs | C32: =ROUNDUP(C15/2.4,0) -> 147
A33: Output | B33: Total Legs Cost (D) | C33: =C32*C31 -> 2290965.6
A34: 5 | B34: Select Type of Linear Motor | C34: LIM
A35: Output | B35: Number of Belts Per Motor | C35: =IF(C34="LSM",VLOOKUP(C11,A4:J8,10,FALSE),VLOOKUP(C11,A4:J8,9,FALSE)) -> 40
A36: Output | B36: Total Number of Motors | C36: =ROUNDUP(C26/C35,0) -> 15
A37: Output | B37: Unit Price per Motor Drive | C37: =VLOOKUP(C34,Loop!C20:D21,2,FALSE) -> 364930.65
A38: Output | B38: Total Drive cost (E) | C38: =C36*C37 -> 5473959.8
A39: Output | B39: Total Loop Control Cost (F) | C39: =IF(OR(C11=A5,C11=A6),Loop!D23,Loop!D24) -> 432669.44
A40: 6 | B40: Select the PLC Platform | C40: Siemens
A41: Output | B41: Total PLC Platform Cost (G) | C41: =VLOOKUP(C40,Loop!C25:D26,2,FALSE) -> 4015547.1
A42: 7 | B42: Server Required? | C42: No
A43: 8 | B43: If Yes, Select the Server Configuration | C43: HAA-Falcon Standard
A44: Output | B44: Unit Price of Selected Server | C44: =IF(C42="Yes",VLOOKUP(C43,Loop!C28:D29,2,FALSE),0) -> 0
A45: Output | B45: Total Server Price (H) | C45: =C44 -> 0
A46: 9 | B46: Enter Number of Induct Zones | C46: 2
A47: 10 | B47: ICR890 12K 5 Camera- 5 Side Per Scan Tunnel | C47: 1
A49: Output
A50: Output
A51: Output | B51: Total Barcode Scanning Cost | C51: =C47*C46*VLOOKUP(B47, Loop!$C$31:$D$37,2,0) -> 11600000 | D51: =(C51/'Overall Costing'!M1)/'Overall Costing'!M5 -> 182821.12
A53: 12 | B53: VMS5200 Per Scan Tunnel | C53: 1
A54: Output
A55: Output
A56: Output | B56: Total Volume Scanning Cost | C56: =C53*C46*VLOOKUP(B53,Loop!$C$39:$D$41,2,0) -> 2090000 | D56: =(C56/'Overall Costing'!M1)/'Overall Costing'!M5 -> 32939.322
A57: Output | B57: Total Scan Tunnel Costs (I) | C57: =C56+C51 -> 13690000
A58: 13 | B58: Select Minimum Height of Product | C58: <10 mm
A59: Output | B59: ECDS Unit Cost | C59: =IF(C58=">=10 mm",Loop!D43,Loop!D44) -> 385828.8
A60: Output | B60: Total ECDS Cost (J) | C60: =C59*C46 -> 771657.6
A61: 14 | B61: Length of Safety Net (in meters) | C61: =(8*15)+(33.768+70.067+2.3+11.612)*2 -> 355.494
A62: Output | B62: Total Safety Net Cost (K) | C62: =C61*Loop!D48 -> 3129911.4
A63: 15 | B63: Length of Wiremesh Fencing (in meters) | C63: =(C74+1+1)*6.5 -> 104
A64: Output | B64: Total Wiremesh fencing Cost (L) | C64: =C63*Loop!D49 -> 788164
A65: 16 | B65: Length of Bridge Plate (in meters) | C65: =94.44*2 -> 188.88
A66: Output | B66: Total Bridge Plate Cost (M) | C66: =C65*Loop!D50 -> 800426.22
B69: Total Loop Cost (A+B+C+D+E+F+G+H+I+J+K+L+M) | C69: =(C20+C24+C29+C33+C38+C39+C41+C45+C57+C60+C62+C64+C66)*E1 -> 67196795
B70: Recommended Sale Price | C70: =C69/C1 -> 99550807 | D70: =C70/'Overall Costing'!M5 -> 1059051.1
B73: Main Inducts
A74: 17 | B74: Enter the Total Number of Inducts in the System | C74: 14
A75: 18 | B75: Select the Width of Induct Conveyors | C75: 1000
A76: 19 | B76: Enter number of Angle Merge Conveyors per Induct | C76: 1
A77: 20 | B77: Enter Number of Short Buffer Conveyors per Induct | C77: 2
A78: 21 | B78: Enter Number of Spacing Conveyors per Induct | C78: 1
A79: 22 | B79: Enter Number of Single Operator Loading Conveyor | C79: 1
A80: 23 | B80: Enter Number of Double Operator Loading Conveyor | C80: 0
A81: 24 | B81: Enter Number of Receiving Conveyor | C81: 0
A82: Output | B82: Main Inducts Costing
A83: Output | C83: QTY | D83: Cost | E83: Cable Tray Length
A84: Output | B84: Angle Merge | C84: =C76*$C$74 -> 14 | D84: =VLOOKUP($C$75,Inducts!$C$3:$E$6,MATCH('Loop CBS'!$C$58,Inducts!$C$2:$E$2,0))*C84 -> 2081945.2 | E84: =VLOOKUP($C$75,Inducts!$C$3:$F$6,4,0)*C84 -> 42
A85: Output | B85: Short Buffer | C85: =C77*$C$74 -> 28 | D85: =VLOOKUP($C$75,Inducts!$C$7:$E$10,MATCH('Loop CBS'!$C$58,Inducts!$C$2:$E$2,0))*C85 -> 3510634.1 | E85: =VLOOKUP($C$75,Inducts!$C$7:$F$10,4,0)*C85 -> 28
A86: Output | B86: Spacing Conveyor | C86: =C78*$C$74 -> 14 | D86: =VLOOKUP($C$75,Inducts!$C$11:$E$14,MATCH('Loop CBS'!$C$58,Inducts!$C$2:$E$2,0))*C86 -> 1833279.5 | E86: =VLOOKUP($C$75,Inducts!$C$11:$F$14,4,0)*C86 -> 21
A87: Output | B87: Single Operator Loading Conveyor | C87: =C79*$C$74 -> 14 | D87: =VLOOKUP($C$75,Inducts!$C$15:$E$18,MATCH('Loop CBS'!$C$58,Inducts!$C$2:$E$2,0))*C87 -> 2602644.3 | E87: =VLOOKUP($C$75,Inducts!$C$15:$F$18,4,0)*C87 -> 21
A88: Output | B88: Double Operator Loading Conveyor | C88: =C80*$C$74 -> 0 | D88: =VLOOKUP($C$75,Inducts!$C$19:$E$22,MATCH('Loop CBS'!$C$58,Inducts!$C$2:$E$2,0))*C88 -> 0 | E88: =VLOOKUP($C$75,Inducts!$C$19:$F$22,4,0)*C88 -> 0
A89: Output | B89: Receiving Conveyor | C89: =C81*$C$74 -> 0 | D89: =VLOOKUP($C$75,Inducts!$C$23:$E$26,MATCH('Loop CBS'!$C$58,Inducts!$C$2:$E$2,0))*C89 -> 0 | E89: =VLOOKUP($C$75,Inducts!$C$23:$F$26,4,0)*C89 -> 0
A90: Output | B90: Total | D90: =SUM(D84:D89) -> 10028503 | E90: =SUM(E84:E89) -> 112
B92: Special Inducts
A93: 25 | B93: Enter the Total Number of Inducts in the System | C93: 0
A94: 26 | B94: Select the Width of Induct Conveyors | C94: 800
A95: 27 | B95: Enter number of Angle Merge Conveyors per Induct | C95: 0
A96: 28 | B96: Enter Number of Short Buffer Conveyors per Induct | C96: 0
A97: 29 | B97: Enter Number of Spacing Conveyors per Induct | C97: 0
A98: 30 | B98: Enter Number of Single Operator Loading Conveyor | C98: 0
A99: 31 | B99: Enter Number of Double Operator Loading Conveyor | C99: 0
A100: 32 | B100: Enter Number of Receiving Conveyor | C100: 0
A101: Output | B101: Special Inducts Costing
A102: Output | C102: QTY | D102: Cost | E102: Cable Tray Length
A103: Output | B103: Angle Merge | C103: =C95*$C$93 -> 0 | D103: =VLOOKUP($C$94,Inducts!$C$3:$E$6,MATCH('Loop CBS'!$C$58,Inducts!$C$2:$E$2,0))*C103 -> 0 | E103: =VLOOKUP($C$94,Inducts!$C$3:$F$6,4,0)*C103 -> 0
A104: Output | B104: Short Buffer | C104: =C96*$C$93 -> 0 | D104: =VLOOKUP($C$94,Inducts!$C$7:$E$10,MATCH('Loop CBS'!$C$58,Inducts!$C$2:$E$2,0))*C104 -> 0 | E104: =VLOOKUP($C$94,Inducts!$C$7:$F$10,4,0)*C104 -> 0
A105: Output | B105: Spacing Conveyor | C105: =C97*$C$93 -> 0 | D105: =VLOOKUP($C$94,Inducts!$C$11:$E$14,MATCH('Loop CBS'!$C$58,Inducts!$C$2:$E$2,0))*C105 -> 0 | E105: =VLOOKUP($C$94,Inducts!$C$11:$F$14,4,0)*C105 -> 0
A106: Output | B106: Single Operator Loading Conveyor | C106: =C98*$C$93 -> 0 | D106: =VLOOKUP($C$94,Inducts!$C$15:$E$18,MATCH('Loop CBS'!$C$58,Inducts!$C$2:$E$2,0))*C106 -> 0 | E106: =VLOOKUP($C$94,Inducts!$C$15:$F$18,4,0)*C106 -> 0
A107: Output | B107: Double Operator Loading Conveyor | C107: =C99*$C$93 -> 0 | D107: =VLOOKUP($C$94,Inducts!$C$19:$E$22,MATCH('Loop CBS'!$C$58,Inducts!$C$2:$E$2,0))*C107 -> 0 | E107: =VLOOKUP($C$94,Inducts!$C$19:$F$22,4,0)*C107 -> 0
A108: Output | B108: Receiving Conveyor | C108: =C100*$C$93 -> 0 | D108: =VLOOKUP($C$94,Inducts!$C$23:$E$26,MATCH('Loop CBS'!$C$58,Inducts!$C$2:$E$2,0))*C108 -> 0 | E108: =VLOOKUP($C$94,Inducts!$C$23:$F$26,4,0)*C108 -> 0
A109: Output | B109: Total | D109: =SUM(D103:D108) -> 0 | E109: =SUM(E103:E108) -> 0
A110: Output
...

Sheet Inducts
B2: Conveyor Name | C2: Width | D2: <10 mm | E2: >=10 mm | F2: Length
B3: Angle Merge | C3: 800 | D3: =120170*1.125 -> 135191.25 | E3: =120170*1.125 -> 135191.25 | F3: 2
B4: Angle Merge | C4: 1000 | D4: =D3*1.1 -> 148710.38 | E4: =E3*1.1 -> 148710.38 | F4: 3
B5: Angle Merge XL | C5: 1000 XL | D5: =D4*1.1 -> 163581.41 | E5: =E4*1.1 -> 163581.41 | F5: 3
B6: Angle Merge | C6: 1200 | D6: =D4*1.2 -> 178452.45 | E6: =E4*1.2 -> 178452.45 | F6: 3
B7: Buffer Conveyor | C7: 800 | D7: =101317*1.125 -> 113981.62 | E7: =D7-24000+4000 -> 93981.625 | F7: 1
B8: Buffer Conveyor | C8: 1000 | D8: =D7*1.1 -> 125379.79 | E8: =E7*1.1 -> 103379.79 | F8: 1
B9: Buffer Conveyor XL | C9: 1000 XL | D9: - | E9: =E8*1.1 -> 113717.77 | F9: 0.5
B10: Buffer Conveyor | C10: 1200 | D10: =D8*1.2 -> 150455.74 | E10: =E8*1.2 -> 124055.74 | F10: =F8 -> 1
B11: Spacing Conveyor | C11: 800 | D11: =105817*1.125 -> 119044.12 | E11: =D11-24000+4000 -> 99044.125 | F11: 1
B12: Spacing Conveyor | C12: 1000 | D12: =D11*1.1 -> 130948.54 | E12: =E11*1.1 -> 108948.54 | F12: 1.5
B13: Spacing Conveyor XL | C13: 1000 XL | D13: - | E13: =E12*1.1 -> 119843.39 | F13: 1.2
B14: Spacing Conveyor | C14: 1200 | D14: =D12*1.2 -> 157138.24 | E14: =E12*1.2 -> 130738.24 | F14: =F12 -> 1.5
B15: Single Operator Loading Conveyor | C15: 800 | D15: =E15+24000-4000 -> 169002.88 | E15: =132447*1.125 -> 149002.88 | F15: 1.5
B16: Single Operator Loading Conveyor | C16: 1000 | D16: =D15*1.1 -> 185903.16 | E16: =E15*1.1 -> 163903.16 | F16: 1.5
B17: Single Operator Loading Conveyor XL | C17: 1000 XL | D17: - | E17: =E16*1.1 -> 180293.48 | F17: =F16 -> 1.5
B18: Single Operator Loading Conveyor | C18: 1200 | D18: =D16*1.2 -> 223083.8 | E18: =E16*1.2 -> 196683.8 | F18: =F16 -> 1.5
B19: Double Operator Loading Conveyor | C19: 800 | D19: =E19+24000-4000 -> 284375 | E19: =235000*1.125 -> 264375 | F19: 3.5
B20: Double Operator Loading Conveyor | C20: 1000 | D20: =D19*1.1 -> 312812.5 | E20: =E19*1.1 -> 290812.5 | F20: 5
B21: Double Operator Loading Conveyor XL | C21: 1000 XL | D21: - | E21: =E20*1.1 -> 319893.75 | F21: =F20 -> 5
B22: Double Operator Loading Conveyor | C22: 1200 | D22: =D20*1.2 -> 375375 | E22: =E20*1.2 -> 348975 | F22: =F20 -> 5
B23: Receiving Conveyor | C23: 800 | D23: =E23+24000-4000 -> 284375 | E23: =235000*1.125 -> 264375 | F23: 3.5
B24: Receiving Conveyor | C24: 1000 | D24: =D23*1.1 -> 312812.5 | E24: =E23*1.1 -> 290812.5 | F24: 5
B25: Receiving Conveyor XL | C25: 1000 XL | D25: - | E25: =E24*1 -> 290812.5 | F25: 3.3
B26: Receiving Conveyor | C26: 1200 | D26: =D24*1.2 -> 375375 | E26: =E24*1.2 -> 348975 | F26: =F24 -> 5
B27: Top Loader Induct | C27: 800 | D27: 130948.54 | E27: 108948.54 | F27: 1
C29: Control Panel | D29: =198000*1.12 -> 221760
C30: Leg Structure | D30: =(75000/6)*1.15 -> 14375
C31: Overshoot Assembly | D31: =14000*1.15 -> 16100
C40: 13

Sheet Linear CBS
B1: Factor | C1: ='Overall Costing'!$M$1 -> 0.675
A3: Model Number Understanding->> | B3: CB-[Single/Dual Belt]-[Carrier Pitch]-[Belt Length]
A4: Model Number | B4: Carrier Type | C4: Carrier Pitch | D4: Carrier Belt- Belt Pitch/Length (mm) | E4: Curve Radius (m) | F4: LIM Compatible? | G4: LSM Compatible? | H4: Belts Per Carrier | I4: Belts per LIM | J4: Belts per LSM
A5: CB-SB-500-800 | B5: Single Belt | C5: 500 | D5: 500/800 | E5: NA | F5: Yes | G5: Yes | H5: 1 | I5: 20 | J5: =VLOOKUP($C$8,Linear!$C$2:$E$3,3,0) -> 30
A8: 1 | B8: Select Model | C8: Heavy Duty | D8: Regular<=10 Kg for Sigle Carrier
A9: 2 | B9: Enter Linear Length (Top side only excluding curves) in meters | C9: 20.08
A10: Output | B10: Straight Track length (m) | C10: =+C9*2 -> 40.16
A11: Output | B11: Cost of Straight Track | C11: =(VLOOKUP($C$8,Linear!C2:$D$3,2,0))*C10 -> 1465840
A12: Output | B12: Cost of Curved track | C12: =+Linear!D4 -> 76500
A13: Output | B13: Total Track Cost (A) | C13: =C12+C11 -> 1542340
A14: Output | B14: Carrier Unit Price | C14: =VLOOKUP($C$8,Linear!$C$7:$D$8,2,0) -> 41500
A15: Output | B15: Number of Carriers | C15: =ROUNDUP((C9*1000/C5)*2+8,0) -> 89
A16: Output | B16: Total Carrier Cost (B) | C16: =C15*C14 -> 3693500
A17: Output | B17: Unit Price per Leg | C17: =Linear!$D$10 -> 8000 | D17: Standard
A18: Output | B18: Number of Legs | C18: =ROUNDUP(C9/2.4,0) -> 9
A19: Output | B19: Total Legs Cost (C) | C19: =C18*C17 -> 72000
A20: 3 | B20: Select Type of Linear Motor | C20: LSM
A21: Output | B21: Number of Belts Per Motor | C21: =IF(C20="LSM",$J$5,IF(C20="LIM",$I$5,0)) -> 30 | D21: Standard LSM
A22: Output | B22: Total Number of Motors | C22: =ROUNDUP(C15/C21,0) -> 3
A23: Output | B23: Unit Price per Motor Drive | C23: =VLOOKUP(C20,Linear!C12:D13,2,FALSE) -> 681000 | F23: ;
A24: Output | B24: Total Drive cost (D) | C24: =C22*C23 -> 2043000
A25: Output | B25: Positionning & Centering Cost (E) | C25: =Linear!D15 -> 333987.56
A26: 4 | B26: Select the PLC Platform & Controle | C26: Omron
A27: Output | B27: Loop Controle | C27: =VLOOKUP($C$26,Linear!$C$16:$D$17,2,0) -> 250000
A28: Output | B28: Main Controle (PLC Platform) | C28: =VLOOKUP($C$26,Linear!$C$19:$D$20,2,0) -> 1400000
A29: Output | B29: Total PLC Platform Cost (F) | C29: =C27+C28 -> 1650000
A30: 5 | B30: Server Required? | C30: YES | D30: NO for International Projects
A31: 6 | B31: If Yes, Select the Server Configuration | C31: HAA-Amazon Standard
A32: Output | B32: Unit Price of Selected Server | C32: =IF(C30="Yes",VLOOKUP(C31,Linear!C22:D23,2,FALSE),0) -> 2128000
A33: Output | B33: Total Server Price (G) | C33: =C32 -> 2128000
A34: 7 | B34: Enter Number of Induct Zones | C34: 0
A35: 8 | B35: Scanning tunnel Qty/ induct zone | C35: 0
A36: 9 | B36: ICR-890 12K | C36: =VLOOKUP(B36,Linear!$C$25:$D$31,2,0) -> 1880402.9
A37: Output | B37: Total Barcode Scanning Cost | C37: =C36*C35*C34 -> 0
A38: 10 | B38: VMS Qty/ induct zone | C38: 0
A39: 11 | B39: VMS 4200 | C39: =VLOOKUP(B39,Linear!$C$32:$D$34,2,0) -> 825000
A40: Output | B40: Total Volume Scanning Cost | C40: =C39*C38*C34 -> 0
A41: Output | B41: Total Scan Tunnel Costs (H) | C41: =C40+C37 -> 0
A42: 12 | B42: Select Minimum Height of Product | C42: >=10 mm
A43: 13 | B43: Length of Wiremesh Fencing (in meters)
A44: Output | B44: Total Wiremesh fencing Cost (I) | C44: =C43*Loop!D49 -> 0
A45: 14 | B45: Length of Bridge Plate (in meters)
A46: Output | B46: Total Bridge Plate Cost (J) | C46: =C45*Loop!D50 -> 0
A47: 15 | B47: Enter number of Safety Gate | C47: 1
A48: Output | B48: Cost Price of Safety Gate | C48: ='Quote Master'!$H$136*C47 -> 60000
B49: Total Loop Cost (A+B+C+D+E+F+G+H+I+J) | C49: =C13+C16+C19+C24+C25+C29+C33+C41+C44+C46+C48 -> 11522828
B50: Recommended Sale Price | C50: =C49/C1 -> 17070856
B53: Main Inducts
A54: 16 | B54: Enter the Total Number of Inducts in the System | C54: 0
A55: 17 | B55: Select the Width of Induct Conveyors | C55: 1000
A56: 18 | B56: Enter number of Angle Merge Conveyors per Induct | C56: 1
A57: 19 | B57: Enter Number of Short Buffer Conveyors per Induct | C57: 1
A58: 20 | B58: Enter Number of Spacing Conveyors per Induct | C58: 1
A59: 21 | B59: Enter Number of Single Operator Loading Conveyor | C59: 1
A60: 22 | B60: Enter Number of Double Operator Loading Conveyor | C60: 1
A61: 23 | B61: Enter Number of Receiving Conveyor | C61: 1
B63: Top loader induct
A64: 24 | B64: Enter the Total Number of Inducts in the System | C64: 1
A65: 25 | B65: Select the Width of Induct Conveyors | C65: 1000
A66: 26 | B66: Enter number of Angle Merge Conveyors per Induct | C66: 0
A67: 27 | B67: Enter Number of Short Buffer Conveyors per Induct | C67: 1
A68: 28 | B68: Enter Number of Spacing Conveyors per Induct | C68: 1
A69: 29 | B69: Enter Number of Top Loaders per Induct | C69: 1
A70: 30 | B70: Enter Number of Single Operator Loading Conveyor | C70: 1
A71: 31 | B71: Enter Number of Double Operator Loading Conveyor | C71: 1
A72: 32 | B72: Enter Number of Receiving Conveyor | C72: 1
B74: Special Inducts
A75: 33 | B75: Enter the Total Number of Inducts in the System | C75: 0
A76: 34 | B76: Select the Width of Induct Conveyors | C76: 1000
A77: 35 | B77: Enter number of Angle Merge Conveyors per Induct | C77: 0
A78: 36 | B78: Enter Number of Short Buffer Conveyors per Induct | C78: 0
A79: 37 | B79: Enter Number of Spacing Conveyors per Induct | C79: 0
A80: 38 | B80: Enter Number of Single Operator Loading Conveyor | C80: 0
A81: 39 | B81: Enter Number of Double Operator Loading Conveyor | C81: 0
A82: 40 | B82: Enter Number of Receiving Conveyor | C82: 0
D86: Unit Price | E86: Total Price | F86: Length (for Cable Tray and Leg Calculation) | G86: Row | H86: Column
A87: Output | B87: Total Number of Angle Merge Conveyors | C87: =C54*C56+C75*C77+C66*C64 -> 0 | D87: {=INDEX(Inducts!D3:E4,'Linear CBS'!G87,'Linear CBS'!H87)} -> 148710.38 | E87: =C87*D87 -> 0 | F87: {=INDEX(Inducts!F3:F4,'Linear CBS'!G87,1)*C87} -> 0 | G87: =MATCH($C$55,Inducts!C3:C4,0) -> 2 | H87: =MATCH(C42,Inducts!D2:E2,0) -> 2
A88: Output | B88: Total Number of Short Buffer Conveyors | C88: =C54*C57+C75*C78+C67*C64 -> 1 | D88: {=INDEX(Inducts!D7:E8,'Linear CBS'!G88,'Linear CBS'!H88)} -> 103379.79 | E88: =C88*D88 -> 103379.79 | F88: {=INDEX(Inducts!F7:F8,'Linear CBS'!G88,1)*C88} -> 1 | G88: =G87 -> 2 | H88: =H87 -> 2
A89: Output | B89: Total Number of Spacing Conveyors | C89: =C54*C58+C75*C79+C68*C64 -> 1 | D89: {=INDEX(Inducts!D11:E12,'Linear CBS'!G89,'Linear CBS'!H89)} -> 108948.54 | E89: =C89*D89 -> 108948.54 | F89: {=INDEX(Inducts!F11:F12,'Linear CBS'!G89,1)*C89} -> 1.5 | G89: =G88 -> 2 | H89: =H88 -> 2
A90: Output | B90: Total Number of Single Operator Loading Conveyor | C90: =C54*C59+C75*C80+C70*C64 -> 1 | D90: {=INDEX(Inducts!D15:E16,'Linear CBS'!G90,'Linear CBS'!H90)} -> 163903.16 | E90: =C90*D90 -> 163903.16 | F90: {=INDEX(Inducts!F15:F16,'Linear CBS'!G90,1)*C90} -> 1.5 | G90: =G89 -> 2 | H90: =H89 -> 2
A91: Output | B91: Total Number of Double Operator Loading Conveyor | C91: =C54*C60+C75*C81+C71*C64 -> 1 | D91: {=INDEX(Inducts!D19:E20,'Linear CBS'!G91,'Linear CBS'!H91)} -> 290812.5 | E91: =C91*D91 -> 290812.5 | F91: {=INDEX(Inducts!F19:F20,'Linear CBS'!G91,1)*C91} -> 5 | G91: =G90 -> 2 | H91: =H90 -> 2
A92: Output | B92: Total Number of Receiving Conveyor | C92: =C54*C61+C75*C82+C72*C64 -> 1 | D92: {=INDEX(Inducts!D23:E24,'Linear CBS'!G92,'Linear CBS'!H92)} -> 290812.5 | E92: =C92*D92 -> 290812.5 | F92: {=INDEX(Inducts!F23:F24,'Linear CBS'!G92,1)*C92} -> 5 | G92: =G91 -> 2 | H92: =H91 -> 2
A93: Output | B93: Total Number of Top Loader conveyors | C93: =C69*C64 -> 1 | D93: {=INDEX(Inducts!D27:E27,'Linear CBS'!G93,'Linear CBS'!H93)} -> #REF! | E93: =C93*D93 -> #REF! | F93: {=INDEX(Inducts!F24:F27,'Linear CBS'!G93,1)*C93} -> 3.3 | G93: =MATCH($C$65,Inducts!C15:C16,0) -> 2 | H93: =H92 -> 2
A94: Output | D94: Total | E94: =SUM(E87:E93) -> #REF! | F94: =SUM(F87:F93) -> 17.3
B95: Total Cost of Induct Conveyors | C95: =E94 -> #REF!
A96: Output | B96: Total Cost of Cable Tray and Legs | C96: =F94*Inducts!D30 -> 248687.5
A97: Output | B97: Total Cost of Over Shoot Assembly | C97: =(C54+C75+C64)*Inducts!D31 -> 16100
A98: Output | B98: Total Cost Control Panel | C98: =(C54+C64+C75)*Inducts!D29 -> 221760
A99: Output | B99: Total Inducts Cost | C99: =SUM(C96:C98) -> 486547.5
A100: Output | B100: Total Inductions | C100: =+(C54+C64+C75) -> 1
B101: Required Hand Barcode scanner for Semi-Auto mode | C101: YES
B102: Hand Barcode Scanner for semi-auto mode | C102: =+IF(C101="Yes",(C100*'Quote Master'!$I$72),0) -> 30000
B103: Recommended Sale Price | C103: =(C99/C1)+C102 -> 750811.11
B104: Enter Number of Weighing Conveyors(Total) | C104: 0
B105: Select Weighing Model | C105: Bizerba WM CWL
B106: Weighing Conveyor Price | C106: =+VLOOKUP(C105,'Weighing Conveyors'!$D$1:$L$8,9,FALSE)*(C104) -> 0
B108: Total Recommended Sale Price (Sorter + Inducts) | C108: =C103+C50+C106 -> 17821667

Sheet Budgetary Costing
B1: Region | C1: Middle East | H1: Sales Factor | I1: 0.6
B2: Item | C2: Qty | D2: UOM | E2: Set | F2: Unit Price | G2: Total Price
B3: NEO Bots | C3: 0 | D3: Nos | E3: 1 | F3: =HLOOKUP($C$1,'NEO New rate data'!$C$2:$E$3,2,0) -> 1396551.7 | G3: =F3*E3*C3 -> 0
B4: Spare battery | C4: =ROUNDUP(C3/3,0) -> 0 | D4: Nos | E4: 1 | F4: =HLOOKUP($C$1,'NEO New rate data'!$C$2:$E$4,3,0) -> 89655.172 | G4: =F4*E4*C4 -> 0
B5: GTC Station | C5: 0 | D5: Nos | E5: 1 | F5: =HLOOKUP($C$1,'NEO New rate data'!$C$2:$E$5,4,0) -> 1370689.7 | G5: =F5*E5*C5 -> 0
B6: GTP Station | C6: 0 | D6: Nos | E6: 1 | F6: =HLOOKUP($C$1,'NEO New rate data'!$C$2:$E$6,5,0) -> 775862.07 | G6: =F6*E6*C6 -> 0 | L6: Partition
B7: Bin Position Cost | C7: 0 | D7: Nos | E7: 1 | F7: =HLOOKUP($C$1,'NEO New rate data'!$C$2:$E$7,6,0) -> 3666.6667 | G7: =F7*E7*C7 -> 0
A8: Bin Type | B8: Six Compartment Bin | C8: =C7 -> 0 | D8: Nos | E8: 1 | F8: =INDEX('NEO New rate data'!$C$9:$E$13,MATCH('Budgetary Costing'!B8,'NEO New rate data'!$B$9:$B$13,0),MATCH('Budgetary Costing'!C1,'NEO New rate data'!C2:E2,0)) -> 1437.5 | G8: =F8*E8*C8 -> 0
B9: Short Side Partition | C9: =VLOOKUP($B$8,'NEO New rate data'!$B$9:$H$13,6,0) -> 2 | D9: Nos | E9: 1 | F9: =HLOOKUP($C$1,'NEO New rate data'!$C$2:$E$14,13,0) -> 50 | G9: =F9*E9*C9*C7 -> 0
B10: Long Side Partition | C10: =VLOOKUP($B$8,'NEO New rate data'!$B$9:$H$13,7,0) -> 1 | D10: Nos | E10: 1 | F10: =HLOOKUP($C$1,'NEO New rate data'!$C$2:$E$15,14,0) -> 71.428571 | G10: =F10*E10*C10*C7 -> 0
B11: Charging Station | C11: 0 | D11: Set | E11: 1 | F11: =HLOOKUP($C$1,'NEO New rate data'!$C$2:$E$16,15,0) -> 926724.14 | G11: =F11*E11*C11 -> 0
B12: IT Server and IT Infra | C12: 1 | D12: Set | E12: 1 | F12: =HLOOKUP($C$1,'NEO New rate data'!$C$2:$E$17,16,0) -> 2672413.8 | G12: =F12*E12*C12 -> 2672413.8
B13: Mechanical and Electrical Infra | C13: 1 | D13: Set | E13: 1 | F13: =(SUM(G3:G12))*4% -> 106896.55 | G13: =F13*E13*C13 -> 106896.55
B14: WCS Cost | C14: 1 | D14: Set | E14: 1 | F14: =HLOOKUP($C$1,'NEO New rate data'!$C$2:$E$19,18,0) -> 2500000 | G14: =F14*E14*C14 -> 2500000
B15: WCS Annual License | C15: 1 | D15: Set | E15: 1 | F15: =HLOOKUP($C$1,'NEO New rate data'!$C$2:$E$20,19,0) -> 250000 | G15: =F15*E15*C15 -> 250000
B16: IT Integration | C16: 1 | D16: Set | E16: 1 | G16: =F16*E16*C16 -> 0 | H16: As per the Scope of Customization and Integration effort
B17: Safety Architecture | C17: 1 | D17: Set | E17: 1 | F17: 400000 | G17: =(F17/I1)*E17*C17 -> 666666.67
B18: Packing and Forwarding | C18: 1 | D18: Set | E18: 1 | F18: =(HLOOKUP($C$1,'NEO New rate data'!$C$2:$E$23,22,0))*SUM(G3:G13) -> 138965.52 | G18: =F18*E18*C18 -> 138965.52
B19: Freight | C19: 1 | D19: Set | E19: 1 | G19: =F19*E19*C19 -> 0 | H19: As per Site Location and BOM
B20: Installation and Commissioning | C20: 1 | D20: Set | E20: 1 | F20: =(HLOOKUP($C$1,'NEO New rate data'!$C$2:$E$25,24,0))*(G3+G4+G5+G6+G7+G11+G12+G13) -> 0 | G20: =F20*E20*C20 -> 0 | H20: To be estimated as per Country/State and Size of the System
B21: Project Management | C21: 1 | D21: Set | E21: 1 | F21: =(HLOOKUP($C$1,'NEO New rate data'!$C$2:$E$22,21,0))*SUM(G3:G20) -> 190048.28 | G21: =F21*E21*C21 -> 190048.28
B22: Grand Total | G22: =SUM(G3:G21) -> 6524990.8

Sheet NEO New rate data
A1: NEO New Rate Card | C1: Quote Price (INR)
A2: S.No | B2: Item | C2: India | D2: ANZ and EU | E2: Middle East
A3: 1 | B3: NEO Bot | C3: 1350000 | D3: 1620000 | E3: 1396551.7
A4: 2 | B4: Spare battery | C4: 86666.667 | D4: 104000 | E4: 89655.172 | F4: Generally Quoted 1 for every 3 Bots
A5: 3 | B5: GTC Station | C5: 1325000 | D5: 1590000 | E5: 1370689.7 | F5: This is Standard GTC Station including Bin Conveyors + Bin Scanners + Touch Screen Operator Panel + Fixed Mounted Scanner for SKU Scanning + Canopy
A6: 4 | B6: GTP Station | C6: 750000 | D6: 900000 | E6: 775862.07 | F6: This is Standard GTP Station including Touch Screen Operator Panel + Fixed Mounted Scanner for SKU Scanning + Canopy
A7: 5 | B7: Bin Position Cost | C7: 3473.6842 | D7: 3882.3529 | E7: 3666.6667 | F7: Includes the Cost of Racking + Teeth Rack + Tracks
A8: 6 | B8: Plastic Bin Cost | G8: Sort side partition | H8: Long side partition
A9: a | B9: Single Compartment Bin | C9: 1017.6471 | D9: 1081.25 | E9: 1081.25 | G9: 0 | H9: 0 | I9: Single Compartment Bin
A10: b | B10: Two Compartment Bin | C10: 1122.3529 | D10: 1192.5 | E10: 1192.5 | G10: 1 | H10: 0 | I10: Two Compartment Bin
A11: c | B11: Three Compartment Bin | C11: 1227.0588 | D11: 1303.75 | E11: 1303.75 | G11: 3 | H11: 0 | I11: Three Compartment Bin
A12: d | B12: Four Compartment Bin | C12: 1247.0588 | D12: 1325 | E12: 1325 | G12: 1 | H12: 1 | I12: Four Compartment Bin
A13: e | B13: Six Compartment Bin | C13: 1352.9412 | D13: 1437.5 | E13: 1437.5 | G13: 2 | H13: 1 | I13: Six Compartment Bin
A14: 7 | B14: Short Side Partition | C14: 43.75 | D14: 50 | E14: 50
A15: 8 | B15: Long Side Partition | C15: 62.5 | D15: 71.428571 | E15: 71.428571
A16: 9 | B16: Charging Station | C16: 895833.33 | D16: 1075000 | E16: 926724.14
A17: 10 | B17: IT Server and IT Infra | C17: 2583333.3 | D17: 3100000 | E17: 2672413.8
A18: 11 | B18: Mechanical and Electrical Infra (% of the equipment Sales Value) | C18: 0.04 | D18: 0.04 | E18: 0.04 | F18: Including - Fencing Mechanical + Electrical - Power Distribution Panels - Control Panels and Field Devices - Distribution Panels and Field Devices - Misc Consumables
A19: 12 | B19: WCS Cost | C19: 1500000 | D19: 2500000 | E19: 2500000 | F19: WCS License and Setup up cost
A20: 13 | B20: WCS Annual License | D20: =D19*0.1 -> 250000 | E20: =E19*0.1 -> 250000 | F20: Annual License Renewal
A21: 14 | B21: IT Integration | C21: Variable | D21: Variable | E21: Variable | F21: As per the Scope of Customization and Integration effort
A22: 15 | B22: Project Management (of Equipment Price) | C22: 0.025 | D22: 0.03 | E22: 0.03
A23: 16 | B23: Packing and Forwarding (of Equipment Price) | C23: 0.02 | D23: 0.05 | E23: 0.05
A24: 17 | B24: Freight | C24: Variable | D24: Variable | E24: Variable | F24: As per Site Location and BOM
A25: 18 | B25: Installation and Commissioning (of Equipment Price excluding Bins) | C25: 0.05 | D25: 0 | E25: 0 | F25: To be estimated as per Country/State and Size of the System

Sheet Linear
C1: Specs | D1: Unit Price | E1: Belt/motor | G1: YES
B2: Sorter track | C2: Regular | D2: ='Final Rate card'!$C$7 -> 32500 | E2: 40 | G2: No
C3: Heavy Duty | D3: ='Final Rate card'!$C$8 -> 36500 | E3: 30
B4: Curves | C4: 360 Deg Curves | D4: ='Final Rate card'!$C$9 -> 76500 | E4: Cost is for 360deg curve /per count
B7: Carrier | C7: Regular | D7: ='Final Rate card'!$C$2+'Final Rate card'!$C$3 -> 39123
C8: Heavy Duty | D8: ='Final Rate card'!$C$2+'Final Rate card'!$C$4 -> 41500
B10: Leg Cost | C10: 1.7 meter height | D10: ='Final Rate card'!$C$10 -> 8000
B12: Linear Motor Drive Set | C12: LIM | D12: 250000
C13: LSM | D13: ='Final Rate card'!C5 -> 681000
B15: Positioning & Centering | D15: 333987.56
B16: Sorter Loop Control | C16: Omron | D16: ='Final Rate card'!$C$11 -> 250000
C17: Siemens | D17: ='Final Rate card'!$C$13 -> 600000
B19: PLC Platform | C19: Omron | D19: ='Final Rate card'!$C$12 -> 1400000
C20: Siemens | D20: ='Final Rate card'!$C$14 -> 3700000
B22: Server Setup | C22: HAA-Falcon Standard | D22: =(764700+186000)*1.12 -> 1064784
C23: HAA-Amazon Standard | D23: =1900000*1.12 -> 2128000
B25: Barcode Scanning Tunnel | C25: ICR-890 8K | D25: =1527639*1.1 -> 1680402.9
C26: ICR-890 12K | D26: =+(1527639*1.1)+200000 -> 1880402.9
C27: ICR890 12K 3 Camera- 3/5 Side Per Scan Tunnel | D27: 3200000
C28: ICR890 12K 5 Camera- 5 Side Per Scan Tunnel | D28: ='Quote Master'!$H$109 -> 5800000
C29: Cognex 3 Camera- Top scan without Image Capturing Per Scan Tunnel | D29: 110000
C30: COGENAX Top side scanning (DM3816X) | D30: ='Quote Master'!$H$110 -> 424771
C31: Cognex 3 Camera- Top scan with Image Capturing Per Scan Tunnel | D31: 1350000
B32: VMS | C32: VMS 4200 | D32: =750000*1.1 -> 825000
C33: VMS5200 | D33: =950000*1.1 -> 1045000
C34: COGNEX VMS (3D- A1000) | D34: ='Quote Master'!$H$113 -> 351032
B38: Safety Net | C38: Per meter | D38: =7656*1.15 -> 8804.4
B39: Fencing | C39: Per meter | D39: =6590*1.15 -> 7578.5
B40: Bridge Plate | C40: Per meter | D40: =3685*1.15 -> 4237.75

Sheet Final Rate card
A1: S.NO | B1: Item | C1: Final Rate card | D1: Specs/Remarks
A2: 1 | B2: Chasis | C2: 15900 | D2: 4 X Blickle 2 X Bharat LSM Magnet Wheel Mounting for Blickel
A3: 2 | B3: Carrier- Regular | C3: 23223 | D3: Bellow Added Sheet Thickness Increased Node Plates are here (Omron or Siemens) Includes CBS Power plate with Meanwell DC converter and Schneider MCB Includes Connector & Communication cable Includes Carrier Position sensor and reflector unit Includes Harness Field | F3: =C2+C3 -> 39123
A4: 3 | B4: Carrier- Heavy Duty | C4: 25600 | D4: Bellow Added Sheet Thickness Increased Node Plates are here (Omron or Siemens) Includes CBS Power plate with Meanwell DC converter and Schneider MCB Includes Connector & Communication cable Includes Carrier Position sensor and reflector unit Includes Harness Field
A5: 4 | B5: Drive Unit- Regular | C5: 681000 | D5: SEW LSM (Linear Magnetic Motor, Inverter, encoder, Braking Resistor, encoder cables, Line Filter, Keypad, Line Choke & Output Choke), Gap Filler and drive unit accessories - One Motor Set for 40 Carriers Includes Linear Sorter LSM motor Junction box Includes Sorter Drive (LSM) Panel Includes Drive Panel (LSM) Field Material
A6: 5 | B6: Drive Unit- Heavy Duty | C6: 681000 | D6: SEW LSM (Linear Magnetic Motor, Inverter, encoder, Braking Resistor, encoder cables, Line Filter, Keypad, Line Choke & Output Choke) -One Motor Set for 30 Carriers Includes Linear Sorter LSM motor Junction box Includes Sorter Drive (LSM) Panel Includes Drive Panel (LSM) Field Material
A7: 6 | B7: Straight Track (per Meter)- Regular | C7: 32500 | D7: Length to be considered from Plan View Bus Bar elements and Leaky Wave is here Includes Linear Current Collector Includes Insulated Conductor & Compact hanger Includes Hooters for CBS Includes SMPS Panel and its accessoriers and SMPS panel Field material Includes Barcode Sensor & Barcode Tape Includes Sorter Cable tray
A8: 7 | B8: Straight Track (per Meter)- Heavy Duty | C8: 36500 | D8: Length to be considered from Plan View Bus Bar elements and Leaky Wave is here Includes Linear Current Collector Includes Insulated Conductor & Compact hanger Includes Hooters for CBS Includes SMPS Panel and its accessoriers and SMPS panel Field material Includes Barcode Sensor & Barcode Tape Includes Sorter Cable tray
A9: 8 | B9: Curev Track (per Count) | C9: 76500 | D9: This cost is for 360 Degree Curve. Consider 8 Carriers on the curve length Includes Tail & Drive end unit and Tail end block
A10: 9 | B10: Legs (per Leg) | C10: 8000 | D10: Consider one Leg per 2.4 meters
A11: 10 | B11: Loop Control- Omron | C11: 250000 | D11: Includes Speed calculation, pitch sensor & monitoring sensor (all three types) Includes Linear Sorter Field material
A12: 11 | B12: Main Control- Omron | C12: 1400000 | D12: Includes Control Panel, Remote panel, wifi Panel, Power distribution panel, Junction Box, Safety Relay/ Controller panel and field material for the same. Includes Sorter Scada Field material Includes Stickers, Panel stand and consumables
A13: 12 | B13: Loop Control- Siemens | C13: 600000 | D13: Includes Speed calculation, pitch sensor & monitoring sensor (all three types) Includes Linear Sorter Field material
A14: 13 | B14: Main Control- Siemens | C14: 3700000 | D14: Includes Control Panel, Remote panel, wifi Panel, Power distribution panel, Junction Box, Safety Relay/ Controller panel, Sorter Safety speed detection Panel and field material for the same. Includes Sorter Scada Field material Includes Stickers, Panel stand and consumables

Sheet Arm Sorter
A1: S.No. | B1: Description | C1: Quantity | D1: UOM | E1: Unit Price | F1: Total | G1: Sales Factor | H1: ='Overall Costing'!$M$1 -> 0.675
A2: 1 | B2: Sorter running length | C2: =(4.14+4.5+4.5+4.5+4.5+4.5+5.46)*2 -> 64.2 | D2: Meters | E2: =100000*2 -> 200000 | F2: =E2*C2 -> 12840000
A3: 2 | B3: Arm XL | C3: =7*2 -> 14 | D3: Nos | E3: =VLOOKUP(B3,'Quote Master'!$C$54:$I$55,7,0) -> 175000 | F3: =E3*C3 -> 2450000
A4: 3 | B4: ICR 890 12K | D4: Nos | E4: =VLOOKUP(B4,'Quote Master'!$C$107:$I$112,7,0) -> 3134004.8 | F4: =E4*C4 -> 0
A5: 4 | B5: VMS 5200 | D5: Nos | E5: =VLOOKUP(B5,'Quote Master'!$C$107:$I$112,7,0) -> 1741666.7 | F5: =E5*C5 -> 0
A6: 5 | B6: PLC based control | C6: =1*2 -> 2 | D6: Nos | E6: =+'Quote Master'!I102 -> 800000 | F6: =+E6*C6 -> 1600000
A7: 6 | B7: Server PC | D7: Nos | E7: =+'Quote Master'!I106 -> 250000 | F7: =E7*C7 -> 0
A8: 7 | B8: HAA Server | D8: Nos | E8: =+'Quote Master'!I103 -> 2121000 | F8: =E8*C8 -> 0
E9: Total | F9: =SUM(F2:F8) -> 16890000 | G9: =F9/'Overall Costing'!M5 -> 179680.85
B11: Induction line
A12: 8 | B12: Enter the Total Number of Inducts in the System | C12: 0
A13: 9 | B13: Width of Induct Conveyors | C13: 800 mm
A14: 10 | B14: Enter number of Launchpad conveyors | C14: 0
A15: 11 | B15: Enter Length of Launchpad conveyor(mm) | C15: 0
A16: 12 | B16: Enter number of Angle Merge Conveyors per Induct | C16: 0
A17: 13 | B17: Enter Number of Short Buffer Conveyors per Induct | C17: 0
A18: 14 | B18: Enter Number of Spacing Conveyors per Induct | C18: 0
A19: 15 | B19: Enter Number of Receiving Conveyor | C19: 0
A20: 16 | B20: Enter length of Receiving Conveyor(mm) | C20: 0
A22: Output | D22: Unit Price | E22: Total Price | F22: Length (for Cable Tray and Leg Calculation) | G22: Row | H22: Column
A23: Output | B23: Total Number of Angle Merge Conveyors | C23: =+C12*C16 -> 0 | D23: {=INDEX('Induct line for Arm'!D3:D4,'Arm Sorter'!G23,'Arm Sorter'!H23)} -> 148710.38 | E23: =C23*D23 -> 0 | F23: {=INDEX('Induct line for Arm'!F3:F4,G23,1)*C23} -> 0 | G23: =MATCH($C$13,'Induct line for Arm'!C3:C4,0) -> 2 | H23: 1
A24: Output | B24: Total Number of Short Buffer Conveyors | C24: =+C17*C12 -> 0 | D24: {=INDEX('Induct line for Arm'!D5:D6,'Arm Sorter'!G24,'Arm Sorter'!H24)} -> 125379.79 | E24: =C24*D24 -> 0 | F24: {=INDEX('Induct line for Arm'!F5:F6,G24,1)*C24} -> 0 | G24: =G23 -> 2 | H24: 1
A25: Output | B25: Total Number of Spacing Conveyors | C25: =+C18*C12 -> 0 | D25: {=INDEX('Induct line for Arm'!D7:D8,'Arm Sorter'!G25,'Arm Sorter'!H25)} -> 130948.54 | E25: =C25*D25 -> 0 | F25: {=INDEX('Induct line for Arm'!F7:F8,G25,1)*C25} -> 0 | G25: =G24 -> 2 | H25: 1
A26: Output | B26: Total Number of Receiving Conveyors | C26: =C12*C19 -> 0 | D26: =+((C20/1000)*'Quote Master'!$I$4)+'Quote Master'!$I$5 -> 180740.74 | E26: =C26*D26*0.6 -> 0 | F26: 0 | G26: =G25 -> 2 | H26: 1
A27: Output | B27: Total Number of Launchpad Conveyors | C27: =+C12*C14 -> 0 | D27: =+((C15/1000)*'Quote Master'!$I$4)+'Quote Master'!$I$5 -> 180740.74 | E27: =C27*D27*0.6 -> 0 | F27: 0 | G27: =G26 -> 2 | H27: 1
D28: Total | E28: =SUM(E23:E27) -> 0 | F28: =SUM(F23:F27) -> 0
A29: Output | B29: Total Cost of Induct Conveyors | C29: =E28 -> 0
A30: Output | B30: Total Cost of Cable Tray and Legs | C30: =F28*'Induct line for Arm'!D11 -> 0
A31: Output | B31: Total Cost Control Panel | C31: =+C12*'Induct line for Arm'!D10 -> 0
A32: Output | B32: Total Inducts Cost | C32: =SUM(C29:C31) -> 0
B33: Total Inductions | C33: =+(C12) -> 0
B34: Required Hand Barcode scanner for Semi-Auto mode | C34: Yes
B35: Hand Barcode Scanner for semi-auto mode | C35: =+IF(C34="Yes",(C33*'Quote Master'!$I$72),0) -> 0
B36: Recommended Sale Price | C36: =(C32/H1)+C35 -> 0
B37: Enter Number of Weighing Conveyors(Total) | C37: 0
B38: Select Weighing Model | C38: Bizerba WM CWL
B39: Weighing Conveyor Price | C39: =+VLOOKUP(C38,'Weighing Conveyors'!$D$1:$L$8,9,FALSE)*C37 -> 0
B42: Total Sale Price for Arm Sorter | C42: =+C36+F9+C39 -> 16890000

Sheet Swedi sorter
A1: S.No. | B1: Description | C1: Quantity | D1: UOM | E1: Unit Price | F1: Total | G1: Sales Factor | H1: ='Overall Costing'!$M$1 -> 0.675
A2: 1 | B2: Swedi | C2: 0 | D2: Nos | E2: 0 | F2: =(E2/$H$1)*C2 -> 0 | G2: Swedi Costing and Calculation sheet
A3: 2 | B3: ICR 890 8K | C3: 0 | D3: Nos | E3: =VLOOKUP(B3,'Quote Master'!$C$107:$I$112,7,0) -> 2800671.5 | F3: =E3*C3 -> 0
A4: 3 | B4: VMS 4200 | C4: 0 | D4: Nos | E4: =VLOOKUP(B4,'Quote Master'!$C$107:$I$112,7,0) -> 1375000 | F4: =E4*C4 -> 0
A5: 4 | B5: PLC Based contoller | D5: Nos | E5: =+'Quote Master'!I102 -> 800000 | F5: =+E5*C5 -> 0
A6: 5 | B6: Server PC | D6: Nos | E6: =+'Quote Master'!I106 -> 250000 | F6: =E6*C6 -> 0
A7: 6 | B7: HAA Server | D7: Nos | E7: =+'Quote Master'!I103 -> 2121000 | F7: =E7*C7 -> 0
B8: Field and Wiring | F8: =F2*'Overall Costing'!$M$3 -> 0
A9: 7 | E9: Total | F9: =SUM(F2:F8) -> 0
A11: 8 | B11: Enter the Total Number of Inducts in the System | C11: 0
A12: 9 | B12: Width of Induct Conveyors | C12: 800 mm
A13: 10 | B13: Enter number of Launchpad conveyors | C13: 1
A14: 11 | B14: Enter Length of Launchpad conveyor(mm) | C14: 1000
A15: 12 | B15: Enter number of Angle Merge Conveyors per Induct | C15: 1
A16: 13 | B16: Enter Number of Short Buffer Conveyors per Induct | C16: 1
A17: 14 | B17: Enter Number of Spacing Conveyors per Induct | C17: 1
A18: 15 | B18: Enter Number of Receiving Conveyor | C18: 1
A19: 16 | B19: Enter length of Receiving Conveyor(mm) | C19: 2000
A20: 17 | B20: Enter Total Number of intermediate Conveyors | C20: 0
A21: 18 | B21: Enter length of intermediate Conveyor(mm) | C21: 2000
A24: Output | D24: Unit Price | E24: Total Price | F24: Length (for Cable Tray and Leg Calculation) | G24: Row | H24: Column
A25: Output | B25: Total Number of Angle Merge Conveyors | C25: =+C11*C15 -> 0 | D25: {=INDEX('Induct Line for Swedi'!D3:E5,'Swedi sorter'!G25,'Swedi sorter'!H25)} -> 148710.38 | E25: =C25*D25 -> 0 | F25: {=INDEX('Induct Line for Swedi'!F3:F5,G25,1)*C25} -> 0 | G25: =MATCH($C$12,'Induct Line for Swedi'!C3:C5,0) -> 2 | H25: 1
A26: Output | B26: Total Number of Short Buffer Conveyors | C26: =+C16*C11 -> 0 | D26: {=INDEX('Induct Line for Swedi'!D6:D8,'Swedi sorter'!G26,'Swedi sorter'!H26)} -> 125379.79 | E26: =C26*D26 -> 0 | F26: {=INDEX('Induct Line for Swedi'!F6:F8,G26,1)*C26} -> 0 | G26: =G25 -> 2 | H26: 1
A27: Output | B27: Total Number of Spacing Conveyors | C27: =+C17*C11 -> 0 | D27: {=INDEX('Induct Line for Swedi'!D9:D11,G27,H27)} -> 130948.54 | E27: =C27*D27 -> 0 | F27: {=INDEX('Induct Line for Swedi'!F9:F11,G27,1)*C27} -> 0 | G27: =G26 -> 2 | H27: 1
A28: Output | B28: Total Number of Receiving Conveyors | C28: =C11*C18 -> 0 | D28: =+((C19/1000)*'Quote Master'!$I$4)+'Quote Master'!$I$5 -> 217777.78 | E28: =(C28*D28)*0.6 -> 0 | F28: 0 | G28: =G27 -> 2 | H28: 1
A29: Output | B29: Total Number of Launchpad Conveyors | C29: =+C11*C13 -> 0 | D29: =+((C14/1000)*'Quote Master'!$I$4)+'Quote Master'!$I$5 -> 199259.26 | E29: =C29*D29*0.6 -> 0 | F29: 0 | G29: =G28 -> 2 | H29: 1
A30: Output | B30: Total Number of Intermediate Conveyors | C30: =+C20 -> 0 | D30: =+((C21/1000)*'Quote Master'!$I$4)+'Quote Master'!$I$5 -> 217777.78 | E30: =C30*D30*0.6 -> 0 | F30: 0 | G30: =G29 -> 2 | H30: 1
D31: Total | E31: =SUM(E25:E29) -> 0 | F31: =SUM(F25:F29) -> 0
A32: Output | B32: Total Cost of Induct Conveyors | C32: =E31 -> 0
A33: Output | B33: Total Cost of Cable Tray and Legs | C33: =F31*'Induct Line for Swedi'!D14 -> 0
A34: Output | B34: Total Cost Control Panel | C34: =+C11*'Induct Line for Swedi'!D13 -> 0
A35: Output | B35: Total Inducts Cost | C35: =SUM(C32:C34) -> 0
B36: Total Inductions | C36: =+(C11) -> 0
B37: Required Hand Barcode scanner for Semi-Auto mode | C37: Yes
B38: Hand Barcode Scanner for semi-auto mode | C38: =+IF(C37="Yes",(C36*'Quote Master'!$I$72),0) -> 0
B39: Recommended Sale Price | C39: =(C35/H1)+C38 -> 0
B40: Enter Number of Weighing Conveyors(Total) | C40: 0
B41: Select Weighing Model | C41: Bizerba WM CWL
B42: Weighing Conveyor Price | C42: =+VLOOKUP(C41,'Weighing Conveyors'!$D$1:$L$8,9,FALSE)*C40 -> 0
B44: Total Sale Price for Swedi Sorter with Inducts | C44: =+C39+F9+C42 -> 0

Sheet Conveyors
P1: Sales Factor | Q1: ='Overall Costing'!M1 -> 0.675
A2: S No. | B2: Name | C2: ANGLE | D2: EL_1 | E2: EL_2 | F2: Conveyor Length (mm) | G2: Conveyor Length (m) | H2: Conveyor width (mm) | I2: Set | J2: Unit Price | K2: Drive Price | L2: MOTOR_POWER (KW) | M2: Base Module (BM) HM+TM+DM | N2: Motor Price(Inculding {Pannel, VFD}) | O2: Cost/ mtr | P2: Total Cost Price | Q2: Selling Price | R2: Family | S2: Price in Euro
A3: 1 | B3: PVC Belt Conveyor(Bulk loading) | C3: 0 | D3: 4050 | E3: 4050 | F3: 5760 | G3: =F3/1000 -> 5.76 | H3: 1210 | I3: 1 | L3: =IF(C3<=0,4,5.5) -> 4 | M3: =VLOOKUP(H3,'Conveyor Costing'!$B$3:$F$7,5,0)*3 -> 381531.85 | N3: =VLOOKUP(L3,'Conveyor Costing'!$T$24:$AB$38,9,0) -> 143651.5 | O3: =VLOOKUP(H3,'Conveyor Costing'!$B$3:$G$7,6,0)*3 -> 55400.098 | P3: =IF(G3<2.4,((M3+((0)*O3))+N3)*I3,((M3+((G3-2.4)*O3))+N3)*I3) -> 711327.68 | Q3: =P3/$Q$1 -> 1053818.8 | R3: Infeed | S3: =Q3/'Overall Costing'!$M$5 -> 11210.838
A4: 2 | B4: PVC Belt Conveyor(Bulk loading) | C4: 0 | D4: 550 | E4: 550 | F4: 5760 | G4: =F4/1000 -> 5.76 | H4: 1210 | I4: 1 | L4: =IF(C4<=0,4,5.5) -> 4 | M4: =VLOOKUP(H4,'Conveyor Costing'!$B$3:$F$7,5,0)*3 -> 381531.85 | N4: =VLOOKUP(L4,'Conveyor Costing'!$T$24:$AB$38,9,0) -> 143651.5 | O4: =VLOOKUP(H4,'Conveyor Costing'!$B$3:$G$7,6,0)*3 -> 55400.098 | P4: =IF(G4<2.4,((M4+((0)*O4))+N4)*I4,((M4+((G4-2.4)*O4))+N4)*I4) -> 711327.68 | Q4: =P4/$Q$1 -> 1053818.8 | R4: Infeed | S4: =Q4/'Overall Costing'!$M$5 -> 11210.838
A5: 3 | B5: PVC Belt Conveyor | C5: 14.3 | D5: 3548 | E5: 5180 | F5: 6440 | G5: =F5/1000 -> 6.44 | H5: 1210 | I5: 1 | L5: =IF(C5<=0,4,5.5) -> 5.5 | M5: =VLOOKUP(H5,'Conveyor Costing'!$B$3:$F$7,5,0)*2 -> 254354.57 | N5: =VLOOKUP(L5,'Conveyor Costing'!$T$24:$AB$38,9,0) -> 169290 | O5: =VLOOKUP(H5,'Conveyor Costing'!$B$3:$G$7,6,0)*2 -> 36933.399 | P5: =IF(G5<2.4,((M5+((0)*O5))+N5)*I5,((M5+((G5-2.4)*O5))+N5)*I5) -> 572855.5 | Q5: =P5/$Q$1 -> 848674.81 | R5: Infeed | S5: =Q5/'Overall Costing'!$M$5 -> 9028.4554
A6: 4 | B6: PVC Belt Conveyor | C6: 0 | D6: 550 | E6: 550 | F6: 5760 | G6: =F6/1000 -> 5.76 | H6: 1210 | I6: 1 | L6: =IF(C6<=0,4,5.5) -> 4 | M6: =VLOOKUP(H6,'Conveyor Costing'!$B$3:$F$7,5,0)*2 -> 254354.57 | N6: =VLOOKUP(L6,'Conveyor Costing'!$T$24:$AB$38,9,0) -> 143651.5 | O6: =VLOOKUP(H6,'Conveyor Costing'!$B$3:$G$7,6,0)*2 -> 36933.399 | P6: =IF(G6<2.4,((M6+((0)*O6))+N6)*I6,((M6+((G6-2.4)*O6))+N6)*I6) -> 522102.29 | Q6: =P6/$Q$1 -> 773484.87 | R6: Infeed | S6: =Q6/'Overall Costing'!$M$5 -> 8228.5624
A7: 5 | B7: PVC Belt Conveyor | C7: 14.8 | D7: 2350 | E7: 4433 | F7: 8000 | G7: =F7/1000 -> 8 | H7: 1210 | I7: 1 | L7: 7.5 | M7: =VLOOKUP(H7,'Conveyor Costing'!$B$3:$F$7,5,0)*2 -> 254354.57 | N7: =VLOOKUP(L7,'Conveyor Costing'!$T$24:$AB$38,9,0) -> 249400 | O7: =VLOOKUP(H7,'Conveyor Costing'!$B$3:$G$7,6,0)*2 -> 36933.399 | P7: =IF(G7<2.4,((M7+((0)*O7))+N7)*I7,((M7+((G7-2.4)*O7))+N7)*I7) -> 710581.6 | Q7: =P7/$Q$1 -> 1052713.5 | R7: Infeed | S7: =Q7/'Overall Costing'!$M$5 -> 11199.08
A8: 6 | B8: PVC Belt Conveyor | C8: 0 | D8: 2452 | E8: 2452 | F8: 2000 | G8: =F8/1000 -> 2 | H8: 1210 | I8: 1 | L8: =IF(C8<=0,4,5.5) -> 4 | M8: =VLOOKUP(H8,'Conveyor Costing'!$B$3:$F$7,5,0)*2 -> 254354.57 | N8: =VLOOKUP(L8,'Conveyor Costing'!$T$24:$AB$38,9,0) -> 143651.5 | O8: =VLOOKUP(H8,'Conveyor Costing'!$B$3:$G$7,6,0)*2 -> 36933.399 | P8: =IF(G8<2.4,((M8+((0)*O8))+N8)*I8,((M8+((G8-2.4)*O8))+N8)*I8) -> 398006.07 | Q8: =P8/$Q$1 -> 589638.62 | R8: Infeed | S8: =Q8/'Overall Costing'!$M$5 -> 6272.7512
A9: 7 | B9: PVC Belt Conveyor | C9: 14.8 | D9: 448 | E9: 2532 | F9: 8000 | G9: =F9/1000 -> 8 | H9: 1210 | I9: 1 | L9: 7.5 | M9: =VLOOKUP(H9,'Conveyor Costing'!$B$3:$F$7,5,0)*2 -> 254354.57 | N9: =VLOOKUP(L9,'Conveyor Costing'!$T$24:$AB$38,9,0) -> 249400 | O9: =VLOOKUP(H9,'Conveyor Costing'!$B$3:$G$7,6,0)*2 -> 36933.399 | P9: =IF(G9<2.4,((M9+((0)*O9))+N9)*I9,((M9+((G9-2.4)*O9))+N9)*I9) -> 710581.6 | Q9: =P9/$Q$1 -> 1052713.5 | R9: Infeed | S9: =Q9/'Overall Costing'!$M$5 -> 11199.08
A10: 8 | B10: PVC Belt Conveyor | C10: 0 | D10: 550 | E10: 550 | F10: 5760 | G10: =F10/1000 -> 5.76 | H10: 1210 | I10: 1 | L10: =IF(C10<=0,4,5.5) -> 4 | M10: =VLOOKUP(H10,'Conveyor Costing'!$B$3:$F$7,5,0)*2 -> 254354.57 | N10: =VLOOKUP(L10,'Conveyor Costing'!$T$24:$AB$38,9,0) -> 143651.5 | O10: =VLOOKUP(H10,'Conveyor Costing'!$B$3:$G$7,6,0)*2 -> 36933.399 | P10: =IF(G10<2.4,((M10+((0)*O10))+N10)*I10,((M10+((G10-2.4)*O10))+N10)*I10) -> 522102.29 | Q10: =P10/$Q$1 -> 773484.87 | R10: Infeed | S10: =Q10/'Overall Costing'!$M$5 -> 8228.5624
A11: 9 | B11: PVC Belt Conveyor | C11: 0 | D11: 3650 | E11: 3650 | F11: 3840 | G11: =F11/1000 -> 3.84 | H11: 1210 | I11: 1 | L11: =IF(C11<=0,4,5.5) -> 4 | M11: =VLOOKUP(H11,'Conveyor Costing'!$B$3:$F$7,5,0)*2 -> 254354.57 | N11: =VLOOKUP(L11,'Conveyor Costing'!$T$24:$AB$38,9,0) -> 143651.5 | O11: =VLOOKUP(H11,'Conveyor Costing'!$B$3:$G$7,6,0)*2 -> 36933.399 | P11: =IF(G11<2.4,((M11+((0)*O11))+N11)*I11,((M11+((G11-2.4)*O11))+N11)*I11) -> 451190.16 | Q11: =P11/$Q$1 -> 668429.87 | R11: Infeed | S11: =Q11/'Overall Costing'!$M$5 -> 7110.956
A12: 10 | B12: PVC Belt Conveyor | C12: 0 | D12: 550 | E12: 550 | F12: 5760 | G12: =F12/1000 -> 5.76 | H12: 1210 | I12: 1 | L12: =IF(C12<=0,4,5.5) -> 4 | M12: =VLOOKUP(H12,'Conveyor Costing'!$B$3:$F$7,5,0)*2 -> 254354.57 | N12: =VLOOKUP(L12,'Conveyor Costing'!$T$24:$AB$38,9,0) -> 143651.5 | O12: =VLOOKUP(H12,'Conveyor Costing'!$B$3:$G$7,6,0)*2 -> 36933.399 | P12: =IF(G12<2.4,((M12+((0)*O12))+N12)*I12,((M12+((G12-2.4)*O12))+N12)*I12) -> 522102.29 | Q12: =P12/$Q$1 -> 773484.87 | R12: Infeed | S12: =Q12/'Overall Costing'!$M$5 -> 8228.5624
A13: 11 | B13: PVC Belt Conveyor | C13: 0 | D13: 2452 | E13: 2452 | F13: 2000 | G13: =F13/1000 -> 2 | H13: 1210 | I13: 1 | L13: =IF(C13<=0,4,5.5) -> 4 | M13: =VLOOKUP(H13,'Conveyor Costing'!$B$3:$F$7,5,0)*2 -> 254354.57 | N13: =VLOOKUP(L13,'Conveyor Costing'!$T$24:$AB$38,9,0) -> 143651.5 | O13: =VLOOKUP(H13,'Conveyor Costing'!$B$3:$G$7,6,0)*2 -> 36933.399 | P13: =IF(G13<2.4,((M13+((0)*O13))+N13)*I13,((M13+((G13-2.4)*O13))+N13)*I13) -> 398006.07 | Q13: =P13/$Q$1 -> 589638.62 | R13: Infeed | S13: =Q13/'Overall Costing'!$M$5 -> 6272.7512
A14: 12 | B14: PVC Belt Conveyor | C14: 14.8 | D14: 2350 | E14: 4433 | F14: 8000 | G14: =F14/1000 -> 8 | H14: 1210 | I14: 1 | L14: 7.5 | M14: =VLOOKUP(H14,'Conveyor Costing'!$B$3:$F$7,5,0)*2 -> 254354.57 | N14: =VLOOKUP(L14,'Conveyor Costing'!$T$24:$AB$38,9,0) -> 249400 | O14: =VLOOKUP(H14,'Conveyor Costing'!$B$3:$G$7,6,0)*2 -> 36933.399 | P14: =IF(G14<2.4,((M14+((0)*O14))+N14)*I14,((M14+((G14-2.4)*O14))+N14)*I14) -> 710581.6 | Q14: =P14/$Q$1 -> 1052713.5 | R14: Infeed | S14: =Q14/'Overall Costing'!$M$5 -> 11199.08
A15: 13 | B15: PVC Belt Conveyor | C15: 0 | D15: 550 | E15: 550 | F15: 5760 | G15: =F15/1000 -> 5.76 | H15: 1210 | I15: 1 | L15: =IF(C15<=0,4,5.5) -> 4 | M15: =VLOOKUP(H15,'Conveyor Costing'!$B$3:$F$7,5,0)*2 -> 254354.57 | N15: =VLOOKUP(L15,'Conveyor Costing'!$T$24:$AB$38,9,0) -> 143651.5 | O15: =VLOOKUP(H15,'Conveyor Costing'!$B$3:$G$7,6,0)*2 -> 36933.399 | P15: =IF(G15<2.4,((M15+((0)*O15))+N15)*I15,((M15+((G15-2.4)*O15))+N15)*I15) -> 522102.29 | Q15: =P15/$Q$1 -> 773484.87 | R15: Infeed | S15: =Q15/'Overall Costing'!$M$5 -> 8228.5624
A16: 14 | B16: PVC Belt Conveyor | C16: 14.3 | D16: 3548 | E16: 5180 | F16: 6440 | G16: =F16/1000 -> 6.44 | H16: 1210 | I16: 1 | L16: =IF(C16<=0,4,5.5) -> 5.5 | M16: =VLOOKUP(H16,'Conveyor Costing'!$B$3:$F$7,5,0)*2 -> 254354.57 | N16: =VLOOKUP(L16,'Conveyor Costing'!$T$24:$AB$38,9,0) -> 169290 | O16: =VLOOKUP(H16,'Conveyor Costing'!$B$3:$G$7,6,0)*2 -> 36933.399 | P16: =IF(G16<2.4,((M16+((0)*O16))+N16)*I16,((M16+((G16-2.4)*O16))+N16)*I16) -> 572855.5 | Q16: =P16/$Q$1 -> 848674.81 | R16: Infeed | S16: =Q16/'Overall Costing'!$M$5 -> 9028.4554
A17: 15 | B17: PVC Belt Conveyor | C17: 0 | D17: 550 | E17: 550 | F17: 5760 | G17: =F17/1000 -> 5.76 | H17: 1210 | I17: 1 | L17: =IF(C17<=0,4,5.5) -> 4 | M17: =VLOOKUP(H17,'Conveyor Costing'!$B$3:$F$7,5,0)*2 -> 254354.57 | N17: =VLOOKUP(L17,'Conveyor Costing'!$T$24:$AB$38,9,0) -> 143651.5 | O17: =VLOOKUP(H17,'Conveyor Costing'!$B$3:$G$7,6,0)*2 -> 36933.399 | P17: =IF(G17<2.4,((M17+((0)*O17))+N17)*I17,((M17+((G17-2.4)*O17))+N17)*I17) -> 522102.29 | Q17: =P17/$Q$1 -> 773484.87 | R17: Infeed | S17: =Q17/'Overall Costing'!$M$5 -> 8228.5624
A18: 16 | B18: PVC Belt Conveyor | C18: 0 | D18: 4050 | E18: 4050 | F18: 5760 | G18: =F18/1000 -> 5.76 | H18: 1210 | I18: 1 | L18: =IF(C18<=0,4,5.5) -> 4 | M18: =VLOOKUP(H18,'Conveyor Costing'!$B$3:$F$7,5,0)*2 -> 254354.57 | N18: =VLOOKUP(L18,'Conveyor Costing'!$T$24:$AB$38,9,0) -> 143651.5 | O18: =VLOOKUP(H18,'Conveyor Costing'!$B$3:$G$7,6,0)*2 -> 36933.399 | P18: =IF(G18<2.4,((M18+((0)*O18))+N18)*I18,((M18+((G18-2.4)*O18))+N18)*I18) -> 522102.29 | Q18: =P18/$Q$1 -> 773484.87 | R18: Infeed | S18: =Q18/'Overall Costing'!$M$5 -> 8228.5624
A19: 17 | B19: PVC Belt Conveyor | C19: 0 | D19: 550 | E19: 550 | F19: 5760 | G19: =F19/1000 -> 5.76 | H19: 1210 | I19: 1 | L19: =IF(C19<=0,4,5.5) -> 4 | M19: =VLOOKUP(H19,'Conveyor Costing'!$B$3:$F$7,5,0)*2 -> 254354.57 | N19: =VLOOKUP(L19,'Conveyor Costing'!$T$24:$AB$38,9,0) -> 143651.5 | O19: =VLOOKUP(H19,'Conveyor Costing'!$B$3:$G$7,6,0)*2 -> 36933.399 | P19: =IF(G19<2.4,((M19+((0)*O19))+N19)*I19,((M19+((G19-2.4)*O19))+N19)*I19) -> 522102.29 | Q19: =P19/$Q$1 -> 773484.87 | R19: Infeed | S19: =Q19/'Overall Costing'!$M$5 -> 8228.5624
A20: 18 | B20: PVC Belt Conveyor | C20: 0 | D20: 3650 | E20: 3650 | F20: 3840 | G20: =F20/1000 -> 3.84 | H20: 1210 | I20: 1 | L20: =IF(C20<=0,4,5.5) -> 4 | M20: =VLOOKUP(H20,'Conveyor Costing'!$B$3:$F$7,5,0)*2 -> 254354.57 | N20: =VLOOKUP(L20,'Conveyor Costing'!$T$24:$AB$38,9,0) -> 143651.5 | O20: =VLOOKUP(H20,'Conveyor Costing'!$B$3:$G$7,6,0)*2 -> 36933.399 | P20: =IF(G20<2.4,((M20+((0)*O20))+N20)*I20,((M20+((G20-2.4)*O20))+N20)*I20) -> 451190.16 | Q20: =P20/$Q$1 -> 668429.87 | R20: Infeed | S20: =Q20/'Overall Costing'!$M$5 -> 7110.956
A21: 19 | B21: PVC Belt Conveyor | C21: 0 | D21: 550 | E21: 550 | F21: 5760 | G21: =F21/1000 -> 5.76 | H21: 1210 | I21: 1 | L21: =IF(C21<=0,4,5.5) -> 4 | M21: =VLOOKUP(H21,'Conveyor Costing'!$B$3:$F$7,5,0)*2 -> 254354.57 | N21: =VLOOKUP(L21,'Conveyor Costing'!$T$24:$AB$38,9,0) -> 143651.5 | O21: =VLOOKUP(H21,'Conveyor Costing'!$B$3:$G$7,6,0)*2 -> 36933.399 | P21: =IF(G21<2.4,((M21+((0)*O21))+N21)*I21,((M21+((G21-2.4)*O21))+N21)*I21) -> 522102.29 | Q21: =P21/$Q$1 -> 773484.87 | R21: Infeed | S21: =Q21/'Overall Costing'!$M$5 -> 8228.5624
A22: 20 | B22: PVC Belt Conveyor | C22: 14.8 | D22: 448 | E22: 2532 | F22: 8000 | G22: =F22/1000 -> 8 | H22: 1210 | I22: 1 | L22: 7.5 | M22: =VLOOKUP(H22,'Conveyor Costing'!$B$3:$F$7,5,0)*2 -> 254354.57 | N22: =VLOOKUP(L22,'Conveyor Costing'!$T$24:$AB$38,9,0) -> 249400 | O22: =VLOOKUP(H22,'Conveyor Costing'!$B$3:$G$7,6,0)*2 -> 36933.399 | P22: =IF(G22<2.4,((M22+((0)*O22))+N22)*I22,((M22+((G22-2.4)*O22))+N22)*I22) -> 710581.6 | Q22: =P22/$Q$1 -> 1052713.5 | R22: Infeed | S22: =Q22/'Overall Costing'!$M$5 -> 11199.08
A23: 21 | B23: Modular Conveyor | C23: 0 | D23: 1200 | E23: 1200 | F23: 4200 | G23: =F23/1000 -> 4.2 | H23: 1238 | I23: 1 | K23: ='Quote Master'!$I$42*1.3 -> 333883.33 | O23: ='Quote Master'!$I$38*2 -> 130333.33 | Q23: =((O23*G23)+K23)*I23 -> 881283.33 | R23: Rejection & Non Con | S23: =Q23/'Overall Costing'!$M$5 -> 9375.3546
A24: 22 | B24: Modular Conveyor | C24: 0 | D24: 800 | E24: 800 | F24: 4500 | G24: =F24/1000 -> 4.5 | H24: 1238 | I24: 1 | K24: ='Quote Master'!$I$42*1.3 -> 333883.33 | O24: ='Quote Master'!$I$38*2 -> 130333.33 | Q24: =((O24*G24)+K24)*I24 -> 920383.33 | R24: Rejection & Non Con | S24: =Q24/'Overall Costing'!$M$5 -> 9791.3121
A25: 23 | B25: Modular Conveyor | C25: 0 | D25: 800 | E25: 800 | F25: 4500 | G25: =F25/1000 -> 4.5 | H25: 1238 | I25: 1 | K25: ='Quote Master'!$I$42*1.3 -> 333883.33 | O25: ='Quote Master'!$I$38*2 -> 130333.33 | Q25: =((O25*G25)+K25)*I25 -> 920383.33 | R25: Rejection & Non Con | S25: =Q25/'Overall Costing'!$M$5 -> 9791.3121
A26: 24 | B26: Modular Conveyor | C26: 0 | D26: 800 | E26: 800 | F26: 3720 | G26: =F26/1000 -> 3.72 | H26: 1238 | I26: 1 | K26: ='Quote Master'!$I$42*1.3 -> 333883.33 | O26: ='Quote Master'!$I$38*2 -> 130333.33 | Q26: =((O26*G26)+K26)*I26 -> 818723.33 | R26: Rejection & Non Con | S26: =Q26/'Overall Costing'!$M$5 -> 8709.8227
A27: 25 | B27: Modular Conveyor | C27: 0 | D27: 1200 | E27: 1200 | F27: 5100 | G27: =F27/1000 -> 5.1 | H27: 1238 | I27: 1 | K27: ='Quote Master'!$I$42*1.3 -> 333883.33 | O27: ='Quote Master'!$I$38*2 -> 130333.33 | Q27: =((O27*G27)+K27)*I27 -> 998583.33 | R27: Rejection & Non Con | S27: =Q27/'Overall Costing'!$M$5 -> 10623.227
A28: 26 | B28: Modular Conveyor | C28: 0 | D28: 1200 | E28: 1200 | F28: 5100 | G28: =F28/1000 -> 5.1 | H28: 1238 | I28: 1 | K28: ='Quote Master'!$I$42*1.3 -> 333883.33 | O28: ='Quote Master'!$I$38*2 -> 130333.33 | Q28: =((O28*G28)+K28)*I28 -> 998583.33 | R28: Rejection & Non Con | S28: =Q28/'Overall Costing'!$M$5 -> 10623.227
A29: 27 | B29: Modular Conveyor | C29: 0 | D29: 1200 | E29: 1200 | F29: 5100 | G29: =F29/1000 -> 5.1 | H29: 1238 | I29: 1 | K29: ='Quote Master'!$I$42*1.3 -> 333883.33 | O29: ='Quote Master'!$I$38*2 -> 130333.33 | Q29: =((O29*G29)+K29)*I29 -> 998583.33 | R29: Rejection & Non Con | S29: =Q29/'Overall Costing'!$M$5 -> 10623.227
A30: 28 | B30: Modular Conveyor | C30: 0 | D30: 800 | E30: 800 | F30: 4500 | G30: =F30/1000 -> 4.5 | H30: 1238 | I30: 1 | K30: ='Quote Master'!$I$42*1.3 -> 333883.33 | O30: ='Quote Master'!$I$38*2 -> 130333.33 | Q30: =((O30*G30)+K30)*I30 -> 920383.33 | R30: Rejection & Non Con | S30: =Q30/'Overall Costing'!$M$5 -> 9791.3121
A31: 29 | B31: Modular Conveyor | C31: 0 | D31: 800 | E31: 800 | F31: 2400 | G31: =F31/1000 -> 2.4 | H31: 1238 | I31: 1 | K31: ='Quote Master'!$I$42*1.3 -> 333883.33 | O31: ='Quote Master'!$I$38*2 -> 130333.33 | Q31: =((O31*G31)+K31)*I31 -> 646683.33 | R31: Rejection & Non Con | S31: =Q31/'Overall Costing'!$M$5 -> 6879.6099
A32: 30 | B32: Modular Conveyor | C32: 0 | D32: 1200 | E32: 1200 | F32: 4200 | G32: =F32/1000 -> 4.2 | H32: 1238 | I32: 1 | K32: ='Quote Master'!$I$42*1.3 -> 333883.33 | O32: ='Quote Master'!$I$38*2 -> 130333.33 | Q32: =((O32*G32)+K32)*I32 -> 881283.33 | R32: Rejection & Non Con | S32: =Q32/'Overall Costing'!$M$5 -> 9375.3546
A33: 31 | B33: Modular Conveyor | C33: 0 | D33: 800 | E33: 800 | F33: 4500 | G33: =F33/1000 -> 4.5 | H33: 1238 | I33: 1 | K33: ='Quote Master'!$I$42*1.3 -> 333883.33 | O33: ='Quote Master'!$I$38*2 -> 130333.33 | Q33: =((O33*G33)+K33)*I33 -> 920383.33 | R33: Rejection & Non Con | S33: =Q33/'Overall Costing'!$M$5 -> 9791.3121
A34: 32 | B34: Modular Conveyor | C34: 0 | D34: 800 | E34: 800 | F34: 4500 | G34: =F34/1000 -> 4.5 | H34: 1238 | I34: 1 | K34: ='Quote Master'!$I$42*1.3 -> 333883.33 | O34: ='Quote Master'!$I$38*2 -> 130333.33 | Q34: =((O34*G34)+K34)*I34 -> 920383.33 | R34: Rejection & Non Con | S34: =Q34/'Overall Costing'!$M$5 -> 9791.3121
... A58: 56 | B58: Modular Conveyor | C58: 0 | D58: 800 | E58: 800 | F58: 4500 | G58: =F58/1000 -> 4.5 | H58: 1238 | I58: 1 | K58: ='Quote Master'!$I$42*1.3 -> 333883.33 | O58: ='Quote Master'!$I$38*2 -> 130333.33 | Q58: =((O58*G58)+K58)*I58 -> 920383.33 | R58: Rejection & Non Con | S58: =Q58/'Overall Costing'!$M$5 -> 9791.3121
A59: 57 | B59: Curve Conveyor(90°) | D59: 650 | E59: 650 | H59: 1000 | I59: 1 | J59: ='Quote Master'!$I$13*2 -> 1520000 | Q59: =I59*J59 -> 1520000 | R59: Rejection & Non Con | S59: =Q59/'Overall Costing'!$M$5 -> 16170.213
A60: 58 | B60: Curve Conveyor(90°) | D60: 650 | E60: 650 | H60: 1000 | I60: 1 | J60: ='Quote Master'!$I$13*2 -> 1520000 | Q60: =I60*J60 -> 1520000 | R60: Rejection & Non Con | S60: =Q60/'Overall Costing'!$M$5 -> 16170.213
P61: Total | Q61: =SUM(Q3:Q60) -> 53128257
F65: Total Conveyor Price | G65: =GETPIVOTDATA("Sum of Selling Price",$M$67) -> 53128257 | M65: Family | N65: (All)
F66: Field wiring and controls | G66: =(GETPIVOTDATA("Sum of Selling Price",$M$67,"Name","PVC Belt Conveyor")+GETPIVOTDATA("Sum of Selling Price",$M$67,"Name","Modular Conveyor")+GETPIVOTDATA("Sum of Selling Price",$M$67,"Name","PVC Belt Conveyor(Bulk loading)"))*'Overall Costing'!M3 -> 7513238.6 | H66: =G66+G67+G68+G69 -> 9148619.3
F67: Conveyor Legs | G67: =NormalConveyorLeg!$H$302 -> 544145.15 | M67: Row Labels | N67: Sum of Conveyor Length (m) | O67: Sum of Set | P67: Sum of Selling Price
F68: End joints | G68: =EndJoints!$I$4 -> 242000 | L68: Cost/meter and base modual cost 2X | M68: PVC Belt Conveyor | N68: 102.64 | O68: 18 | P68: 14612219
F69: Leg Guards | G69: ='Leg Guards'!$E$5 -> 849235.56 | L69: Unit Price 2X | M69: Curve Conveyor(90°) | O69: 2 | P69: 3040000
F70: Overall Price | G70: =SUM(G65:G69) -> 62276876 | L70: Cost/meter 2X and Drive modual 30% | M70: Modular Conveyor | N70: 163.8 | O70: 36 | P70: 33368400 | Q70: =GETPIVOTDATA("Sum of Conveyor Length (m)",$M$67,"Name","Modular Conveyor")+'Arm Sorter'!C2 -> 228
L71: Cost/meter and base modual cost 3X | M71: PVC Belt Conveyor(Bulk loading) | N71: 11.52 | O71: 2 | P71: 2107637.6
M72: Grand Total | N72: 277.96 | O72: 58 | P72: 53128257
M75: Inbound Conveyor | N75: =S3+S4+S5+S6+S8+S9+S10+S11+S12+S13+S15+S16 -> 104248.37
M76: Rejection Line | N76: =S7+S14+S23+S24+S25+S26+S27+S28+S59+S60 -> 113652.84
M77: Field Wiring | N77: =H66/'Overall Costing'!M5 -> 97325.737

Sheet Conveyor Costing
A1: PVC Conveyor
C2: Head Module (HM) | D2: Tail Module (TM) | E2: Drive Module (DM) | F2: Base Module (BM) HM+TM+DM | G2: Cost/ mtr
A3: 600 width | B3: 610 | C3: 27306.018 | D3: 28801.314 | E3: 45770.662 | F3: =C3+D3+E3 -> 101877.99 | G3: 14365.914 | K3: BOTTOM COVER MODULE | M3: 1746.5555
A4: 800 width | B4: 810 | C4: 29307.738 | D4: 31067.986 | E4: 46628.891 | F4: =C4+D4+E4 -> 107004.62 | G4: 16165.194 | K4: COMPONENT GUIDE MODULE | M4: 6144.0099
A5: 1000 width | B5: 1010 | C5: 33231.005 | D5: 35451.005 | E5: 50560 | F5: =C5+D5+E5 -> 119242.01 | G5: 17854 | K5: CONVEYOR BELT | M5: 3381.9588
A6: 1200 width | B6: 1210 | C6: 34341.482 | D6: 37664.005 | E6: 55171.796 | F6: =C6+D6+E6 -> 127177.28 | G6: 18466.699
A7: 1400 width | B7: 1410 | C7: 40369.382 | D7: 43158.405 | E7: 63811.58 | F7: =C7+D7+E7 -> 147339.37 | G7: 22035.982
A9: Bagging Conveyor
C10: Head Module (HM) | D10: Tail Module (TM) | E10: Drive Module (DM) | F10: Base Module (BM) HM+TM+DM | G10: Cost/ mtr | I10: SR NO | J10: POWER | K10: ITEM ID | L10: Motor MODEL NO | M10: PO NO | N10: Motor PRICE/UNIT | O10: VFD | P10: Panel DM | Q10: Total Cost | S10: International Project (RF Series)
A11: 600 width | B11: 610 | E11: NA | G11: 14365.914 | I11: 1 | J11: 1.5 | K11: 66021 | N11: 20823 | O11: 13755 | P11: 14200 | Q11: =N11+O11+P11 -> 48778 | S11: SR NO | T11: POWER | U11: ITEM ID | V11: Motor MODEL NO | W11: PO NO | X11: Motor price/unit (INR) | Y11: Average Cost | Z11: VFD | AA11: Panel DM | AB11: Total Cost
A12: 800 width | B12: 810 | E12: Na | G12: 16165.194 | I12: 2 | J12: 2.2 | K12: 26704 | L12: RF67 DIBE100S4 | M12: PO-2022-23-0714 | N12: 26117 | O12: 15000 | P12: 14200 | Q12: =N12+O12+P12 -> 55317 | S12: 1 | T12: 1.5 | U12: 115350 | V12: R27DRN90L4 | W12: PO-2024-25-0234 | X12: 30418 | Y12: =AVERAGE(X12) -> 30418 | Z12: 13755 | AA12: 14200 | AB12: =Y12+Z12+AA12 -> 58373
A13: 1000 width | B13: 1010 | C13: 50692 | D13: 31799 | E13: NA | F13: =C13+D13 -> 82491 | G13: 17854 | I13: 3 | J13: 3 | K13: 85889 | L13: RF67 DIBE100M4 | M13: PO-2022-23-0714 | N13: 35896 | O13: 17000 | P13: 14600 | Q13: =N13+O13+P13 -> 67496 | S13: 2 | T13: 2.2 | U13: 120748 | V13: R37DRN100LS4 | W13: PO-2024-25-4766-V-1 | X13: 36651 | Y13: =AVERAGE(X13:X15) -> 36040 | Z13: 15000 | AA13: 14200 | AB13: =Y13+Z13+AA13 -> 65240
A14: 1200 width | B14: 1210 | C14: 54466 | D14: 34389 | E14: NA | F14: =C14+D14 -> 88855 | G14: 18466.699 | I14: 4 | J14: 4 | K14: 20348 | L14: RF77 DIBE112M4 | M14: PO-2021-22-2713 | N14: 38065 | O14: 20370 | P14: 14600 | Q14: =N14+O14+P14 -> 73035 | U14: 118195 | V14: R27DRN100LM4 | W14: PO-2024-25-2262 | X14: 36587
A15: 1400 width | B15: 1410 | E15: NA | G15: 22035.982 | I15: 5 | J15: 5.5 | K15: 86632 | L15: RF87 DIBE132S4/RS | M15: PO-2022-23-0714 | N15: 67743 | O15: 33390 | P15: 19300 | Q15: =N15+O15+P15 -> 120433 | U15: 113248 | V15: R27DRN100LS4 | W15: PO-2023-24-7004 | X15: 34882
I16: 6 | J16: 7.5 | K16: 91949 | L16: RF87 DIBE132M4/RS | M16: PO-2022-23-1240 | N16: 69107 | O16: 48000 | P16: 24300 | Q16: =N16+O16+P16 -> 141407 | S16: 3 | T16: 3 | U16: 118194 | V16: R37DRN100L4 | W16: PO-2024-25-2262 | X16: 39592 | Y16: =AVERAGE(X16) -> 39592 | Z16: 17000 | AA16: 14600 | AB16: =Y16+Z16+AA16 -> 71192
S17: 4 | T17: 4 | U17: 121011 | V17: RF77 DRN112M4/BE5/HR | W17: PO-2024-25-4927 | X17: 86107 | Y17: =AVERAGE(X17) -> 86107 | Z17: 20370 | AA17: 14600 | AB17: =Y17+Z17+AA17 -> 121077
S18: 5 | T18: 5.5 | Z18: 33390 | AA18: 19300
I19: SR NO | J19: POWER | K19: ITEM ID | L19: MODEL NO | M19: PO NO | N19: PRICE/UNIT | S19: 6 | T19: 7.5 | Z19: 48000 | AA19: 24300
I20: 1 | J20: 1.5 | N20: 33696 | O20: 13755 | P20: 14200 | Q20: =N20+O20+P20 -> 61651
I21: 2 | J21: 2.2 | K21: 62293 | L21: SA57/T DIBE100S4 | M21: PO-2022-23-1240 | N21: 36167 | O21: 15000 | P21: 14200 | Q21: =N21+O21+P21 -> 65367
I22: 3 | J22: 3 | K22: 64204 | L22: SA67/T DIBE100M4 | M22: PO-2022-23-0714 | N22: 45454 | O22: 17000 | P22: 14600 | Q22: =N22+O22+P22 -> 77054 | S22: International Project (SA series)
I23: 4 | J23: 4 | K23: 63408 | L23: SA67/T DIBE112M4 | M23: PO-2022-23-1240 | N23: 48390 | O23: 20370 | P23: 14600 | Q23: =N23+O23+P23 -> 83360 | S23: SR NO | T23: POWER | U23: ITEM ID | V23: MODEL NO | W23: PO NO | X23: Motor price/unit (INR) | Y23: Average Cost | Z23: VFD | AA23: Panel DM | AB23: Total Cost
I24: 5 | J24: 5.5 | K24: 32288 | L24: SA77/T DIBS132S4 | M24: NA | N24: =N15+15000 -> 82743 | O24: 33390 | P24: 19300 | Q24: =N24+O24+P24 -> 135433 | S24: 1 | T24: 1.5 | U24: 102768 | V24: SA67/T DRN90L4 | W24: PO-2023-24-1382 | X24: 61190.44 | Y24: =AVERAGE(X24:X25) -> 56974.72 | Z24: 13755 | AA24: 14200 | AB24: =Y24+Z24+AA24 -> 84929.72
I25: 6 | J25: 7.5 | K25: 101915 | N25: =N16+15000 -> 84107 | O25: 48000 | P25: 24300 | Q25: =N25+O25+P25 -> 156407 | U25: 110017 | V25: SA47/T DRN90L4 | W25: PO-2023-24-3602 | X25: 52759
S26: 2 | T26: 2.2 | U26: 102756 | V26: SA67/T DRN100LS4/BE5/HR | W26: PO-2023-24-1382 | X26: 83494.49 | Y26: =AVERAGE(X26:X31) -> 67885.748 | Z26: 15000 | AA26: 14200 | AB26: =Y26+Z26+AA26 -> 97085.748
U27: 116985 | V27: SA57/T DRN100LS4/BE5/HR | W27: PO-2024-25-1072 | X27: 72798
U28: 118166 | V28: SA67/T DRN100LM4 | W28: PO-2024-25-2262 | X28: 68375
U29: 115236 | V29: SA67/T DRN100LS4 | W29: PO-2024-25-0185 | X29: 66871
U30: 120301 | V30: SA57/T DRN100LM4 | W30: PO-2024-25-3843 | X30: 60058
U31: 115365 | V31: SA57/T DRN100LS4 | W31: PO-2024-25-0234 | X31: 55718
S32: 3 | T32: 3 | U32: 102759 | V32: SA67/T DRN100L4/BE5/HR | W32: PO-2023-24-1382 | X32: 87311.03 | Y32: =AVERAGE(X32:X34) -> 72764.45 | Z32: 17000 | AA32: 14600 | AB32: =Y32+Z32+AA32 -> 104364.45
U33: 102758 | V33: SA67/T DRN100L4 | W33: PO-2023-24-1382 | X33: 71055.32
U34: 75130 | V34: SA57/T DRN100L4 | W34: PO-2024-25-1572 | X34: 59927
S35: 4 | T35: 4 | U35: 115235 | V35: SA77/T DRN112M4/BE5/HR | W35: PO-2024-25-0319 | X35: 115987 | Y35: =AVERAGE(X35:X36) -> 108681.5 | Z35: 20370 | AA35: 14600 | AB35: =Y35+Z35+AA35 -> 143651.5
U36: 115234 | V36: SA77/T DRN112M4 | W36: PO-2024-25-0185 | X36: 101376
S37: 5 | T37: 5.5 | U37: 115237 | V37: SA77/T DRN132S4 | W37: PO-2024-25-0020 | X37: 116600 | Y37: =AVERAGE(X37) -> 116600 | Z37: 33390 | AA37: 19300 | AB37: =Y37+Z37+AA37 -> 169290
S38: 6 | T38: 7.5 | X38: =70000*2.3*1.1 -> 177100 | Y38: =AVERAGE(X38) -> 177100 | Z38: 48000 | AA38: 24300 | AB38: =Y38+Z38+AA38 -> 249400

Sheet NormalConveyorLeg
A1: SL NO | B1: NAME | C1: WIDTH | D1: HEIGHT | E1: SET | F1: COST | G1: TOTAL COST | H1: TOTAL PRICE | I1: LAYER | Q1: Legs Cost Per Sq Meter | R1: 2072.2906 | S1: INR
A2: 1 | B2: Normal Conveyor Leg | C2: 1238 | D2: 800 | E2: 1 | F2: =$R$1 -> 2072.2906 | G2: =IF(D2>800,((C2*(D2-800))/10^6)*F2,0) -> 0 | H2: =(G2/$R$2)*E2 -> 0 | I2: legs | Q2: Sales Factor | R2: ='Overall Costing'!$M$1 -> 0.675
A3: 2 | B3: Normal Conveyor Leg | C3: 1238 | D3: 800 | E3: 1 | F3: =$R$1 -> 2072.2906 | G3: =IF(D3>800,((C3*(D3-800))/10^6)*F3,0) -> 0 | H3: =(G3/$R$2)*E3 -> 0 | I3: legs
A4: 3 | B4: Normal Conveyor Leg | C4: 1238 | D4: 1200 | E4: 1 | F4: =$R$1 -> 2072.2906 | G4: =IF(D4>800,((C4*(D4-800))/10^6)*F4,0) -> 1026.1983 | H4: =(G4/$R$2)*E4 -> 1520.2938 | I4: legs
A5: 4 | B5: Normal Conveyor Leg | C5: 1238 | D5: 1200 | E5: 1 | F5: =$R$1 -> 2072.2906 | G5: =IF(D5>800,((C5*(D5-800))/10^6)*F5,0) -> 1026.1983 | H5: =(G5/$R$2)*E5 -> 1520.2938 | I5: legs
A6: 5 | B6: Normal Conveyor Leg | C6: 1238 | D6: 800 | E6: 1 | F6: =$R$1 -> 2072.2906 | G6: =IF(D6>800,((C6*(D6-800))/10^6)*F6,0) -> 0 | H6: =(G6/$R$2)*E6 -> 0 | I6: legs
A7: 6 | B7: Normal Conveyor Leg | C7: 1238 | D7: 800 | E7: 1 | F7: =$R$1 -> 2072.2906 | G7: =IF(D7>800,((C7*(D7-800))/10^6)*F7,0) -> 0 | H7: =(G7/$R$2)*E7 -> 0 | I7: legs
A8: 7 | B8: Normal Conveyor Leg | C8: 1250 | D8: 800 | E8: 1 | F8: =$R$1 -> 2072.2906 | G8: =IF(D8>800,((C8*(D8-800))/10^6)*F8,0) -> 0 | H8: =(G8/$R$2)*E8 -> 0 | I8: legs
A9: 8 | B9: Normal Conveyor Leg | C9: 1238 | D9: 800 | E9: 1 | F9: =$R$1 -> 2072.2906 | G9: =IF(D9>800,((C9*(D9-800))/10^6)*F9,0) -> 0 | H9: =(G9/$R$2)*E9 -> 0 | I9: legs
A10: 9 | B10: Normal Conveyor Leg | C10: 1238 | D10: 800 | E10: 1 | F10: =$R$1 -> 2072.2906 | G10: =IF(D10>800,((C10*(D10-800))/10^6)*F10,0) -> 0 | H10: =(G10/$R$2)*E10 -> 0 | I10: legs
A11: 10 | B11: Normal Conveyor Leg | C11: 1238 | D11: 1200 | E11: 1 | F11: =$R$1 -> 2072.2906 | G11: =IF(D11>800,((C11*(D11-800))/10^6)*F11,0) -> 1026.1983 | H11: =(G11/$R$2)*E11 -> 1520.2938 | I11: legs
A12: 11 | B12: Normal Conveyor Leg | C12: 1238 | D12: 1200 | E12: 1 | F12: =$R$1 -> 2072.2906 | G12: =IF(D12>800,((C12*(D12-800))/10^6)*F12,0) -> 1026.1983 | H12: =(G12/$R$2)*E12 -> 1520.2938 | I12: legs
A13: 12 | B13: Normal Conveyor Leg | C13: 1238 | D13: 1200 | E13: 1 | F13: =$R$1 -> 2072.2906 | G13: =IF(D13>800,((C13*(D13-800))/10^6)*F13,0) -> 1026.1983 | H13: =(G13/$R$2)*E13 -> 1520.2938 | I13: legs
A14: 13 | B14: Normal Conveyor Leg | C14: 1238 | D14: 1200 | E14: 1 | F14: =$R$1 -> 2072.2906 | G14: =IF(D14>800,((C14*(D14-800))/10^6)*F14,0) -> 1026.1983 | H14: =(G14/$R$2)*E14 -> 1520.2938 | I14: legs
... A301: 300 | B301: Normal Conveyor Leg | C301: 1238 | D301: 800 | E301: 1 | F301: =$R$1 -> 2072.2906 | G301: =IF(D301>800,((C301*(D301-800))/10^6)*F301,0) -> 0 | H301: =(G301/$R$2)*E301 -> 0 | I301: legs
G302: Total Cost Price | H302: =SUM(H2:H292) -> 544145.15

Sheet Loop
C1: Specs | D1: Unit Price
B2: Sorter track | C2: With Leaky Wave Cable | D2: =(17209+1800)*1.15 -> 21860.35
C3: XL With Leaky Wave Cable | D3: 30075.84
B4: Curves- 30 Degree | C4: 3.5 | D4: =(55729/3)*1.15 -> 21362.783
C5: 4.5 | D5: =(D4*4.5/3.5) -> 27466.436
C6: 4.58 | D6: 34700
B7: Carrier Pitch (mm) | C7: 600 | D7: =10333*1.18 -> 12192.94
C8: 1175 | D8: =12539*1.18 -> 14796.02
C9: 1200 | D9: 22637
C10: 800 | D10: 20637
B12: Carrier Belt- Belt Pitch/Length (mm) | C12: 600/800 | D12: =28932*1.05 -> 30378.6
C13: 600/1200 | D13: 49213
C14: 800/1200 | D14: 59213
B16: Carrier Belt Top Height | C16: <=2.4 meter | D16: =9000*1.15 -> 10350
C17: >2.4 meter and <=3.5 meter | D17: =13552*1.15 -> 15584.8
C18: XL>2.4 meter and <=3.5 meter | D18: 24000
B20: Linear Motor Drive Set | C20: LIM | D20: =347553*1.05 -> 364930.65
C21: LSM | D21: =792675*1.1 -> 871942.5
B23: Sorter Loop Control | C23: For Leaky Wave Cable | D23: =(257312+300000-171000)*1.12 -> 432669.44
C24: XL For Leaky Wave Cable | D24: 540836.8
B25: PLC Platform | C25: Omron | D25: =(2325266-764700-186000-176000)*1.12 -> 1342393.9
C26: Siemens | D26: =(D25+276000+496700+818216+100000+552000)*1.12 -> 4015547.1
B28: Server Setup | C28: HAA-Falcon Standard | D28: 1272600 | E28: Updated on 28-07-2023
C29: HAA-Amazon Standard | D29: =1900000*1.12 -> 2128000
B31: Barcode Scanning Tunnel | C31: ICR-890 8K | D31: =1527639*1.1 -> 1680402.9
C32: ICR-890 12K | D32: =+(1527639*1.1)+200000 -> 1880402.9
C33: ICR890 12K 3 Camera- 3/5 Side Per Scan Tunnel | D33: =3100000+100000 -> 3200000
C34: ICR890 12K 5 Camera- 5 Side Per Scan Tunnel | D34: ='Quote Master'!$H$109 -> 5800000
C35: Cognex 3 Camera- Top Scan Without Image Capturing Per Scan Tunnel | D35: 1100000
C36: COGENAX Top side scanning (DM3816X) | D36: ='Quote Master'!$H$110 -> 424771
C37: Cognex 3 Camera- Top Scan With Image Capturing Per Scan Tunnel | D37: =D35+250000 -> 1350000
B39: VMS | C39: VMS 4200 Per Scan Tunnel | D39: =750000*1.1 -> 825000
C40: VMS5200 Per Scan Tunnel | D40: =950000*1.1 -> 1045000
C41: COGNEX VMS (3D- A1000) | D41: ='Quote Master'!$H$113 -> 351032
B43: Zone Cost | C43: With Sensor Based ECDS (>10 mm products) | D43: =84490*1.1 -> 92939
C44: With Camera Based ECDS (<10 mm products) | D44: =344490*1.12 -> 385828.8
B48: Safety Net | C48: Per meter | D48: =7656*1.15 -> 8804.4
B49: Fencing | C49: Per meter | D49: =6590*1.15 -> 7578.5
B50: Bridge Plate | C50: Per meter | D50: =3685*1.15 -> 4237.75

Sheet Bag Sorter Induct
A1: Factor | B1: 0.6
A3: Item | B3: Unit Price | C3: QP
A4: Loading Conveyor | B4: 235000 | C4: =B4/$B$1 -> 391666.67 | D4: 3 meter Long
A5: IFU/Spacing Conveyor/Buffer | B5: 129000 | C5: =B5/$B$1 -> 215000
A6: Weighing Conveyor | B6: 350000 | C6: =B6/$B$1 -> 583333.33
A7: MLG | B7: 107000 | C7: =B7/$B$1 -> 178333.33
A8: Leg Structure + Cable Tray | B8: =60000+15000 -> 75000 | C8: =B8/$B$1 -> 125000 | D8: For 5 conveyors
A9: Electrical Cost | B9: 77000 | C9: =B9/$B$1 -> 128333.33
A10: Common Cost | B10: =31000-12000 -> 19000 | C10: =B10/$B$1 -> 31666.667
A12: Total Cost of 4 Section Induct | B12: =SUM(B4:B10) -> 992000 | C12: =SUM(C4:C10) -> 1653333.3

Sheet Leg Guards
A1: SL NO | B1: Dm No | C1: SET | D1: PRICE | E1: TOTAL PRICE
A2: 1 | B2: D5348-0001-V0-R0 | C2: 100 | D2: =VLOOKUP(B2,'Quote Master'!$C$133:$I$135,7,0) -> 1555.5556 | E2: =D2*C2 -> 155555.56
A3: 2 | B3: D5348-0002-V0-R0 | C3: 0 | D3: =VLOOKUP(B3,'Quote Master'!$C$133:$I$135,7,0) -> 5641.4815 | E3: =D3*C3 -> 0
A4: 3 | B4: D5348-0003-V0-R0 | C4: 174 | D4: =VLOOKUP(B4,'Quote Master'!$C$133:$I$135,7,0) -> 3986.6667 | E4: =D4*C4 -> 693680 | J4: =126*1.4 -> 176.4
D5: Total Cost Price | E5: =SUM(E2:E4) -> 849235.56 | J5: =1.6*100 -> 160

Sheet EndJoints
A1: SL NO | B1: NAME | C1: MODULE_ID | D1: DESCRIPTION | E1: ANGLE | F1: WIDTH | G1: SET | H1: PRICE | I1: TOTAL PRICE
A2: 1 | B2: End Joint | C2: EJ_B3 | D2: EJ_B3IH250B00 | E2: 0 | F2: 810/1010/1210 | G2: 0 | H2: =VLOOKUP(D2,'Quote Master'!$C$124:$I$132,7,0) -> 9000 | I2: =H2*G2 -> 0
A3: 2 | B3: End Joint | C3: EJ_B5 | D3: EJ_B5IH400R00 | E3: 0 | F3: 810/1010/1210 | G3: =11+11 -> 22 | H3: =VLOOKUP(D3,'Quote Master'!$C$124:$I$132,7,0) -> 11000 | I3: =H3*G3 -> 242000
H4: Total Cost Price | I4: =SUM(I2:I3) -> 242000

Sheet Sample Inducts
G2: Austrian Post | N2: TCI | T2: DEL8
C3: DEL8
C4: 1242
C5: Austrian Post
C6: TCI
F22: T-1242 (Ecom India One)
C28: Penalty

Sheet Selection
G1: LIM
G2: LSM
B3: Q1 | G3: =IF(VLOOKUP(#REF!,#REF!,7,0)="Yes","LSM","") -> #REF!
B4: <10 mm
B5: >=10 mm
B7: Q7 | G7: =IF(#REF!="yes","HAA-Falcon Standard","") -> #REF!
B8: <=2.4 meter | G8: =IF(#REF!="yes","HAA-Amazon Standard","") -> #REF!
B9: >2.4 meter and <=3.5 meter
B10: XL>2.4 meter and <=3.5 meter
B12: Q10
B13: Yes
B14: No
B16: Q11
B17: Falcon Standard Specification HAA
B18: Amazon Specification HAA
B22: Standard Arm | C22: 600 mm
B23: Arm XL | C23: 800 mm | G23: Reference
C24: 1000 mm | G24: T910
G25: RHT BHS
G26: DEL8 RFP
G27: Tirol RFP
G28: T1242
G29: XL-DB

Sheet Induct line for Arm
B2: Conveyor Name | C2: Width | D2: <10 mm | E2: >=10 mm | F2: Length
B3: Angle Merge | C3: 600 mm | D3: =120170*1.125 -> 135191.25 | E3: =120170*1.125 -> 135191.25 | F3: 2
B4: Angle Merge | C4: 800 mm | D4: =D3*1.1 -> 148710.38 | E4: =E3*1.1 -> 148710.38 | F4: 3
B5: Buffer Conveyor | C5: 600 mm | D5: =101317*1.125 -> 113981.62 | E5: =D5-24000+4000 -> 93981.625 | F5: 1
B6: Buffer Conveyor | C6: 800 mm | D6: =D5*1.1 -> 125379.79 | E6: =E5*1.1 -> 103379.79 | F6: 1
B7: Spacing Conveyor | C7: 600 mm | D7: =105817*1.125 -> 119044.12 | E7: =D7-24000+4000 -> 99044.125 | F7: 1
B8: Spacing Conveyor | C8: 800 mm | D8: =D7*1.1 -> 130948.54 | E8: =E7*1.1 -> 108948.54 | F8: 1.5
C10: Control Panel | D10: =198000*1.12 -> 221760
C11: Leg Structure | D11: =(75000/6)*1.15 -> 14375

Sheet Induct Line for Swedi
B2: Conveyor Name | C2: Width | D2: <10 mm | E2: >=10 mm | F2: Length
B3: Angle Merge | C3: 600 mm | D3: =120170*1.125 -> 135191.25 | E3: =120170*1.125 -> 135191.25 | F3: 2
B4: Angle Merge | C4: 800 mm | D4: =D3*1.1 -> 148710.38 | E4: =E3*1.1 -> 148710.38 | F4: 2
B5: Angle Merge | C5: 1000 mm | D5: =D4*1.1 -> 163581.41 | E5: =E4*1.1 -> 163581.41 | F5: 2
B6: Buffer Conveyor | C6: 600 mm | D6: =101317*1.125 -> 113981.62 | E6: =D6-24000+4000 -> 93981.625 | F6: 1
B7: Buffer Conveyor | C7: 800 mm | D7: =D6*1.1 -> 125379.79 | E7: =E6*1.1 -> 103379.79 | F7: 1
B8: Buffer Conveyor | C8: 1000 mm | D8: =D7*1.1 -> 137917.77 | E8: =E7*1.1 -> 113717.77 | F8: 1
B9: Spacing Conveyor | C9: 600 mm | D9: =105817*1.125 -> 119044.12 | E9: =D9-24000+4000 -> 99044.125 | F9: 1
B10: Spacing Conveyor | C10: 800 mm | D10: =D9*1.1 -> 130948.54 | E10: =E9*1.1 -> 108948.54 | F10: 1.5
B11: Spacing Conveyor | C11: 1000 mm | D11: =D10*1.1 -> 144043.39 | E11: =E10*1.1 -> 119843.39 | F11: 1.5
C13: Control Panel | D13: =198000*1.12 -> 221760
C14: Leg Structure | D14: =(75000/6)*1.15 -> 14375

Sheet Destinations
A1: S.No | B1: Description | C1: Qty | D1: Chute Area | E1: UOM | F1: Unit Price | G1: Total Price | K1: Chute Area Factor | L1: 1.2
A2: 1 | B2: VDS Chutes | C2: =7*2 -> 14 | E2: sqm | F2: =('RECOMMEDED DESIGNS'!$P$15/'Overall Costing'!$M$1)*6 -> 543532.47 | G2: =C2*F2 -> 7609454.6 | H2: Reference in Chute Library
A3: 2 | B3: Standard Chutes | C3: =52*2 -> 104 | E3: sqm | F3: 150000 | G3: =F3*C3 -> 15600000
A4: 3 | B4: Narrow Chutes | C4: =5*2 -> 10 | E4: sqm | F4: 130000 | G4: =F4*C4 -> 1300000
A5: 4 | B5: Technical Chutes-01(Collection Type) | C5: =1*2 -> 2 | E5: sqm | F5: ='Chute Costing '!E4 -> 345450 | G5: =F5*C5 -> 690900
A6: 4 | B6: Technical Chutes-02(Sprial Type) | C6: =1*2 -> 2 | E6: set | F6: =((('RECOMMEDED DESIGNS'!$P$24)/3)*2)/'Overall Costing'!M1 -> 470586.11 | G6: =F6*C6 -> 941172.21 | H6: No. reference in Chute Library
A7: 6 | B7: Bulk REJECT Chute( at end of VDS) | C7: =1*2 -> 2 | D7: =(16.6779243)*L1 -> 20.013509 | E7: sqm | F7: =+'Quote Master'!$I$56*6 -> 70560 | G7: =+F7*C7*D7 -> 2824306.4 | H7: No. reference in Chute Library
A8: 7 | B8: Rejection Chutes | E8: sqm | F8: =+'Quote Master'!$I$56 -> 11760 | G8: =+F8*C8*D8 -> 0
A9: 8 | B9: Irregular Shipment Chutes | C9: =C2 -> 14 | E9: set | F9: ='RECOMMEDED DESIGNS'!$P$7/'Overall Costing'!M1 -> 79927.831 | G9: =F9*C9 -> 1118989.6 | H9: Chute type found in Chute library, however this is looking tentative similar setup | I9: #VALUE!
A10: 9 | B10: DBO Chutes | E10: sqm | F10: =+'Quote Master'!$I$56 -> 11760 | G10: =+F10*C10*D10 -> 0
A11: 10 | B11: Sort Fail Chute | E11: sqm | F11: =+'Quote Master'!$I$56 -> 11760 | G11: =+F11*C11*D11 -> 0
A12: 11 | B12: Roller based chute | E12: sqm | F12: 0 | G12: =+F12*C12*D12 -> 0
A13: 12 | B13: Spring Loaded Fixed Bin | E13: Numbers | F13: =+'Quote Master'!I60 -> 50400 | G13: =+F13*C13 -> 0
A14: 13 | B14: Spring Loaded Portatble Bin | E14: Numbers | F14: =+'Quote Master'!I61 -> 56000 | G14: =+F14*C14 -> 0
A15: 14 | B15: Simple Fixed Bin | E15: Numbers | F15: =+'Quote Master'!I62 -> 13440 | G15: =+F15*C15 -> 0
A16: 15 | B16: Simple Portable Bin | E16: Numbers | F16: =+'Quote Master'!$I$63 -> 16800 | G16: =+F16*C16 -> 0
A17: 16 | B17: Rejection Trolley | E17: Numbers | F17: =+'Quote Master'!$I$63 -> 16800 | G17: =+F17*C17 -> 0
A18: 17 | B18: Bag Holder Assembly | E18: Numbers | F18: =+'Quote Master'!I59 -> 12880 | G18: =+F18*C18 -> 0
A19: 19 | B19: Chute Full Sensors | C19: =(SUM($C$2:$C$7))*2 -> 268 | E19: Numbers | F19: =+'Quote Master'!I57 -> 5600 | G19: =+F19*C19 -> 1500800
A20: 21 | B20: Tower lamps (3 colour) | C20: =(SUM($C$2:$C$7)) -> 134 | E20: Numbers | F20: ='Quote Master'!I86 -> 7500 | G20: =+F20*C20 -> 1005000
A21: 22 | B21: Push Button | C21: =(SUM($C$3:$C$7)) -> 120 | E21: Numbers | F21: =+'Quote Master'!I96 -> 5000 | G21: =+F21*C21 -> 600000
A22: 20 | B22: I/O for Chute full sensors | C22: =ROUNDUP(SUM(C19:C21)/4,0)+1 -> 132 | D22: =+ROUNDUP((D19+D20+D21)/4,0) -> 0 | E22: Numbers | F22: =+'Quote Master'!I88 -> 34000 | G22: =+F22*C22 -> 4488000
F23: Total | G23: =+SUM(G2:G22) -> 37678623
B26: Chute Price | D26: =G2+G3+G4+G5+G6+G7+G9 -> 30084823 | F26: =D26/'Overall Costing'!M5 -> 320051.31
B27: Chute Accessories | D27: =G19+G20+G21+G22 -> 7593800 | F27: =D27/'Overall Costing'!M5 -> 80785.106

Sheet RECOMMEDED DESIGNS
A1: FAPL CHUTE LIBRARY | P1: DOC. CODE: M-Des./DOC/CHC/002/R1 EFF. DT: 30.10.24
A2: Sl No. | B2: Product type | C2: Product size LxWxH (mm) | D2: Product weight max/min (kg) | E2: Chute type | F2: Sorter Type | G2: Design type | H2: End Use | I2: Reference Site | J2: Location | K2: Released TSPR | L2: Dimensions | M2: Image | N2: Weight | O2: DM No. | P2: Unit Cost | Q2: Remarks
A3: 1 | B3: Parcel | C3: Max - 500x500x500 Min - 100x50x5 | D3: 10 / 0.05 | E3: L type sorting chute | F3: Double Decker CBS | G3: Curve | H3: PTL | I3: 3525 | J3: Delhivery - Bangalore | K3: Tool : 3525 Stn : J1 R351 & 356 Qty : 41 | L3: Total Width : 2520 mm Working Width : 800 mm Input height (upper) : 5250 mm Input height (lower) : 3250 mm Output height : 750 mm | M3: #VALUE! | N3: 678.67844 | O3: NA | P3: 93382.042
A4: 2 | B4: Parcel | C4: Max - 500x500x500 Min - 100x50x5 | D4: 10 / 0.05 | E4: L type sorting chute | F4: Double Decker CBS | G4: Curve | H4: PTL | I4: NEW | J4: NA | K4: NA | L4: Total Width : 2350 mm Working Width : 800 mm Input height (upper) : 5250 mm Input height (lower) : 3250 mm Output height : 750 mm | M4: #VALUE! | N4: 500 | O4: NA | P4: =500*150 -> 75000 | Q4: Weight reducued in comparision to T3525_J1
A5: 3 | B5: Parcel | C5: Max - 600x400x300 Min - 100x50x5 | D5: 10 / 0.05 | E5: Direct bagging chute | F5: Double Decker CBS | G5: L type | H5: Bagging Conveyor | I5: 2833 | J5: Delhivery - Bhiwandi | K5: Tool : 2833 Stn : J24,J9,J3 GR38, R377,R359,R353,R903, R913 Qty : 50 | L5: Total Width : 900 mm Working Width : 800 mm Input chute height : 5500 mm Output chute height : 1360 mm Bag height : 800mm Table height : 560mm | M5: #VALUE! | N5: 395 | O5: NA | P5: =(1704826/50)+(868931/100) -> 42785.83 | Q5: Cost without bridge plate (including bag holder with table) Not recommended to use due to parcel spillage and damage.
A6: 4 | B6: Parcel | C6: Max - 600x400x300 Min - 100x50x5 | D6: 10 / 0.05 | E6: Direct bagging chute | F6: Double Decker CBS | G6: L type | H6: Bagging Conveyor | I6: NEW | J6: NA | K6: NA | L6: Total Width : 2350 mm Working Width : 800 mm Input height (upper) : 5250 mm Input height (lower) : 3250 mm Output height : 750 mm | M6: #VALUE! | N6: MS weight - 400 | O6: NA | P6: 65000 | Q6: More smooth parcel flow with placon roller for easy Bag push.
A7: 5 | B7: Parcel | C7: Max - 500x500x500 Min - 100x50x5 | D7: 10 / 0.05 | E7: Irregular Chute | F7: Double Decker CBS | G7: Ltype - Curve | H7: Irregular Line Conveyor | I7: 3525 | J7: Delhivery - Bangalore | K7: Tool : 3525 Stn : J10, J25 R360, R378 Qty : 14 | L7: Total Width : NA mm Input Width : 300 mm Output width : 800 mm Input height : 3320 mm output height : 630 mm | M7: #VALUE! | N7: 535 | O7: NA | P7: =755318/14 -> 53951.286 | Q7: Irregular chute for 2K Feedline
A8: 6 | B8: Box / Parcel | C8: Max - 1000x600x600 Min - 100x10x5 | D8: 40 / 0.2 | E8: Sorting chute | F8: Single Decker CBS | G8: Straight | I8: 2333 | J8: Aramax, Australia | K8: Tool : 2333 Stn : J5 R355 Qty : 50 | L8: Total Width : 1900 mm Input Width : 1820 mm Input height : 3400 mm output height : 850 mm | M8: #VALUE! | N8: MS weight - 640 | O8: NA | P8: =6371270.2932/50 -> 127425.41 | Q8: cost -without bridge plate - with Aluminium profile and curtains
A9: 7 | B9: Bag/Large Parcel | C9: Max - 1100x1000x600 Min - 180x180x5 | D9: 50 / 0.1 | E9: Sorting chute | F9: Single Decker CBS | G9: Straight | H9: Gravity Roller Collection Conveyor | I9: 3641 | J9: Alstef - Sydney | K9: Tool : 3641 Stn : J5 GR36,R355,R357,R358,R359 & R361 Qty : 12 | L9: Total Width : 2570 mm Working Width : 2200 mm Input height : 4350 mm output height : 850 mm | M9: #VALUE! | N9: 2610.3973 | O9: NA | P9: 335678.5
A10: 8 | B10: Bag/Large Parcel | C10: Max - 1100x1000x600 Min - 180x180x5 | D10: 50 / 0.1 | E10: Irregular Chute | F10: Auto Feedline | G10: Curve | H10: Irregular Line Conveyor | I10: 3641 | J10: Alstef - Sydney | K10: Tool : 3641 Stn : J10 R360 Qty : 3 | L10: Total Width : 1650 mm Working Width : 1570 mm Input height : 4365 mm output height : 1400 mm | M10: #VALUE! | N10: 762.2 | O10: NA | P10: 115740.21
A11: 9 | B11: Parcel | C11: Max - 600x400x300 Min - 100x50x3 | D11: 8 / 0.05 | E11: L type sorting chute | F11: Single Decker CBS | G11: Curve | H11: PTL | I11: 3626 | J11: Flipkart - Jaipur | K11: Tool : 3626 Stn : J1 R351,R352 & R904 Qty : 20 | L11: Total Width : 2075 mm Working Width : 800 mm Input height : 3000 mm output height : 750 mm | M11: #VALUE! | N11: 294.1805 | O11: NA | P11: 42423.325
A12: 10 | B12: Parcel | C12: Max - 600x400x300 Min - 100x50x3 | D12: 8 / 0.05 | E12: L type sorting chute | F12: Single Decker CBS | G12: Curve | H12: PTL | I12: New | J12: NA | K12: NA | L12: Total Width : 2075 mm Working Width : 800 mm Input height : 3000 mm output height : 750 mm | M12: #VALUE! | N12: 220 | O12: NA | P12: =N12*145 -> 31900 | Q12: 25% weight has been reduced in comparison to T3626_J1
A13: 11 | B13: Parcel | C13: Max - 600x400x300 Min - 100x50x3 | D13: 8 / 0.05 | E13: Rejection chute | F13: Single Decker CBS | G13: Straight | H13: Bin | I13: 3626 | J13: Flipkart - Jaipur | K13: Tool : 3626 Stn : J4 R354 Qty : 4 | L13: Total Width : 1110 mm Working Width : 1000 mm Input height : 3000 mm output height : 1285 mm | M13: #VALUE! | N13: 220 | O13: NA | P13: =125602.412/4 -> 31400.603
A14: 12 | B14: Parcel | C14: Max - 600x400x300 Min - 100x50x3 | D14: 8 / 0.05 | E14: Irregular Chute | F14: Mannual | G14: Curve | H14: Irregular Line Conveyor | I14: 3626 | J14: Flipart - Surat | K14: Tool : 3626 Stn : J10 R360 Qty : 12 | L14: Total Width : 1600 mm Working Width : 800 mm Input height : 3050 mm output height : 1000 mm | M14: #VALUE! | N14: 279.873 | O14: NA | P14: 40901.851
A15: 13 | B15: Parcel | C15: Max - 600x400x300 Min - 100x50x3 | D15: 8 / 0.05 | E15: VDS Chute | F15: Arm Based VDS | G15: Taper | H15: Feedline | I15: 3627 | J15: Flipkart - Jaipur | K15: Tool : 3627 Stn : J20 R370 & R902 Qty : 12 | L15: Total Width : 2820 mm Working Width : TAPER Input height : 2600 mm output height : 850 mm | M15: #VALUE! | N15: 318.88741 | O15: NA | P15: 61147.403
A16: 14 | B16: Parcel | C16: Max - 600x400x300 Min - 100x50x3 | D16: 8 / 0.05 | E16: Irregular Chute | F16: Mannual Feedline | G16: Curve | H16: Irregular Line Conveyor | I16: 3627 | J16: Flipart - Jaipur | K16: Tool : 3627 Stn : J10 R360 Qty : 12 | L16: Total Width : 1860 mm Working Width : 700 mm Input height : 2680 mm output height : 800 mm | M16: #VALUE! | N16: 245.21967 | O16: NA | P16: 35456.27
A17: 15 | B17: Parcel | C17: Max - 600x400x300 Min - 100x50x3 | D17: 8 / 0.05 | E17: Irregular Chute | F17: Irregular Line Conveyor | G17: Straight | H17: Irregular Line | I17: 3627 | J17: Flipkart - Jaipur | K17: Tool : 3627 Stn : J41 R901 & R903 Qty : 2 | L17: Total Width : 1090 mm Working Width : 1010 mm Input height : 1300 mm output height : 750 mm | M17: #VALUE! | N17: 157 | O17: NA | P17: =48031/2 -> 24015.5
A18: 16 | B18: Parcel | C18: Max - 915x610x610 Min - 100x75x5 | D18: 20 / 0.05 | E18: L type sorting chute | F18: Linear CBS | G18: Curve | H18: PTL | I18: 3765 | J18: Alstef - Florida | K18: Tool : 3765 Stn : J43 GR12,R903 & R911 Qty : 4 | L18: Total Width : 3410 mm Working Width : 1000 mm Input height : 5150 mm output height : 900 mm | M18: #VALUE! | N18: 782.03475 | O18: NA | P18: 122406.95
A19: 17 | B19: Parcel | C19: Max - 915x610x610 Min - 100x75x5 | D19: 20 / 0.05 | E19: Sorting chute | F19: Linear CBS | G19: Straight | H19: PTL | I19: 3765 | J19: Alstef - Florida | K19: Tool : 3765 Stn : J41 R901 Qty : 15 | L19: Total Width : 1300 mm Input Width : 1200 mm Output width : 1050 mm Input height : 1700 mm output height : 600 mm | M19: #VALUE! | N19: 250 | O19: NA | P19: =531098.4051/15 -> 35406.56
A20: 18 | B20: Parcel | C20: Max - 915x610x610 Min - 100x75x5 | D20: 20 / 0.05 | E20: Sortfail Roller | F20: Linear CBS | G20: Straight | H20: PTL | I20: 3765 | J20: Alstef - Florida | K20: Tool : 3765 Stn : J46 R906 Qty : 1 | L20: Total Width : 1580 mm Input Width : 1540 mm Output width : 1200 mm Input height : 1700 mm output height : 700 mm | M20: #VALUE! | N20: MS weight - 158 | O20: NA | P20: =80932.42645/1 -> 80932.426 | Q20: To be used when inclination angle < 25deg
A21: 19 | B21: Parcel | C21: Max - 915x610x610 Min - 100x75x5 | D21: 20 / 0.05 | E21: Sortfail PVC conveyor with chute | F21: Linear CBS | G21: Straight | H21: PTL | I21: 3765 | J21: Alstef - Florida | K21: Tool : 3765 Stn : J47,48,E1 R907,R908 Qty : 1 | L21: Total Width : NA Input Width : 1000 mm Conveyor Output width : 1200 mm Chute length : 950+1400 mm Conveyor Length : 4.3mtr Height Transfer : 400 mm | M21: #VALUE! | N21: MS weight - 70 & 125 | O21: NA | P21: =246510/1 -> 246510 | Q21: Conveyor along with chute to be used always instead of BIN for Linear CBS
A22: 20 | B22: Parcel / Box | C22: Max - 800x800x600 Min - 300x300x50 | D22: 20 / 2.0 | E22: Sorting chute | F22: SWEDI Sorter | G22: Straight | H22: PTL | I22: 3902 | J22: Flipkart - Sangareddy | K22: Tool : 3902 Stn : J41 GR17,R901,R904,R905,R906 & R907 Qty : 8 | L22: Total Width : 1940 mm Working Width : 1300 mm Input height : 3200 mm output height : 650 mm | M22: #VALUE! | N22: 432.5505 | O22: NA | P22: 72498.76 | Q22: Chute with Hingeable top bed for SWEDI maintenance. Belt used for reducing speed of parcel.
A23: 21 | B23: Parcel / Box | C23: Max - 800x800x600 Min - 300x300x50 | D23: 20 / 2.0 | E23: Rejection chute | F23: SWEDI Sorter | G23: Straight | H23: PTL | I23: 3902 | J23: Flipkart - Sangareddy | K23: Tool : 3902 Stn : J43 GR12,GR 20, R903, R905, R908 Qty : 1 | L23: Total Width : NA Entry Width : 1010 mm Working Width : 1210 mm Input height : 3200 mm output height : 650 mm | M23: #VALUE! | N23: 535 | O23: NA | P23: =N23*150 -> 80250
A24: 22 | B24: Bag/Large Parcel | C24: Max - 1000x850x800 Min - 150x150x50 | D24: 40 / 0.2 | E24: Spiral (One I/P, One O/P) | F24: Double Decker CBS | G24: Spiral | H24: PTL | I24: 2832 | J24: Delhivery - Bhiwandi | K24: Tool : 2832 Stn : J51 R911, R912 & R914 Qty : 27 | L24: Total Width : NA Working Width : 1350 mm Input height : 6500 mm Output height : 3500 mm | M24: #VALUE! | N24: NA | O24: NA | P24: 476468.43
A25: 23 | B25: Bag/Large Parcel | C25: Max - 1000x850x800 Min - 150x150x50 | D25: 40 / 0.2 | E25: Sprial Chute (Two I/P, One O/P) | F25: Single Decker CBS | G25: Spiral | H25: PTL | I25: 3511 | J25: Delhivery - Bangalore | K25: Tool : 3511 Stn : J49 R909,R915 & R916 Qty : 20 | L25: Total Width : NA Working Width : 1350 mm Input height (upper) : 6500 mm Input height (lower) : 4000 mm Output height : 900 mm | M25: #VALUE! | N25: NA | O25: NA | P25: 511042.18
A26: 24 | B26: Bag/Large Parcel | C26: Max - 1000x850x800 Min - 150x150x50 | D26: 40 / 0.2 | E26: Roller chute | F26: Double Decker CBS | G26: Roller conveyor with GI sheet | H26: BIN | I26: 3511 | J26: Delhivery - Bangalore | K26: Tool : 3511 Stn : K61 GR 80, R451,R453 & R454 Qty : 42 | L26: Total Width : 1430mm Working Width : 1350 mm Input height : 900 mm Output height : 700 mm | M26: #VALUE! | N26: NA | O26: NA | P26: =1586025.193956/42 -> 37762.505
A27: 25 | B27: Bag/Large Parcel | C27: Max - 1000x850x800 Min - 150x150x50 | D27: 40 / 0.2 | E27: Dual Infeed Bag Segregation Chute | F27: Double Decker CBS | G27: Spiral | H27: PTL | I27: 3511 | J27: Delhivery - Bangalore | K27: Tool : 3511 Stn : J43 R903 Qty : 5 | L27: Total Width : 3200 mm Input Width : 3050 mm Output width : 1700 mm Input height : 2500 mm Output height : 480 mm | M27: #VALUE! | N27: 502 | O27: NA | P27: =281369/5 -> 56273.8
A28: 26 | B28: Bag/Large Parcel | C28: Max - 1000x850x800 Min - 150x150x50 | D28: 40 / 0.2 | E28: Single Infeed (right) Bag Segregation Chute | F28: Double Decker CBS | G28: Spiral | H28: PTL | I28: 3511 | J28: Delhivery - Bangalore | K28: Tool : 3511 Stn : J41 R901 Qty : 2 | L28: Total Width : 2440 mm Input Width : 2340 mm Output width : 1700 mm Input height : 2500 mm Output height : 480 mm | M28: #VALUE! | N28: 464 | O28: NA | P28: =104414/2 -> 52207
A29: 27 | B29: Bag/Large Parcel | C29: Max - 1000x850x800 Min - 150x150x50 | D29: 40 / 0.2 | E29: Single Infeed (left) Bag Segregation Chute | F29: Double Decker CBS | G29: Spiral | H29: PTL | I29: 3511 | J29: Delhivery - Bangalore | K29: Tool : 3511 Stn : J42 R902 Qty : 1 | L29: Total Width : 2440 mm Input Width : 2340 mm Output width : 1700 mm Input height : 2500 mm Output height : 480 mm | M29: #VALUE! | N29: 464 | O29: NA | P29: =51967.866386/1 -> 51967.866
A30: 28 | B30: Bag/Large Parcel | C30: Max - 1000x850x800 Min - 150x150x50 | D30: 40 / 0.2 | E30: Overdimension reject chute | F30: Double Decker CBS | G30: Straight | H30: BIN | I30: 3511 | J30: Delhivery - Bangalore | K30: Tool : 3511 Stn : J46 (for chute) + K62 (for roller conveyor) R906, R914 + K62_GR80,R452,R453 Qty : (1+5) | L30: Total Width : 1670mm Working Width : 1400 mm Input height : 6515 mm Output height : 500 mm | M30: #VALUE! | N30: MS chute wt - 1010 | O30: NA | P30: =143994+(195232/5) -> 183040.4 | Q30: For upper deck sorter, Chute with roller conveyor
A31: 29 | B31: Bag/Large Parcel | C31: Max - 1000x850x800 Min - 150x150x50 | D31: 40 / 0.2 | E31: Overdimension reject chute | F31: Double Decker CBS | G31: Straight | H31: BIN | I31: NEW | J31: NA | K31: NA | L31: Total Width : 1670mm Working Width : 1400 mm Input height : 4015 mm Output height : 500 mm | M31: #VALUE! | N31: NA | O31: NA | P31: =85000+(195232/5) -> 124046.4 | Q31: For lowerdeck sorter, Chute with roller conveyor
A32: 30 | B32: Parcel | C32: Max - 450x200x350 Min - 100x100x3 | D32: 10 / 0.1 | E32: Direct bagging chute | F32: Single Decker CBS | G32: L Type | H32: Bagging Conveyor | I32: 3245 | J32: BLUEDART, BHIWANDI | K32: Tool : 3245 Stn : J23 (LH) R376 Qty : 98 | L32: Total Width : 1240 mm Working Width : 800 mm Input chute height : 3000 mm Output chute height : 1480 mm Bag height : 800mm Table height : 650mm | M32: #VALUE! | N32: 185 | O32: NA | P32: 24760
A33: 31 | B33: Parcel | C33: Max - 600x400x300 Min - 100x100x0.03 | D33: 50 / 30 (kg/mtr) | E33: VDS Chute (Inclination as per Flipkart) | F33: Arm Based VDS | G33: Straight | H33: PTL | I33: 3796 | J33: Flipkart, Indore | K33: Tool : 3796 Stn : J43 (LH) R902 Qty : 4 | L33: Total Width : 2330 mm Input Width : 1820 mm Output width : 1200 mm Input height : 2500 mm Output height : 650 mm | M33: #VALUE! | N33: 320 | O33: NA | P33: =415250/8 -> 51906.25
A34: 32 | B34: Parcel | C34: Max - 600x400x300 Min - 100x100x0.03 | D34: 50 / 30 (kg/mtr) | E34: Rejection L type (Inclination as per Flipkart) | F34: Arm Based VDS | G34: Straight | H34: PTL | I34: 3796 | J34: Flipkart, Indore | K34: Tool : 3796 Stn : J13 (RH) R902,R907 Qty : 2 | L34: Total Width : 1320 mm Input Width : 1240 mm Output width : 1200 mm Input height : 2500 mm Output height : 650 mm | M34: #VALUE! | N34: 335 | O34: NA | P34: =98104/2 -> 49052
A35: 33 | B35: Parcel | C35: Max - 800x600x600 Min - 200x100x20 | D35: 35 / 0.1 | E35: Low height sorting chute | F35: Single Decker CBS | G35: Straight | H35: Bin | I35: 4132 | J35: Bosta, Egypt | K35: Tool : 4132 Stn : J5 R355 Qty : 10 | L35: Total Width : 1560 mm Input Width : 1460 mm Output width : 1260 mm Input height : 1800 mm Output height : 1000 mm | M35: #VALUE! | N35: 55 | O35: NA | P35: =105874.5/10 -> 10587.45
A36: 34 | B36: Parcel | C36: Max - 800x600x600 Min - 200x100x20 | D36: 35 / 0.1 | E36: Low height bagging chute | F36: Single Decker CBS | G36: Straight | H36: Bin | I36: 4132 | J36: Bosta, Egypt | K36: Tool : 4132 Stn : A22 R53 Qty : 17 | L36: Total Width : 1560 mm Input Width : 1000 mm Output width : 430 mm Input chute height : 1800 mm Output chute height : 1000 mm Bag height : 800mm | M36: #VALUE! | N36: 80 | O36: NA | P36: =247991/17 -> 14587.706 | Q36: Diverter with Bridge plate & Bag holder
A37: 35 | B37: Parcel | C37: Max - 500x500x500 Min - 100x50x5 | D37: 40 / NS | E37: Infeed chute | F37: Linear CBS | G37: Infeed collection chute | H37: Feedline operator | I37: 3953 | J37: DTDC, Banglore | K37: Tool : 3953 Stn : J6 R358 Qty : 2 | L37: Input Width : 950 mm Output width : 1750 mm Input height : 1530 mm Output height : 840 mm | M37: #VALUE! | N37: 175 | O37: NA | P37: =52028.1338/2 -> 26014.067
A38: 36 | B38: Parcel | C38: Max - 600x800x600 Min - 100x100x20 | D38: 20 / 0.05 | E38: PTL chute | F38: Single Decker CBS | H38: PTL | I38: 1631 | J38: Ecom, Bhiwandi | K38: Tool : 1631 Stn : J7 GR72,R213,R294,R75 Qty : 34 | L38: Total Width : 950mm Working Width : 1160 mm Height Transfer : 610 mm Total Length : 1060 mm | M38: #VALUE! | N38: 120 | O38: NA | P38: =609674/34 -> 17931.588
A39: 37 | B39: Bag | C39: Max - 600x800x600 Min - 100x100x20 | D39: 20 / 0.05 | E39: Half spiral FRP chute + straight metallic slide | F39: Single Decker CBS | G39: Spiral + Straight | H39: Bin | I39: 1634 | J39: Ecom, Bilaspur | K39: Tool : 1634 Stn : J22 GR53,GR49,R5 Qty : 22 | L39: Total Width : 1470mm Working Width : 1380 mm Height Transfer : 2100 mm Total Length : NA | M39: #VALUE! | N39: FRP - Fixed cost MS chute weight = 350kg | O39: NA | P39: =15000+(350*150) -> 67500
A44: PREPARED BY | H44: REVIEWED BY | L44: APPROVED BY
A45: NAME | F45: SIGN | H45: NAME | K45: SIGN | L45: NAME | P45: SIGN
A46: Ritik Sharma | H46: Peeyush Yadav | L46: Sabyasachi Mallick
A48: Note:- This is falcon Autotech confidential document

Sheet PTL
A1: S.No | B1: Description | C1: Qty | D1: UOM | E1: Unit Price | F1: Total Price | K1: Total Put Station | L1: ='[9]Budgetary Costing'!$C$4 -> 2 | O1: Total Pick Stattion | P1: ='[9]Budgetary Costing'!$C$3 -> 4
A2: 1 | B2: PTL Racks Bagging | D2: Numbers | E2: =+'Quote Master'!$I$67 -> 2040 | F2: =+E2*C2 -> 0 | K2: Bin Rack/ Put Station | L2: 0 | O2: Pigeon Rack/Pick Station | P2: 0
A3: 2 | B3: PTL Racks Bin Type | D3: Numbers | E3: =+'Quote Master'!I68 -> 2520 | F3: =+E3*C3 -> 0 | K3: PTL Light/Bin Rack | L3: 0 | O3: PTL Light/Pigeon Rack | P3: 0
A4: 3 | B4: PTL Racks Push Back | D4: Numbers | E4: =+'Quote Master'!I69 -> 4080 | F4: =+E4*C4 -> 0 | K4: PTL Control Box/Station | L4: 0 | M4: 24/card | O4: PTL Control Box/Station | P4: 0 | Q4: 24/card
A5: 3 | B5: PTL Frame | D5: Numbers | E5: =+'Quote Master'!$I$67 -> 2040 | F5: =+E5*C5 -> 0 | K5: Extra control Card/Station | L5: 0 | M5: 24/card | O5: Extra control Card/Station | Q5: 24/card
A6: 4 | B6: PTL Modules | C6: =L6 -> 0 | D6: Numbers | E6: =+'Quote Master'!I64 -> 6500 | F6: =+E6*C6 -> 0 | K6: Total PTL lights | L6: =L3*L2*L1 -> 0 | O6: Total PTL lights | P6: =P3*P2*P1 -> 0
A7: 5 | B7: PTL Control Box | C7: =L7 -> 0 | D7: Numbers | E7: =+'Quote Master'!I65 -> 30000 | F7: =+E7*C7 -> 0 | K7: Total Control Box | L7: =L4*L1 -> 0 | O7: Total Control Box | P7: =P4*P1 -> 0
A8: 6 | B8: Extra control Card | C8: =L8 -> 0 | D8: Numbers | E8: =+'Quote Master'!I66 -> 10000 | F8: =+E8*C8 -> 0 | K8: Total Extra Control Card | L8: =L5*L1 -> 0 | O8: Total Extra Control Card | P8: =P5*P1 -> 0
A9: 7 | B9: PTL hand barcode scanner 1D | C9: =L1 -> 2 | D9: Numbers | E9: =+'Quote Master'!$I$72 -> 30000 | F9: =+E9*C9 -> 60000
A10: 8 | B10: PTL hand barcode scanner 2D | D10: Numbers | E10: ='Quote Master'!$I$73 -> 0 | F10: =+E10*C10 -> 0
A11: 9 | B11: Field wiring and controls | E11: =+C6*1000 -> 0 | F11: =+E11 -> 0
E12: Total | F12: =+SUM(F2:F11) -> 60000

Sheet Steelworks
A1: S.No | B1: Description | C1: Qty | D1: Area | E1: UOM | F1: Unit Price | G1: Total Price
A2: 1 | B2: Archetype-D | C2: 2 | D2: =198.76 -> 198.76 | E2: sqm | F2: 80000 | G2: =+F2*C2*D2 -> 31801600 | H2: Operator Mezzanine | I2: =D2*C2 -> 397.52
A3: 2 | B3: Archetype-A | C3: 2 | D3: =118.4 -> 118.4 | E3: sqm | F3: 80000 | G3: =+F3*C3*D3 -> 18944000 | H3: VDS Mezzanine | I3: =D3*C3 -> 236.8
A4: 3 | B4: Archetype-C | C4: 2 | D4: =(12+8.33+4.5) -> 24.83 | E4: sqm | F4: 80000 | G4: =+F4*C4*D4 -> 3972800 | H4: Stairs & Scanning Tunnel Mezzanine | I4: =D4*C4 -> 49.66
A5: 4 | B5: Archetype-C | C5: 1 | D5: 0 | F5: 80000 | G5: =+F5*C5*D5 -> 0
A6: 5 | B6: Stairs ( upto 1.2m) | C6: 2 | E6: Numbers | F6: =+'Quote Master'!I77 -> 50000 | G6: =+F6*C6 -> 100000
A7: 6 | B7: Stairs ( 1.3m-2.5m) | C7: 18 | E7: Numbers | F7: =+'Quote Master'!I78*3 -> 225000 | G7: =F7*C7 -> 4050000
A8: 7 | B8: Stairs (>2.5m) | C8: 2 | E8: Numbers | F8: =+'Quote Master'!I79 -> 100000 | G8: =+F8*C8 -> 200000
A9: 8 | B9: Monkey Ladder | C9: 2 | E9: Numbers | F9: =+'Quote Master'!I75 -> 33600 | G9: =+F9*C9 -> 67200 | I9: =2.7*3600/1.175 -> 8272.3404 | J9: =I9*2 -> 16544.681
F10: Total | G10: =+SUM(G2:G9) -> 59135600 | H10: =G10/'Overall Costing'!M5 -> 629102.13
J11: =J9*1.33*85% -> 18703.762
H13: =20000*750 -> 15000000

Sheet Software Packages
A1: S.No. | B1: Description | C1: Quantity | D1: UOM | E1: Unit Price | F1: Total
A2: 1 | B2: Control and Software Package | C2: 1 | D2: Nos | E2: 300000 | F2: =E2*C2 -> 300000
A3: 2 | B3: IT Integration | C3: 1 | D3: Nos | E3: 300000 | F3: =E3*C3 -> 300000
A4: 3 | B4: SCADA | C4: 1 | D4: Nos | E4: 500000 | F4: =E4*C4 -> 500000 | G4: Need to add Tablet Price of 3 Lakh | H4: =(2+1)/0.6*2 -> 10
A5: 4 | B5: Translation Charge | C5: 1 | D5: Nos | E5: 300000 | F5: =E5*C5 -> 300000
A6: 5 | B6: Tool Kit | C6: 1 | D6: Nos | E6: 100000 | F6: =E6*C6 -> 100000
E7: Total | F7: =SUM(F2:F6) -> 1500000

Sheet Quote Master
J1: ='Overall Costing'!$M$1 -> 0.675
A2: S.No. | B2: Category | C2: Description | D2: Item Code | E2: UOM | F2: Costing Type | G2: Width | H2: Cost | I2: Unit Price | J2: Sales Factor Requirement | K2: Re | L2: Unit Price | P2: Updated Prices
A3: 1 | B3: PVC | C3: Launch Pad | E3: Meter | F3: Fixed Cost | J3: Yes
A4: 2 | C4: Straight PVC Conveyor (610mm) | E4: Meter | F4: Fixed Cost | G4: 610 | H4: 12500 | I4: =H4/$J$1 -> 18518.519 | J4: Already applied
A5: 3 | C5: PVC Drive Station cost (610mm) | E5: Meter | F5: Fixed Cost | G5: 610 | H5: 122000 | I5: =H5/$J$1 -> 180740.74 | J5: Already applied
A6: 4 | C6: Straight PVC Conveyor (810mm) | E6: Meter | F6: Fixed Cost | G6: 810 | I6: =H6/$J$1 -> 0 | J6: Already applied
A7: 5 | C7: PVC Drive Station cost (810mm) | E7: Meter | F7: Fixed Cost | G7: 810 | I7: =H7/$J$1 -> 0 | J7: Already applied
A8: 6 | C8: Straight PVC Conveyor (1010mm) | E8: Meter | F8: Fixed Cost | G8: 1010 | I8: =H8/$J$1 -> 0 | J8: Already applied
A9: 7 | C9: PVC Drive Station cost (1010mm) | E9: Meter | F9: Fixed Cost | G9: 1010 | I9: =H9/$J$1 -> 0 | J9: Already applied
A10: 8 | C10: Straight PVC Conveyor (1210mm) | E10: Meter | F10: Fixed Cost | G10: 1210 | H10: 18000 | I10: =H10/$J$1 -> 26666.667 | J10: Already applied
A11: 9 | C11: PVC Drive Station cost (1210mm) | E11: Meter | F11: Fixed Cost | G11: 1210 | H11: 135000 | I11: =H11/$J$1 -> 200000 | J11: Already applied
A12: 10 | B12: Modular Conveyors | C12: 90° Turn BW1200 | E12: Number | F12: Fixed Cost | G12: 1200 | I12: 825000 | J12: No | L12: 825000
A13: 11 | C13: 90° Turn BW1000 | E13: Number | F13: Fixed Cost | G13: 1000 | I13: 760000 | L13: 760000
A14: 12 | C14: 60° Turn | E14: Number | F14: Fixed Cost | I14: 760000 | L14: 760000
A15: 13 | C15: 45° Turn | E15: Number | F15: Fixed Cost | I15: 760000 | L15: 760000
A16: 14 | C16: 30° Turn | E16: Number | F16: Fixed Cost | I16: 760000 | L16: 760000
A17: 15 | C17: Weighing Conveyor (Not Legal for Trade) | F17: Fixed Cost | I17: 900000 | J17: No | L17: 900000
A18: 16 | C18: Weighing Conveyor ( Legal for Trade) | F18: Fixed Cost | I18: 1800000 | L18: 1800000
A19: 17 | C19: Spacing Conveyor BW1000 | F19: Fixed Cost | G19: 1000 | I19: 250000 | J19: No | L19: 250000
A20: 18 | C20: Spacing Conveyor BW800 | F20: Fixed Cost | G20: 800 | I20: 225000 | J20: No | L20: 225000
A21: 19 | C21: Scanning ConveyorBW1000 | F21: Fixed Cost | G21: 1000 | I21: 250000 | L21: 250000
A22: 20 | C22: Scanning ConveyorBW800 | F22: Fixed Cost | G22: 800 | I22: 225000 | L22: 225000
A23: 21 | B23: Roller Conveyor | C23: Straight Roller Conveyor (600mm) | E23: Meter | F23: Fixed Cost | G23: 600 | H23: 31350 | I23: =H23/$J$1 -> 46444.444 | J23: No | K23: 20 | L23: =15000 -> 15000
A24: 22 | C24: Straight Roller Conveyor (800mm) | E24: Meter | F24: Fixed Cost | G24: 800 | H24: 42660 | I24: =H24/$J$1 -> 63200 | J24: No | K24: 20 | L24: =15000 -> 15000
A25: 23 | C25: Straight Roller Conveyor (1000mm) | E25: Meter | F25: Fixed Cost | G25: 1000 | H25: 53970 | I25: =H25/$J$1 -> 79955.556 | J25: No | K25: 20 | L25: =15000 -> 15000
A26: 24 | C26: Straight Roller Conveyor (1200mm) | E26: Meter | F26: Fixed Cost | G26: 1200 | H26: 65280 | I26: =H26/$J$1 -> 96711.111 | J26: No | K26: 20 | L26: =15000 -> 15000
A27: 25 | C27: Straight Roller Conveyor (Accumulation) (600mm) | E27: Meter | F27: Fixed Cost | G27: 600 | H27: 33350 | I27: =H27/$J$1 -> 49407.407 | J27: No | K27: 20 | L27: 15000
A28: 26 | C28: Straight Roller Conveyor (Accumulation) (800mm) | E28: Meter | F28: Fixed Cost | G28: 800 | H28: =H24+($H$27-$H$23) -> 44660 | I28: =H28/$J$1 -> 66162.963 | J28: No | K28: 20 | L28: 15000
A29: 27 | C29: Straight Roller Conveyor (Accumulation) (1000mm) | E29: Meter | F29: Fixed Cost | G29: 1000 | H29: =H25+($H$27-$H$23) -> 55970 | I29: =H29/$J$1 -> 82918.519 | J29: No | K29: 20 | L29: 15000
A30: 28 | C30: Straight Roller Conveyor (Accumulation) (1200mm) | E30: Meter | F30: Fixed Cost | G30: 1200 | H30: =H26+($H$27-$H$23) -> 67280 | I30: =H30/$J$1 -> 99674.074 | J30: No | K30: 20 | L30: 15000
A31: 29 | C31: Gravity Roller | E31: Meter | F31: Fixed Cost | I31: =+L31*(1+K31/100) -> 18000 | J31: No | K31: 20 | L31: 15000
A32: 30 | C32: Y Merge roller | E32: Number | F32: Fixed Cost | I32: =+L32*(1+K32/100) -> 360000 | J32: No | K32: 20 | L32: 300000
A33: 31 | C33: Roller Merge/Divert | E33: Number | F33: Fixed Cost | I33: =+L33*(1+K33/100) -> 198000 | J33: No | K33: 20 | L33: 165000
A34: 32 | C34: 90° Turn Roller | E34: Number | F34: Fixed Cost | I34: =+L34*(1+K34/100) -> 198000 | J34: No | K34: 20 | L34: 165000
A35: 33 | C35: 60° Turn Roller | E35: Number | F35: Fixed Cost | I35: =+L35*(1+K35/100) -> 198000 | J35: No | K35: 20 | L35: 165000
A36: 34 | C36: 45° Turn Roller | E36: Number | F36: Fixed Cost | I36: =+L36*(1+K36/100) -> 198000 | J36: No | K36: 20 | L36: 165000
A37: 35 | C37: 30° Turn Roller | E37: Number | F37: Fixed Cost | I37: =+L37*(1+K37/100) -> 198000 | J37: No | K37: 20 | L37: 165000
A38: 36 | B38: Modular & Teliscopic Conveyor | C38: Straight Modular Belt Conveyor | E38: Meter | F38: Fixed Cost | I38: =+L38*(1+K38/100) -> 65166.667 | J38: No | K38: 15 | L38: =34000/0.6 -> 56666.667
A39: 37 | C39: Modular Belt Drive section (upto 10m) | E39: Meter | F39: Fixed Cost | I39: =+L39*(1+K39/100) -> 233833.33 | J39: No | K39: 15 | L39: =122000/0.6 -> 203333.33
A40: 38 | C40: Modular Belt Drive section (10 to 15m) | E40: Meter | F40: Fixed Cost | I40: =+L40*(1+K40/100) -> 243416.67 | J40: No | K40: 15 | L40: =127000/0.6 -> 211666.67
A41: 39 | C41: Modular Belt Drive section (15 to 20m) | E41: Meter | F41: Fixed Cost | I41: =+L41*(1+K41/100) -> 253000 | J41: No | K41: 15 | L41: =132000/0.6 -> 220000
A42: 40 | C42: Modular Belt Drive section (20 to 25m) | E42: Meter | F42: Fixed Cost | I42: =+L42*(1+K42/100) -> 256833.33 | J42: No | K42: 15 | L42: =134000/0.6 -> 223333.33
A43: 41 | C43: Telescopic Conveyor(4/12) | E43: Number | F43: Fixed Cost | I43: =+L43*(1+K43/100) -> 1650000 | J43: No | L43: 1650000
A44: 42 | C44: Telescopic Conveyor(6/18) | E44: Number | F44: Fixed Cost | I44: =+L44*(1+K44/100) -> 1900000 | J44: No | L44: 1900000
A45: 43 | C45: ARB Frame | E45: Meter | I45: =+L45*(1+K45/100) -> 134400 | J45: No | K45: 12 | L45: 120000
A46: 44 | C46: ARB Drive Section | E46: Number | F46: Fixed Cost | I46: =+L46*(1+K46/100) -> 132000 | J46: No | K46: 10 | L46: 120000
A47: 45 | C47: ARB divert Point | E47: Number | F47: Fixed Cost | I47: =+L47*(1+K47/100) -> 400000 | J47: No | L47: 400000
A48: 46 | C48: Pop up unit | E48: Number | F48: Fixed Cost | I48: =+L48*(1+K48/100) -> 600000 | J48: No | K48: 20 | L48: 500000
A49: 47 | C49: Swivel Wheel Unit | E49: Number | F49: Special cost sheet | I49: =+L49*(1+K49/100) -> 0 | K49: 10
A50: 48 | C50: Pusher Unit (Electric) | I50: =+L50*(1+K50/100) -> 210000 | J50: No | K50: 20 | L50: 175000
A51: 49 | C51: Side Barcode Scanner | I51: =+L51*(1+K51/100) -> 550000 | J51: No | K51: 10 | L51: 500000
A52: 50 | C52: Centring Sensors | I52: =+L52*(1+K52/100) -> 100000 | J52: No | L52: 100000
A53: 51 | C53: Positioning Sensors | I53: =+L53*(1+K53/100) -> 100000 | J53: No | L53: 100000
A54: 52 | C54: Standard Arm | I54: =+L54*(1+K54/100) -> 140000 | J54: No | L54: 140000
A55: 53 | C55: Arm XL | I55: =+L55*(1+K55/100) -> 175000 | J55: No | L55: 175000
A56: 54 | C56: Chutes | E56: Sq Meter | I56: =+L56*(1+K56/100) -> 11760 | J56: No | K56: 12 | L56: 10500
A57: 55 | C57: Chute Full Sensor | I57: =+L57*(1+K57/100) -> 5600 | J57: No | K57: 12 | L57: 5000
A58: 56 | C58: Display Indicator on Chute(PTL) | I58: =+L58*(1+K58/100) -> 6500 | J58: No | L58: 6500
A59: 57 | C59: Bag Holding Assembly | I59: =+L59*(1+K59/100) -> 12880 | J59: No | K59: 12 | L59: 11500
A60: 58 | C60: Spring Loaded Fixed Bin | I60: =+L60*(1+K60/100) -> 50400 | J60: No | K60: 12 | L60: 45000
A61: 59 | C61: Spring Loaded Portatble Bin | I61: =+L61*(1+K61/100) -> 56000 | J61: No | K61: 12 | L61: 50000
A62: 60 | C62: Simple Fixed Bin | I62: =+L62*(1+K62/100) -> 13440 | J62: No | K62: 12 | L62: 12000
A63: 61 | C63: Simple Portable Bin | I63: =+L63*(1+K63/100) -> 16800 | J63: No | K63: 12 | L63: 15000
A64: 62 | C64: PTL Module | I64: =+L64*(1+K64/100) -> 6500 | J64: No | L64: 6500
A65: 63 | C65: PTL Control Box | I65: =+L65*(1+K65/100) -> 30000 | J65: No | L65: 30000
A66: 64 | C66: Extra Control Card | I66: =+L66*(1+K66/100) -> 10000 | L66: 10000
A67: 65 | C67: PTL Rack Bagging | I67: =+L67*(1+K67/100) -> 2040 | K67: 20 | L67: 1700
A68: 66 | C68: PTL Rack Bin/ Pigeon Hole | I68: =+L68*(1+K68/100) -> 2520 | K68: 20 | L68: 2100
A69: 67 | C69: PTL Rack Push Back type | I69: =+L69*(1+K69/100) -> 4080 | K69: 20 | L69: 3400
A70: 68 | C70: PTL Ducts | I70: =+L70*(1+K70/100) -> 1500 | L70: 1500
A71: 69 | C71: Manual Label Printer | I71: =+L71*(1+K71/100) -> 30000 | J71: No | L71: 30000
A72: 70 | C72: Wireless Barcode Scanner(1D) | I72: =+L72*(1+K72/100) -> 30000 | J72: No | L72: 30000
A73: 71 | C73: Wireless Barcode Scanner(2D) | I73: =+L73*(1+K73/100) -> 0 | J73: No
A74: 72 | C74: Server PC (Standard) | I74: =+L74*(1+K74/100) -> 250000 | J74: No | L74: 250000
A75: 73 | C75: Monkey Ladders | I75: =+L75*(1+K75/100) -> 33600 | K75: 12 | L75: 30000
A76: 74 | C76: Platform for operators (mezz) | E76: Sq Meter | I76: =+L76*(1+K76/100) -> 13000 | J76: No | L76: 13000
A77: 75 | C77: Stairs 1.2m | I77: =+L77*(1+K77/100) -> 50000 | J77: No | L77: 50000
A78: 76 | C78: Stairs 1.3- 2.5m | I78: =+L78*(1+K78/100) -> 75000 | J78: No | L78: 75000
A79: 77 | C79: Stairs (>2.5m) | I79: =+L79*(1+K79/100) -> 100000 | J79: No | L79: 100000
A80: 78 | C80: Hooters | I80: =+L80*(1+K80/100) -> 0
A81: 79 | C81: Pull Cords | I81: =+L81*(1+K81/100) -> 0
A82: 80 | C82: Lotto switch | I82: =+L82*(1+K82/100) -> 0
A83: 81 | C83: Harmonic Filter | I83: =+L83*(1+K83/100) -> 0
A84: 82 | C84: Surge Suppressor | I84: =+L84*(1+K84/100) -> 0
A85: 83 | C85: Tower lamps (2 colour) | I85: =+L85*(1+K85/100) -> 6000 | L85: 6000
A86: 84 | C86: Tower lamps (3 colour) | I86: =+L86*(1+K86/100) -> 7500 | L86: 7500
A87: 85 | C87: Tower lamps (4 colour) | I87: =+L87*(1+K87/100) -> 9000 | L87: 9000
A88: 86 | C88: I/o Card for chutefull sensor | I88: =+L88*(1+K88/100) -> 34000 | L88: 34000
A89: 87 | C89: Emergency Stops | I89: =+L89*(1+K89/100) -> 6000 | L89: 6000
A90: 88 | C90: Fencing | H90: =#REF! -> #REF! | I90: =H90/$J$1 -> #REF!
A91: 89 | C91: Netting | I91: =+L91*(1+K91/100) -> 0
A92: 90 | C92: Cabling Switches Router | I92: =+L92*(1+K92/100) -> #VALUE! | L92: 25% of conveyor cost
A93: 91 | C93: Control IT Software | I93: =+L93*(1+K93/100) -> 300000 | L93: 300000
A94: 92 | C94: Custom IT Integration | I94: =+L94*(1+K94/100) -> 300000 | L94: 300000
A95: 93 | C95: Arm for VDS or Bag Sorter | F95: Fixed | I95: =+L95*(1+K95/100) -> 0
A96: 94 | C96: Push Button | E96: Number | F96: Fixed Cost | I96: =+L96*(1+K96/100) -> 5000 | L96: 5000
A97: 95 | C97: DLIC Software | I97: =+L97*(1+K97/100) -> 300000 | L97: 300000
A98: 96 | C98: DLIC license | I98: =+L98*(1+K98/100) -> 300000 | L98: 300000
A99: 97 | C99: Pre Sort Scan Tunnel Stand alone(Excluding Hand held scanner and control system) | I99: =+L99*(1+K99/100) -> 450000 | L99: 450000
A100: 98 | C100: Aligning Conveyor (Falcon) | I100: =+L100*(1+K100/100) -> 250000 | L100: 250000
...

Sheet Weighing Conveyors
A1: S.No. | B1: Make | C1: Model | D1: Name | E1: Weighing Range | F1: Least Count | G1: Max Speed | H1: Accuracy | I1: Min Parcel Size(mm) | J1: Max Parcel Size(mm) | K1: Cost Price | L1: Selling Price
A2: 1 | B2: Mettler Toledo | C2: CK 30 | D2: Mettler Toledo CK 30 | E2: 200g-40Kg | F2: 10g | G2: 65m/min | H2: +/- 10g | I2: 160x50x25 | J2: 820x800x600 | K2: 550000 | L2: =+K2/0.6 -> 916666.67
A3: 2 | B3: Mettler Toledo | C3: TLW 155(60) | D3: Mettler Toledo TLW 155(60) | E3: 200g-50Kg | F3: 20g | G3: 120m/min | H3: +/- 20g | I3: BW 1000 | J3: BW 1200 | K3: 900000 | L3: =+K3/0.6 -> 1500000 | M3: LFT
A4: 3 | B4: Bizerba | C4: WM CWL | D4: Bizerba WM CWL | E4: 100g - 40Kg | F4: 10g | G4: 80m/min | H4: +/- 50g | I4: 160x50x25 | J4: 820x800x600 | K4: 500000 | L4: =+K4/0.6 -> 833333.33
A5: 4 | C5: Austrlia Weighing | D5: Austrlia Weighing | K5: 1400000 | L5: =+K5/0.6 -> 2333333.3
A6: 5 | B6: Mettler Toledo | C6: TLW 250(80) | D6: Mettler Toledo TLW 250(80) | E6: 0-80kg | F6: 20g | G6: 90m/min | H6: +/- 20g | I6: BW 500 | J6: BW 1100
A7: 6 | B7: Mettler Toledo | C7: TLW 450(80) | D7: Mettler Toledo TLW 450(80) | E7: 0-80kg | F7: 10g | G7: 180m/min | H7: +/- 10g | I7: BW 500 | J7: BW 1100
A8: 7 | B8: Mettler Toledo | C8: TLW 155(30) | D8: Mettler Toledo TLW 155(30) | E8: 0-30Kg | F8: 10g | G8: 90m/min | H8: +/- 10g | I8: BW 600 | J8: BW 800

Sheet Mezzanien Description
A1: Archetype | B1: Mezzanine Description | C1: Reference Tool | D1: Cost (INR/sq. mtr)
A2: Archetype-A | B2: Rectangular Plain vanilla mezzanine | C2: T-3245 (Blue Dart Bhiwandi) | D2: Rs 9,500/sq. mtr
B3: Around 2000 to 4000 sq. ft area
B4: No special load requirements except placing falcon feedline or conveyors.
B5: No special height – height of around 3-4 meters
B6: No excess cut outs.
B7: No specific column grid size requirement from customer
A8: Archetype-A.1 | B8: Rectangular Plain vanila mezzanine | C8: T-2832 (Delhivery Bhiwandi) | D8: Rs 12,500/sq. mtr
B9: Around 2000 to 4000 sq. ft area
B10: No special load requirements except placing falcon feedline or conveyors.
B11: Height requirement of 6-7 meters
B12: No excess cut outs.
B13: No specific column grid size requirement from customer
A14: Archetype-B | B14: Base mezzanine for sorter | C14: T-2833 (Delhivery Bhiwandi) | D14: Rs 12,000/sq. mtr
B15: High strength requirement for higher load carrying capacity.
B16: Large grid size requirement (5 m or 6 m – column space) as in this case, customers need bottom area for operations
A17: Archetype-C | B17: Small maintenance platform | C17: T-3627 (Flipkart Jaipur) | D17: Rs 30,000/sq. mtr
B18: Typical size lesser than 150/200 sq. ft
A19: Archetype-D | B19: Odd sized mezzanines which may have | C19: T-3626+T-3629 (Flipkart Surat) | D19: Rs 18750/sq. mtr
B20: Odd shape mezzanines – nonrectangular
B21: Has multiple cut outs – cut out area more than 10 or 15% of the overall mezzanine area
B22: Has cantilever type platforms which require special supports.
B23: Length/Breadth ratio of the mezzanine is higher than 6 or 7

Sheet Chute Costing 
C1: Standard Chute | G1: Narrow
C2: Puru Quoted price for 1.4 m pitch chute | D2: 2450 | G2: Puru Quoted price for 1.4 m pitch chute | H2: 2450
C3: Price for 1.6 m pitch chute | D3: =D2*1.2 -> 2940 | G3: Price for 1 narrow chute | H3: =H2*0.8 -> 1960
C4: Sales Price | D4: =D3/0.8 -> 3675 | E4: =D4*'Overall Costing'!M5 -> 345450 | G4: Sales Price | H4: =H3/0.8 -> 2450 | I4: =H4*'Overall Costing'!M5 -> 230300
